Workbook
Name DATA: 'F&B'!$1:$1048606
Name ExternalData_1: 'Live Rate'!$A$1:$C$398

Sheet Cover D
A1: DEKWANEH | E1: =#REF! -> #REF! | F1: Cost > 40%
A2: =E1 -> #REF!
A3: ='Live Rate'!D2 -> 89,700 | B3: SP USD | C3: SP LBP | E3: Cost Price | F3: Cost % | G3: Net Profit | H3: Current Price | I3: Cost Price | J3: Profit | K3: Cost %
A4: Starters | H4: 0.1
A5: French Fries | B5: 6 | C5: =B5*90000 -> 540000 | D5: =E5/$A$2 -> #REF! | E5: =STARTERS!$C$10 -> #REF! | F5: =IF(E5="","",IF(ISBLANK(C5),"",E5/C5)) -> #REF! | G5: =C5-E5 -> #REF! | H5: =(C5*$H$4)+C5 -> 594000 | I5: =E5 -> #REF! | J5: =H5-I5 -> #REF! | K5: =I5/H5 -> #REF!
A6: Wedges | B6: 6.5 | C6: =B6*90000 -> 585000 | D6: =E6/$A$2 -> #REF! | E6: =STARTERS!$L$10 -> #REF! | F6: =IF(E6="","",IF(ISBLANK(C6),"",E6/C6)) -> #REF! | G6: =C6-E6 -> #REF! | H6: =(C6*$H$4)+C6 -> 643500 | I6: =E6 -> #REF! | J6: =H6-I6 -> #REF! | K6: =I6/H6 -> #REF!
A7: Baked Potato | B7: 5 | C7: =B7*90000 -> 450000 | D7: =E7/$A$2 -> #REF! | E7: =STARTERS!$C$54 -> #REF! | F7: =IF(E7="","",IF(ISBLANK(C7),"",E7/C7)) -> #REF! | G7: =C7-E7 -> #REF! | H7: =(C7*$H$4)+C7 -> 495000 | I7: =E7 -> #REF! | J7: =H7-I7 -> #REF! | K7: =I7/H7 -> #REF!
A8: Onion Rings | C8: =B8*90000 -> 0 | D8: =E8/$A$2 -> #REF! | E8: =STARTERS!$C$237 -> #REF! | F8: =IF(E8="","",IF(ISBLANK(C8),"",E8/C8)) -> #REF! | G8: =C8-E8 -> #REF! | H8: =(C8*$H$4)+C8 -> 0 | I8: =E8 -> #REF! | J8: =H8-I8 -> #REF! | K8: =I8/H8 -> #REF!
A9: Cheese Garlic | B9: 6 | C9: =B9*90000 -> 540000 | D9: =E9/$A$2 -> #REF! | E9: =STARTERS!$L$54 -> #REF! | F9: =IF(E9="","",IF(ISBLANK(C9),"",E9/C9)) -> #REF! | G9: =C9-E9 -> #REF! | H9: =(C9*$H$4)+C9 -> 594000 | I9: =E9 -> #REF! | J9: =H9-I9 -> #REF! | K9: =I9/H9 -> #REF!
A10: Classic Nachos | C10: =B10*90000 -> 0 | D10: =E10/$A$2 -> #REF! | E10: =STARTERS!$C$191 -> #REF! | F10: =IF(E10="","",IF(ISBLANK(C10),"",E10/C10)) -> #REF! | G10: =C10-E10 -> #REF! | H10: =(C10*$H$4)+C10 -> 0 | I10: =E10 -> #REF! | J10: =H10-I10 -> #REF! | K10: =I10/H10 -> #REF!
A11: Cheese Nachos | B11: 10 | C11: =B11*90000 -> 900000 | D11: =E11/$A$2 -> #REF! | E11: =STARTERS!$C$99 -> #REF! | F11: =IF(E11="","",IF(ISBLANK(C11),"",E11/C11)) -> #REF! | G11: =C11-E11 -> #REF! | H11: =(C11*$H$4)+C11 -> 990000 | I11: =E11 -> #REF! | J11: =H11-I11 -> #REF! | K11: =I11/H11 -> #REF!
A12: Chicken Wings | B12: 7.5 | C12: =B12*90000 -> 675000 | D12: =E12/$A$2 -> #REF! | E12: =STARTERS!$L$99 -> #REF! | F12: =IF(E12="","",IF(ISBLANK(C12),"",E12/C12)) -> #REF! | G12: =C12-E12 -> #REF! | H12: =(C12*$H$4)+C12 -> 742500 | I12: =E12 -> #REF! | J12: =H12-I12 -> #REF! | K12: =I12/H12 -> #REF!
A13: Chicken Nuggets | B13: 5 | C13: =B13*90000 -> 450000 | D13: =E13/$A$2 -> #REF! | E13: =STARTERS!$L$191 -> #REF! | F13: =IF(E13="","",IF(ISBLANK(C13),"",E13/C13)) -> #REF! | G13: =C13-E13 -> #REF! | H13: =(C13*$H$4)+C13 -> 495000 | I13: =E13 -> #REF! | J13: =H13-I13 -> #REF! | K13: =I13/H13 -> #REF!
A14: Pro's Combo | C14: =B14*90000 -> 0 | D14: =E14/$A$2 -> #REF! | E14: =STARTERS!$L$237 -> #REF! | F14: =IF(E14="","",IF(ISBLANK(C14),"",E14/C14)) -> #REF! | G14: =C14-E14 -> #REF! | H14: =(C14*$H$4)+C14 -> 0 | I14: =E14 -> #REF! | J14: =H14-I14 -> #REF! | K14: =I14/H14 -> #REF!
A15: Breaded Mozzarella | B15: 7.5 | C15: =B15*90000 -> 675000 | D15: =E15/$A$2 -> #REF! | E15: =STARTERS!$L$144 -> #REF! | F15: =IF(E15="","",IF(ISBLANK(C15),"",E15/C15)) -> #REF! | G15: =C15-E15 -> #REF! | H15: =(C15*$H$4)+C15 -> 742500 | I15: =E15 -> #REF! | J15: =H15-I15 -> #REF! | K15: =I15/H15 -> #REF!
A16: Quesadillas Chicken | B16: 7 | C16: =B16*90000 -> 630000 | D16: =E16/$A$2 -> #REF! | E16: =STARTERS!C284 -> #REF! | F16: =IF(E16="","",IF(ISBLANK(C16),"",E16/C16)) -> #REF! | G16: =C16-E16 -> #REF! | H16: =(C16*$H$4)+C16 -> 693000 | I16: =E16 -> #REF! | J16: =H16-I16 -> #REF! | K16: =I16/H16 -> #REF!
A17: Chicken Tenders | B17: 9 | C17: =B17*90000 -> 810000 | D17: =E17/$A$2 -> #REF! | E17: =STARTERS!C144 -> #REF! | F17: =IF(E17="","",IF(ISBLANK(C17),"",E17/C17)) -> #REF! | G17: =C17-E17 -> #REF! | H17: =(C17*$H$4)+C17 -> 891000 | I17: =E17 -> #REF! | J17: =H17-I17 -> #REF! | K17: =I17/H17 -> #REF!
A18: Salmon Delight | C18: =B18*90000 -> 0 | D18: =E18/$A$2 -> #REF! | E18: =STARTERS!L599 -> #REF! | F18: =IF(E18="","",IF(ISBLANK(C18),"",E18/C18)) -> #REF! | G18: =C18-E18 -> #REF! | H18: =(C18*$H$4)+C18 -> 0 | I18: =E18 -> #REF! | J18: =H18-I18 -> #REF! | K18: =I18/H18 -> #REF!
A19: =STARTERS!L640 -> Truffle Puttin | C19: =B19*90000 -> 0 | D19: =E19/$A$2 -> #REF! | E19: =STARTERS!L644 -> #REF! | F19: =IF(E19="","",IF(ISBLANK(C19),"",E19/C19)) -> #REF! | G19: =C19-E19 -> #REF! | H19: =(C19*$H$4)+C19 -> 0 | I19: =E19 -> #REF! | J19: =H19-I19 -> #REF! | K19: =I19/H19 -> #REF!
A20: Dynamite Shrimps | B20: 11 | C20: =B20*90000 -> 990000 | D20: =E20/$A$2 -> #REF! | E20: =STARTERS!$C$329 -> #REF! | F20: =IF(E20="","",IF(ISBLANK(C20),"",E20/C20)) -> #REF! | G20: =C20-E20 -> #REF! | H20: =(C20*$H$4)+C20 -> 1089000 | I20: =E20 -> #REF! | J20: =H20-I20 -> #REF! | K20: =I20/H20 -> #REF!
A21: Truffle Fries | B21: 9 | C21: =B21*90000 -> 810000 | D21: =E21/$A$2 -> #REF! | E21: =STARTERS!$L$329 -> 26242.167 | F21: =IF(E21="","",IF(ISBLANK(C21),"",E21/C21)) -> 0.032397738 | G21: =C21-E21 -> 783757.83 | H21: =(C21*$H$4)+C21 -> 891000 | I21: =E21 -> 26242.167 | J21: =H21-I21 -> 864757.83 | K21: =I21/H21 -> 0.029452489
A22: Dynamite Chicken | C22: =B22*90000 -> 0 | D22: =E22/$A$2 -> #REF! | E22: =STARTERS!$C$374 -> #REF! | F22: =IF(E22="","",IF(ISBLANK(C22),"",E22/C22)) -> #REF! | G22: =C22-E22 -> #REF! | H22: =(C22*$H$4)+C22 -> 0 | I22: =E22 -> #REF! | J22: =H22-I22 -> #REF! | K22: =I22/H22 -> #REF!
A23: Criss Cut Truffle | C23: =B23*90000 -> 0 | D23: =E23/$A$2 -> #REF! | E23: =STARTERS!$C$465 -> #REF! | H23: =(C23*$H$4)+C23 -> 0 | I23: =E23 -> #REF! | J23: =H23-I23 -> #REF! | K23: =I23/H23 -> #REF!
A24: Twiter Fries | B24: 8.5 | C24: =B24*90000 -> 765000 | D24: =E24/$A$2 -> #REF! | E24: =STARTERS!$L$374 -> #REF! | F24: =IF(E24="","",IF(ISBLANK(C24),"",E24/C24)) -> #REF! | G24: =C24-E24 -> #REF! | H24: =(C24*$H$4)+C24 -> 841500 | I24: =E24 -> #REF! | J24: =H24-I24 -> #REF! | K24: =I24/H24 -> #REF!
A25: Cheese Potato | C25: =B25*90000 -> 0 | D25: =E25/$A$2 -> #REF! | E25: =STARTERS!$C$420 -> #REF! | F25: =IF(E25="","",IF(ISBLANK(C25),"",E25/C25)) -> #REF! | G25: =C25-E25 -> #REF! | H25: =#REF!*$H$4+#REF! -> #REF! | I25: =#REF! -> #REF! | J25: =H25-I25 -> #REF! | K25: =IF(#REF!="","",IF(ISBLANK(H25),"",I25/H25)) -> #REF!
A26: HM Wedges Truffle | C26: =B26*90000 -> 0 | D26: =E26/$A$2 -> #REF! | E26: =STARTERS!$L$420 -> #REF! | F26: =IF(E26="","",IF(ISBLANK(C26),"",E26/C26)) -> #REF! | G26: =C26-E26 -> #REF! | H26: =#REF!*$H$4+#REF! -> #REF! | I26: =#REF! -> #REF! | J26: =H26-I26 -> #REF! | K26: =IF(#REF!="","",IF(ISBLANK(H26),"",I26/H26)) -> #REF!
A27: Fries Combo | C27: =B27*90000 -> 0 | D27: =E27/$A$2 -> #REF! | E27: =STARTERS!$C$510 -> #REF! | F27: =IF(E27="","",IF(ISBLANK(C27),"",E27/C27)) -> #REF! | G27: =C27-E27 -> #REF! | H27: =#REF!*$H$4+#REF! -> #REF! | I27: =#REF! -> #REF! | J27: =H27-I27 -> #REF! | K27: =IF(#REF!="","",IF(ISBLANK(H27),"",I27/H27)) -> #REF!
B28: 9 | C28: =B28*90000 -> 810000 | F28: =IF(E28="","",IF(ISBLANK(C28),"",E28/C28))
A29: Salads | F29: =IF(E29="","",IF(ISBLANK(C29),"",E29/C29))
A30: Rocket Parmesan | C30: =B30/90000 -> 0 | D30: =E30/$A$2 -> #REF! | E30: =SALADS!$C$10 -> #REF! | F30: =IF(E30="","",IF(ISBLANK(C30),"",E30/C30)) -> #REF! | G30: =C30-E30 -> #REF! | H30: =#REF!*$H$4+#REF! -> #REF! | I30: =#REF! -> #REF! | J30: =H30-I30 -> #REF! | K30: =IF(#REF!="","",IF(ISBLANK(H30),"",I30/H30)) -> #REF!
A31: Greek | B31: 8 | C31: =B31*90000 -> 720000 | D31: =E31/$A$2 -> #REF! | E31: =SALADS!$L$10 -> #REF! | F31: =IF(E31="","",IF(ISBLANK(C31),"",E31/C31)) -> #REF! | G31: =C31-E31 -> #REF! | H31: =(C31*$H$4)+C31 -> 792000 | I31: =E31 -> #REF! | J31: =H31-I31 -> #REF! | K31: =I31/H31 -> #REF!
A32: Caesar | B32: 8 | C32: =B32*90000 -> 720000 | D32: =E32/$A$2 -> #REF! | E32: =SALADS!$C$54 -> #REF! | F32: =IF(E32="","",IF(ISBLANK(C32),"",E32/C32)) -> #REF! | G32: =C32-E32 -> #REF! | H32: =(C32*$H$4)+C32 -> 792000 | I32: =E32 -> #REF! | J32: =H32-I32 -> #REF! | K32: =I32/H32 -> #REF!
A33: Chicken Caesar | B33: 11 | C33: =B33*90000 -> 990000 | D33: =E33/$A$2 -> #REF! | E33: =SALADS!$L$54 -> #REF! | F33: =IF(E33="","",IF(ISBLANK(C33),"",E33/C33)) -> #REF! | G33: =C33-E33 -> #REF! | H33: =(C33*$H$4)+C33 -> 1089000 | I33: =E33 -> #REF! | J33: =H33-I33 -> #REF! | K33: =I33/H33 -> #REF!
A34: Pasta Tuna | B34: 9 | C34: =B34*90000 -> 810000 | D34: =E34/$A$2 -> #REF! | E34: =SALADS!$C$99 -> #REF! | F34: =IF(E34="","",IF(ISBLANK(C34),"",E34/C34)) -> #REF! | G34: =C34-E34 -> #REF! | H34: =(C34*$H$4)+C34 -> 891000 | I34: =E34 -> #REF! | J34: =H34-I34 -> #REF! | K34: =I34/H34 -> #REF!
A35: Freekeh Halloumi Salad | C35: =B35*90000 -> 0 | D35: =E35/$A$2 -> #REF! | E35: =SALADS!L373 -> #REF! | F35: =IF(E35="","",IF(ISBLANK(C35),"",E35/C35)) -> #REF! | G35: =C35-E35 -> #REF! | H35: =(C35*$H$4)+C35 -> 0 | I35: =E35 -> #REF! | J35: =H35-I35 -> #REF! | K35: =I35/H35 -> #REF!
A36: Pro's | C36: =B36*90000 -> 0 | D36: =E36/$A$2 -> #REF! | E36: =SALADS!$C$146 -> #REF! | F36: =IF(E36="","",IF(ISBLANK(C36),"",E36/C36)) -> #REF! | G36: =C36-E36 -> #REF! | H36: =(C36*$H$4)+C36 -> 0 | I36: =E36 -> #REF! | J36: =H36-I36 -> #REF! | K36: =I36/H36 -> #REF!
A37: Crab Avocado | B37: 10 | C37: =B37*90000 -> 900000 | D37: =E37/$A$2 -> #REF! | E37: =SALADS!$L$282 -> #REF! | F37: =IF(E37="","",IF(ISBLANK(C37),"",E37/C37)) -> #REF! | G37: =C37-E37 -> #REF! | H37: =(C37*$H$4)+C37 -> 990000 | I37: =E37 -> #REF! | J37: =H37-I37 -> #REF! | K37: =I37/H37 -> #REF!
A38: Kale Chicken | B38: 10 | C38: =B38*90000 -> 900000 | D38: =E38/$A$2 -> #REF! | E38: =SALADS!C192 -> #REF! | F38: =IF(E38="","",IF(ISBLANK(C38),"",E38/C38)) -> #REF! | G38: =C38-E38 -> #REF! | H38: =(C38*$H$4)+C38 -> 990000 | I38: =E38 -> #REF! | J38: =H38-I38 -> #REF! | K38: =I38/H38 -> #REF!
A39: Cranberry Citrus Crunch | C39: =B39*90000 -> 0 | D39: =E39/$A$2 -> #REF! | E39: =SALADS!L463 -> #REF! | F39: =IF(E39="","",IF(ISBLANK(C39),"",E39/C39)) -> #REF! | G39: =C39-E39 -> #REF! | H39: =(C39*$H$4)+C39 -> 0 | I39: =E39 -> #REF! | J39: =H39-I39 -> #REF! | K39: =I39/H39 -> #REF!
A40: BBQ Chicken Salad | B40: 10 | C40: =B40*90000 -> 900000 | D40: =E40/$A$2 -> #REF! | E40: =SALADS!$L$237 -> #REF! | F40: =IF(E40="","",IF(ISBLANK(C40),"",E40/C40)) -> #REF! | G40: =C40-E40 -> #REF! | H40: =(C40*$H$4)+C40 -> 990000 | I40: =E40 -> #REF! | J40: =H40-I40 -> #REF! | K40: =I40/H40 -> #REF!
A41: Cobb Salad | B41: 10 | C41: =B41*90000 -> 900000 | D41: =E41/$A$2 -> #REF! | E41: =SALADS!$L$328 -> #REF! | F41: =IF(E41="","",IF(ISBLANK(C41),"",E41/C41)) -> #REF! | G41: =C41-E41 -> #REF! | H41: =(C41*$H$4)+C41 -> 990000 | I41: =E41 -> #REF! | J41: =H41-I41 -> #REF! | K41: =I41/H41 -> #REF!
A42: Chicken Peanut Garden | C42: =B42*90000 -> 0 | D42: =E42/$A$2 -> #REF! | E42: =SALADS!C509 -> #REF! | F42: =IF(E42="","",IF(ISBLANK(C42),"",E42/C42)) -> #REF! | G42: =C42-E42 -> #REF! | H42: =(C42*$H$4)+C42 -> 0 | I42: =E42 -> #REF! | J42: =H42-I42 -> #REF! | K42: =I42/H42 -> #REF!
A43: Kale Shrimps Salad | B43: 11 | C43: =B43*90000 -> 990000 | D43: =E43/$A$2 -> #REF! | E43: =SALADS!$C$328 -> #REF! | F43: =IF(E43="","",IF(ISBLANK(C43),"",E43/C43)) -> #REF! | G43: =C43-E43 -> #REF! | H43: =(C43*$H$4)+C43 -> 1089000 | I43: =E43 -> #REF! | J43: =H43-I43 -> #REF! | K43: =I43/H43 -> #REF!
A44: =SALADS!C550 -> Goat Cheese | B44: 12 | C44: =B44*90000 -> 1080000 | D44: =E44/$A$2 -> #REF! | E44: =SALADS!C554 -> #REF! | F44: =IF(E44="","",IF(ISBLANK(C44),"",E44/C44)) -> #REF! | G44: =C44-E44 -> #REF! | H44: =(C44*$H$4)+C44 -> 1188000 | I44: =E44 -> #REF! | J44: =H44-I44 -> #REF! | K44: =I44/H44 -> #REF!
A45: =SALADS!L505 -> Salmon Quinoa | B45: 15 | C45: =B45*90000 -> 1350000 | D45: =E45/$A$2 -> #REF! | E45: =SALADS!L509 -> #REF! | F45: =IF(E45="","",IF(ISBLANK(C45),"",E45/C45)) -> #REF! | G45: =C45-E45 -> #REF! | H45: =(C45*$H$4)+C45 -> 1485000 | I45: =E45 -> #REF! | J45: =H45-I45 -> #REF! | K45: =I45/H45 -> #REF!
F46: =IF(E46="","",IF(ISBLANK(C46),"",E46/C46))
A47: Pizza
A48: Margherita | B48: 10 | C48: =B48*90000 -> 900000 | D48: =E48/$A$2 -> #REF! | F48: =IF(E48="","",IF(ISBLANK(C48),"",E48/C48)) | G48: =C48-E48 -> 900000 | H48: =(C48*$H$4)+C48 -> 990000 | I48: =E48 | J48: =H48-I48 -> 990000 | K48: =I48/H48 -> 0
A49: Vegetarian | B49: 11 | C49: =B49*90000 -> 990000 | D49: =E49/$A$2 -> #REF! | E49: =PIZZA!$C$54 -> #REF! | F49: =IF(E49="","",IF(ISBLANK(C49),"",E49/C49)) -> #REF! | G49: =C49-E49 -> #REF! | H49: =(C49*$H$4)+C49 -> 1089000 | I49: =E49 -> #REF! | J49: =H49-I49 -> #REF! | K49: =I49/H49 -> #REF!
A50: Regular | B50: 13 | C50: =B50*90000 -> 1170000 | D50: =E50/$A$2 -> #REF! | E50: =PIZZA!$L$10 -> #REF! | F50: =IF(E50="","",IF(ISBLANK(C50),"",E50/C50)) -> #REF! | G50: =C50-E50 -> #REF! | H50: =(C50*$H$4)+C50 -> 1287000 | I50: =E50 -> #REF! | J50: =H50-I50 -> #REF! | K50: =I50/H50 -> #REF!
A51: Pepperoni | B51: 12 | C51: =B51*90000 -> 1080000 | D51: =E51/$A$2 -> #REF! | E51: =PIZZA!$L$54 -> #REF! | F51: =IF(E51="","",IF(ISBLANK(C51),"",E51/C51)) -> #REF! | G51: =C51-E51 -> #REF! | H51: =(C51*$H$4)+C51 -> 1188000 | I51: =E51 -> #REF! | J51: =H51-I51 -> #REF! | K51: =I51/H51 -> #REF!
A52: BBQ Chicken | B52: 15 | C52: =B52*90000 -> 1350000 | D52: =E52/$A$2 -> #REF! | E52: =PIZZA!$L$99 -> #REF! | F52: =IF(E52="","",IF(ISBLANK(C52),"",E52/C52)) -> #REF! | G52: =C52-E52 -> #REF! | H52: =(C52*$H$4)+C52 -> 1485000 | I52: =E52 -> #REF! | J52: =H52-I52 -> #REF! | K52: =I52/H52 -> #REF!
A53: Sundried Tomato | B53: 16 | C53: =B53*90000 -> 1440000 | D53: =E53/$A$2 -> #REF! | E53: =PIZZA!$C$99 -> 32219.237 | F53: =IF(E53="","",IF(ISBLANK(C53),"",E53/C53)) -> 0.02237447 | G53: =C53-E53 -> 1407780.8 | H53: =(C53*$H$4)+C53 -> 1584000 | I53: =E53 -> 32219.237 | J53: =H53-I53 -> 1551780.8 | K53: =I53/H53 -> 0.020340427
A54: =PIZZA!C187 -> Alfredo | B54: 16 | C54: =B54*90000 -> 1440000 | D54: =E54/$A$2 -> #REF! | E54: =PIZZA!C191 -> #REF! | F54: =IF(E54="","",IF(ISBLANK(C54),"",E54/C54)) -> #REF! | G54: =C54-E54 -> #REF! | H54: =(C54*$H$4)+C54 -> 1584000 | I54: =E54 -> #REF! | J54: =H54-I54 -> #REF! | K54: =I54/H54 -> #REF!
A55: =PIZZA!L187 -> Goat Cheese | C55: =B55*90000 -> 0 | D55: =E55/$A$2 -> #REF! | E55: =PIZZA!L191 -> #REF! | F55: =IF(E55="","",IF(ISBLANK(C55),"",E55/C55)) -> #REF! | G55: =C55-E55 -> #REF! | H55: =(C55*$H$4)+C55 -> 0 | I55: =E55 -> #REF! | J55: =H55-I55 -> #REF! | K55: =I55/H55 -> #REF!
A56: =PIZZA!C232 -> Salmon | C56: =B56*90000 -> 0 | D56: =E56/$A$2 -> #REF! | E56: =PIZZA!C236 -> #REF! | F56: =IF(E56="","",IF(ISBLANK(C56),"",E56/C56)) -> #REF! | G56: =C56-E56 -> #REF! | H56: =(C56*$H$4)+C56 -> 0 | I56: =E56 -> #REF! | J56: =H56-I56 -> #REF! | K56: =I56/H56 -> #REF!
A57: =PIZZA!L232 -> Shrimps Pesto | C57: =B57*90000 -> 0 | D57: =E57/$A$2 -> #REF! | E57: =PIZZA!L236 -> #REF! | F57: =IF(E57="","",IF(ISBLANK(C57),"",E57/C57)) -> #REF! | G57: =C57-E57 -> #REF! | H57: =(C57*$H$4)+C57 -> 0 | I57: =E57 -> #REF! | J57: =H57-I57 -> #REF! | K57: =I57/H57 -> #REF!
A58: Truffle Pizza | B58: 17 | C58: =B58*90000 -> 1530000 | F58: =IF(E58="","",IF(ISBLANK(C58),"",E58/C58))
A59: Pasta | F59: =IF(E59="","",IF(ISBLANK(C59),"",E59/C59))
A60: Arrabiata | B60: 9 | C60: =B60*90000 -> 810000 | D60: =E60/$A$2 -> #REF! | E60: =PASTA!$C$10 -> #REF! | F60: =IF(E60="","",IF(ISBLANK(C60),"",E60/C60)) -> #REF! | G60: =C60-E60 -> #REF! | H60: =(C60*$H$4)+C60 -> 891000 | I60: =E60 -> #REF! | J60: =H60-I60 -> #REF! | K60: =I60/H60 -> #REF!
A61: Four Cheese | B61: 12 | C61: =B61*90000 -> 1080000 | D61: =E61/$A$2 -> #REF! | E61: =PASTA!$L$10 -> #REF! | F61: =IF(E61="","",IF(ISBLANK(C61),"",E61/C61)) -> #REF! | G61: =C61-E61 -> #REF! | H61: =(C61*$H$4)+C61 -> 1188000 | I61: =E61 -> #REF! | J61: =H61-I61 -> #REF! | K61: =I61/H61 -> #REF!
A62: Tagliatelle Al Pollo | B62: 14 | C62: =B62*90000 -> 1260000 | D62: =E62/$A$2 -> #REF! | E62: =PASTA!$C$54 -> #REF! | F62: =IF(E62="","",IF(ISBLANK(C62),"",E62/C62)) -> #REF! | G62: =C62-E62 -> #REF! | H62: =(C62*$H$4)+C62 -> 1386000 | I62: =E62 -> #REF! | J62: =H62-I62 -> #REF! | K62: =I62/H62 -> #REF!
A63: Mac n Cheese | B63: 16 | C63: =B63*90000 -> 1440000 | D63: =E63/$A$2 -> #REF! | E63: =PASTA!$L$54 -> #REF! | F63: =IF(E63="","",IF(ISBLANK(C63),"",E63/C63)) -> #REF! | G63: =C63-E63 -> #REF! | H63: =(C63*$H$4)+C63 -> 1584000 | I63: =E63 -> #REF! | J63: =H63-I63 -> #REF! | K63: =I63/H63 -> #REF!
A64: Pinky Shrimps | B64: 13 | C64: =B64*90000 -> 1170000 | D64: =E64/$A$2 -> #REF! | E64: =PASTA!$C$99 -> #REF! | F64: =IF(E64="","",IF(ISBLANK(C64),"",E64/C64)) -> #REF! | G64: =C64-E64 -> #REF! | H64: =(C64*$H$4)+C64 -> 1287000 | I64: =E64 -> #REF! | J64: =H64-I64 -> #REF! | K64: =I64/H64 -> #REF!
A65: Spaghetti Bolognese | C65: =B65*90000 -> 0 | D65: =E65/$A$2 -> #REF! | E65: =PASTA!$L$99 -> #REF! | F65: =IF(E65="","",IF(ISBLANK(C65),"",E65/C65)) -> #REF! | G65: =C65-E65 -> #REF! | H65: =(C65*$H$4)+C65 -> 0 | I65: =E65 -> #REF! | J65: =H65-I65 -> #REF! | K65: =I65/H65 -> #REF!
A66: Chicken Pesto | C66: =B66*90000 -> 0 | D66: =E66/$A$2 -> #REF! | E66: =PASTA!L144 -> #REF! | F66: =IF(E66="","",IF(ISBLANK(C66),"",E66/C66)) -> #REF! | G66: =C66-E66 -> #REF! | H66: =(C66*$H$4)+C66 -> 0 | I66: =E66 -> #REF! | J66: =H66-I66 -> #REF! | K66: =I66/H66 -> #REF!
A67: Truflle Pasta | B67: 12 | C67: =B67*90000 -> 1080000 | D67: =E67/$A$2 -> #REF! | E67: =PASTA!C189 -> #REF! | F67: =IF(E67="","",IF(ISBLANK(C67),"",E67/C67)) -> #REF! | G67: =C67-E67 -> #REF! | H67: =(C67*$H$4)+C67 -> 1188000 | I67: =E67 -> #REF! | J67: =H67-I67 -> #REF! | K67: =I67/H67 -> #REF!
A68: =PASTA!L185 -> Salmon Pasta | C68: =B68*90000 -> 0 | D68: =E68/$A$2 -> #REF! | E68: =PASTA!L189 -> #REF! | F68: =IF(E68="","",IF(ISBLANK(C68),"",E68/C68)) -> #REF! | G68: =C68-E68 -> #REF!
A69: Pesto | C69: =B69*90000 -> 0 | D69: =E69/$A$2 -> #REF! | E69: =PASTA!C144 -> #REF! | F69: =IF(E69="","",IF(ISBLANK(C69),"",E69/C69)) -> #REF! | G69: =C69-E69 -> #REF! | H69: =(C69*$H$4)+C69 -> 0 | I69: =E69 -> #REF! | J69: =H69-I69 -> #REF! | K69: =I69/H69 -> #REF!
F70: =IF(E70="","",IF(ISBLANK(C70),"",E70/C70))
A71: Burger | F71: =IF(E71="","",IF(ISBLANK(C71),"",E71/C71))
A72: Classic 90 | B72: 10 | C72: =B72*90000 -> 900000 | D72: =E72/$A$2 -> #REF! | E72: ='BURGERS '!$C$10 -> #REF! | F72: =IF(E72="","",IF(ISBLANK(C72),"",E72/C72)) -> #REF! | G72: =C72-E72 -> #REF! | H72: =(C72*$H$4)+C72 -> 990000 | I72: =E72 -> #REF! | J72: =H72-I72 -> #REF! | K72: =I72/H72 -> #REF!
A73: Mini Sliders | C73: =B73*90000 -> 0 | D73: =E73/$A$2 -> #REF! | E73: ='BURGERS '!$L$10 -> #REF! | F73: =IF(E73="","",IF(ISBLANK(C73),"",E73/C73)) -> #REF! | G73: =C73-E73 -> #REF! | H73: =(C73*$H$4)+C73 -> 0 | I73: =E73 -> #REF! | J73: =H73-I73 -> #REF! | K73: =I73/H73 -> #REF!
A74: BBQ Bacon | B74: 15 | C74: =B74*90000 -> 1350000 | D74: =E74/$A$2 -> #REF! | E74: ='BURGERS '!$C$236 -> #REF! | F74: =IF(E74="","",IF(ISBLANK(C74),"",E74/C74)) -> #REF! | G74: =C74-E74 -> #REF! | H74: =(C74*$H$4)+C74 -> 1485000 | I74: =E74 -> #REF! | J74: =H74-I74 -> #REF! | K74: =I74/H74 -> #REF!
A75: Swiss Mushrooms | B75: 14 | C75: =B75*90000 -> 1260000 | D75: =E75/$A$2 -> #REF! | E75: ='BURGERS '!C146 -> #REF! | F75: =IF(E75="","",IF(ISBLANK(C75),"",E75/C75)) -> #REF! | G75: =C75-E75 -> #REF! | H75: =(C75*$H$4)+C75 -> 1386000 | I75: =E75 -> #REF! | J75: =H75-I75 -> #REF! | K75: =I75/H75 -> #REF!
A76: Chicken Pesto | C76: =B76*90000 -> 0 | D76: =E76/$A$2 -> #REF! | E76: ='BURGERS '!C282 -> #REF! | F76: =IF(E76="","",IF(ISBLANK(C76),"",E76/C76)) -> #REF! | G76: =C76-E76 -> #REF! | H76: =(C76*$H$4)+C76 -> 0 | I76: =E76 -> #REF! | J76: =H76-I76 -> #REF! | K76: =I76/H76 -> #REF!
A77: Tangy | B77: 16 | C77: =B77*90000 -> 1440000 | D77: =E77/$A$2 -> #REF! | E77: ='BURGERS '!$C$100 -> #REF! | F77: =IF(E77="","",IF(ISBLANK(C77),"",E77/C77)) -> #REF! | G77: =C77-E77 -> #REF! | H77: =(C77*$H$4)+C77 -> 1584000 | I77: =E77 -> #REF! | J77: =H77-I77 -> #REF! | K77: =I77/H77 -> #REF!
A78: Volcanco | B78: 16 | C78: =B78*90000 -> 1440000 | D78: =E78/$A$2 -> #REF! | E78: ='BURGERS '!$L$146 -> #REF! | F78: =IF(E78="","",IF(ISBLANK(C78),"",E78/C78)) -> #REF! | G78: =C78-E78 -> #REF! | H78: =(C78*$H$4)+C78 -> 1584000 | I78: =E78 -> #REF! | J78: =H78-I78 -> #REF! | K78: =I78/H78 -> #REF!
A79: Pulled Beef | B79: 14 | C79: =B79*90000 -> 1260000 | D79: =E79/$A$2 -> #REF! | E79: ='BURGERS '!L236 -> #REF! | F79: =IF(E79="","",IF(ISBLANK(C79),"",E79/C79)) -> #REF! | G79: =C79-E79 -> #REF! | H79: =(C79*$H$4)+C79 -> 1386000 | I79: =E79 -> #REF! | J79: =H79-I79 -> #REF! | K79: =I79/H79 -> #REF!
A80: Truffle | B80: 15 | C80: =B80*90000 -> 1350000 | D80: =E80/$A$2 -> #VALUE! | E80: ='BURGERS '!$C$191:$D$191 -> #VALUE! | F80: =IF(E80="","",IF(ISBLANK(C80),"",E80/C80)) -> #VALUE! | G80: =C80-E80 -> #VALUE! | H80: =(C80*$H$4)+C80 -> 1485000 | I80: =E80 -> #VALUE! | J80: =H80-I80 -> #VALUE! | K80: =I80/H80 -> #VALUE!
F81: =IF(E81="","",IF(ISBLANK(C81),"",E81/C81))
A82: Mains | F82: =IF(E82="","",IF(ISBLANK(C82),"",E82/C82))
A83: Cordon Blu | C83: =B83/90000 -> 0 | D83: =E83/$A$2 -> #REF! | E83: 0 | F83: =IF(E83="","",IF(ISBLANK(C83),"",E83/C83)) -> #DIV/0! | G83: =C83-E83 -> 0 | H83: 10.5 | K83: =IF(#REF!="","",IF(ISBLANK(H83),"",#REF!/H83)) -> #REF!
A84: Grilled Chicken | B84: 13 | C84: =B84*90000 -> 1170000 | D84: =E84/$A$2 -> #REF! | E84: =MAINS!$L$10 -> #REF! | F84: =IF(E84="","",IF(ISBLANK(C84),"",E84/C84)) -> #REF! | G84: =C84-E84 -> #REF! | H84: =(C84*$H$4)+C84 -> 1287000 | I84: =E84 -> #REF! | J84: =H84-I84 -> #REF! | K84: =I84/H84 -> #REF!
A85: Chicken Mushroom | B85: 15.5 | C85: =B85*90000 -> 1395000 | D85: =E85/$A$2 -> #REF! | E85: =MAINS!$L$54 -> #REF! | F85: =IF(E85="","",IF(ISBLANK(C85),"",E85/C85)) -> #REF! | G85: =C85-E85 -> #REF! | H85: =(C85*$H$4)+C85 -> 1534500 | I85: =E85 -> #REF! | J85: =H85-I85 -> #REF! | K85: =I85/H85 -> #REF!
A86: Taouk | B86: 13 | C86: =B86*90000 -> 1170000 | D86: =E86/$A$2 -> #REF! | E86: =MAINS!$C$54 -> #REF! | F86: =IF(E86="","",IF(ISBLANK(C86),"",E86/C86)) -> #REF! | G86: =C86-E86 -> #REF! | H86: =(C86*$H$4)+C86 -> 1287000 | I86: =E86 -> #REF! | J86: =H86-I86 -> #REF! | K86: =I86/H86 -> #REF!
A87: Chicken Fajita | B87: 16 | C87: =B87*90000 -> 1440000 | D87: =E87/$A$2 -> #REF! | E87: =MAINS!$L$99 -> #REF! | F87: =IF(E87="","",IF(ISBLANK(C87),"",E87/C87)) -> #REF! | G87: =C87-E87 -> #REF! | H87: =(C87*$H$4)+C87 -> 1584000 | I87: =E87 -> #REF! | J87: =H87-I87 -> #REF! | K87: =I87/H87 -> #REF!
A88: Shrimps Fajita | B88: 16 | C88: =B88*90000 -> 1440000 | D88: =E88/$A$2 -> #REF! | E88: =MAINS!$L$144 -> #REF! | F88: =IF(E88="","",IF(ISBLANK(C88),"",E88/C88)) -> #REF! | G88: =C88-E88 -> #REF! | H88: =(C88*$H$4)+C88 -> 1584000 | I88: =E88 -> #REF! | J88: =H88-I88 -> #REF! | K88: =I88/H88 -> #REF!
A89: Shrimps Mix | C89: =B89*90000 -> 0 | D89: =E89/$A$2 -> #REF! | E89: =MAINS!C415 -> #REF! | F89: =IF(E89="","",IF(ISBLANK(C89),"",E89/C89)) -> #REF! | G89: =C89-E89 -> #REF! | H89: =(C89*$H$4)+C89 -> 0 | I89: =E89 -> #REF! | J89: =H89-I89 -> #REF! | K89: =I89/H89 -> #REF!
A90: Boneless | B90: 16 | C90: =B90*90000 -> 1440000 | D90: =E90/$A$2 -> #REF! | E90: =LEBANESE!$L$99 -> #REF! | F90: =IF(E90="","",IF(ISBLANK(C90),"",E90/C90)) -> #REF! | G90: =C90-E90 -> #REF! | H90: =(C90*$H$4)+C90 -> 1584000 | I90: =E90 -> #REF! | J90: =H90-I90 -> #REF! | K90: =I90/H90 -> #REF!
A91: Butterfly Escalope | B91: 13 | C91: =B91*90000 -> 1170000 | D91: =E91/$A$2 -> #REF! | E91: =MAINS!L279 -> #REF! | F91: =IF(E91="","",IF(ISBLANK(C91),"",E91/C91)) -> #REF! | G91: =C91-E91 -> #REF! | H91: =(C91*$H$4)+C91 -> 1287000 | I91: =E91 -> #REF! | J91: =H91-I91 -> #REF! | K91: =I91/H91 -> #REF!
A92: Great Escalope | B92: 15 | C92: =B92*90000 -> 1350000 | D92: =E92/$A$2 -> #REF! | E92: =MAINS!$C$189 -> #REF! | F92: =IF(E92="","",IF(ISBLANK(C92),"",E92/C92)) -> #REF! | G92: =C92-E92 -> #REF! | H92: =(C92*$H$4)+C92 -> 1485000 | I92: =E92 -> #REF! | J92: =H92-I92 -> #REF! | K92: =I92/H92 -> #REF!
A93: Pros Escalope | B93: 18 | C93: =B93*90000 -> 1620000 | D93: =E93/$A$2 -> #REF! | E93: =MAINS!$L$189 -> #REF! | F93: =IF(E93="","",IF(ISBLANK(C93),"",E93/C93)) -> #REF! | G93: =C93-E93 -> #REF! | H93: =(C93*$H$4)+C93 -> 1782000 | I93: =E93 -> #REF! | J93: =H93-I93 -> #REF! | K93: =I93/H93 -> #REF!
A94: Grilled Salmon | B94: 22 | C94: =B94*90000 -> 1980000 | D94: =E94/$A$2 -> #REF! | E94: =MAINS!L325 -> #REF! | F94: =IF(E94="","",IF(ISBLANK(C94),"",E94/C94)) -> #REF! | G94: =C94-E94 -> #REF! | H94: =(C94*$H$4)+C94 -> 2178000 | I94: =E94 -> #REF! | J94: =H94-I94 -> #REF! | K94: =I94/H94 -> #REF!
A95: Grilled Shrimps | C95: =B95*90000 -> 0 | D95: =E95/$A$2 -> #REF! | E95: =MAINS!C325 -> #REF! | F95: =IF(E95="","",IF(ISBLANK(C95),"",E95/C95)) -> #REF! | G95: =C95-E95 -> #REF! | H95: =(C95*$H$4)+C95 -> 0 | I95: =E95 -> #REF! | J95: =H95-I95 -> #REF! | K95: =I95/H95 -> #REF!
A96: Steak Swiss Tenderloin | C96: =B96*90000 -> 0 | D96: =E96/$A$2 -> #REF! | E96: =MAINS!C370 -> #REF! | F96: =IF(E96="","",IF(ISBLANK(C96),"",E96/C96)) -> #REF! | G96: =C96-E96 -> #REF! | H96: =(C96*$H$4)+C96 -> 0 | I96: =E96 -> #REF! | J96: =H96-I96 -> #REF! | K96: =I96/H96 -> #REF!
A97: ENTRECOTE | B97: 17 | C97: =B97*90000 -> 1530000 | D97: =E97/$A$2 -> #REF! | E97: =MAINS!L370 -> #REF! | F97: =IF(E97="","",IF(ISBLANK(C97),"",E97/C97)) -> #REF! | G97: =C97-E97 -> #REF! | H97: =(C97*$H$4)+C97 -> 1683000 | I97: =E97 -> #REF! | J97: =H97-I97 -> #REF! | K97: =I97/H97 -> #REF!
A98: Steak & Fries | B98: 21 | C98: =B98*90000 -> 1890000 | D98: =E98/$A$2 -> #REF! | E98: =MAINS!$C$99 -> #REF! | F98: =IF(E98="","",IF(ISBLANK(C98),"",E98/C98)) -> #REF! | G98: =C98-E98 -> #REF! | H98: =(C98*$H$4)+C98 -> 2079000 | I98: =E98 -> #REF! | J98: =H98-I98 -> #REF! | K98: =I98/H98 -> #REF!
A99: Rice Chicken | B99: 15 | C99: =B99*90000 -> 1350000 | D99: =E99/$A$2 -> #REF! | E99: ='RICE MEALS'!C55 -> #REF! | F99: =IF(E99="","",IF(ISBLANK(C99),"",E99/C99)) -> #REF! | G99: =C99-E99 -> #REF! | H99: =(C99*$H$4)+C99 -> 1485000 | I99: =E99 -> #REF! | J99: =H99-I99 -> #REF! | K99: =I99/H99 -> #REF!
A100: Rice Crispy Chicken | B100: 13.5 | C100: =B100*90000 -> 1215000 | D100: =E100/$A$2 -> #REF! | E100: ='RICE MEALS'!C101 -> #REF! | F100: =IF(E100="","",IF(ISBLANK(C100),"",E100/C100)) -> #REF! | G100: =C100-E100 -> #REF! | H100: =(C100*$H$4)+C100 -> 1336500 | I100: =E100 -> #REF! | J100: =H100-I100 -> #REF! | K100: =I100/H100 -> #REF!
...

Sheet F&B
B1: Item | C1: Unit | D1: Qty | E1: Unit Price $ | F1: Unit Price LBP | G1: Total Price | H1: Supplier | I1: Brand
B2: Food
B3: BAKERY
B4: ARABIC BREAD | C4: BAG | E4: 0.97 | F4: =E4*9000 -> 8730 | G4: =D4*F4 -> 0 | H4: WOODEN BAKERY | I4: WOODEN BAKERY
B5: BAGUETTE 24CM 40 PCS | C5: BOX | E5: 25.22 | F5: =E5*9000 -> 226980 | G5: =D5*F5 -> 0 | H5: Delifrance | I5: Delifrance
B6: BAGUETTE BROWN 40 PCS | C6: BOX | E6: =27.93*1.1 -> 30.723 | F6: =E6*9000 -> 276507 | G6: =D6*F6 -> 0 | H6: Delifrance | I6: Delifrance
B7: BREAD CRUMBS YELLOW 25 KG | C7: BAG | E7: 2 | F7: =E7*9000 -> 18000 | G7: =D7*F7 -> 0 | H7: Aya Foods
B8: PANCO CRUMBS 10 KG | C8: Bag | E8: =4.5*1.1 -> 4.95 | F8: =E8*9000 -> 44550 | G8: =D8*F8 -> 0 | H8: E. JABRA
B9: KAAK CRUSHED WHITE KG | C9: KG | E9: 2.22 | F9: =E9*9000 -> 19980 | G9: =D9*F9 -> 0 | H9: WOODEN BAKERY | I9: WOODEN BAKERY
B10: BURGER BUN 6 PCS | C10: Bag | E10: =(31.18*1.1)/(54/6) -> 3.8108889 | F10: =E10*9000 -> 34298 | G10: =D10*F10 -> 0 | H10: Delifrance | I10: Delifrance
B11: SOURDOUGH BAGUETTE W 50 PCS 28 CM | C11: BOX | E11: =27.45*1.1 -> 30.195 | F11: =E11*9000 -> 271755 | G11: =D11*F11 -> 0 | H11: Delifrance | I11: Delifrance
B12: SOURDOUGH BAGUETTE B 50 PCS 28 CM | C12: BOX | E12: =31.67*1.1 -> 34.837 | F12: =E12*9000 -> 313533 | G12: =D12*F12 -> 0 | H12: Delifrance | I12: Delifrance
B13: BURGER BUN BROWN 6 PCS | C13: Bag | E13: 3.7 | F13: =E13*9000 -> 33300 | G13: =D13*F13 -> 0 | H13: Delifrance | I13: Delifrance
B14: MINI BURGER BUN 12 PCS | C14: Bag | E14: =2.11*1.1 -> 2.321 | F14: =E14*9000 -> 20889 | G14: =D14*F14 -> 0 | H14: Delifrance | I14: Delifrance
B15: CIABATTA PCS 40 PCS | C15: Box | E15: =1.1*21.4 -> 23.54 | F15: =E15*9000 -> 211860 | G15: =D15*F15 -> 0 | H15: Delifrance | I15: Delifrance
B16: CIABATTA BROWN 40 PCS | C16: Box | E16: 53 | F16: =E16*9000 -> 477000 | G16: =D16*F16 -> 0 | H16: Delifrance | I16: Delifrance
B17: FLOUR EXTRA (50KG) | C17: Bag | E17: 29.42 | F17: =E17*9000 -> 264780 | G17: =D17*F17 -> 0 | H17: PC FOOD | I17: Taj
B18: FLOUR T65 (25KG) | C18: Bag | E18: 19 | F18: =E18*9000 -> 171000 | G18: =D18*F18 -> 0 | H18: BAKALIAN | I18: T65
B19: CAPUTO FLOUR 5 KG | C19: Bag | E19: 22 | F19: =E19*9000 -> 198000 | G19: =D19*F19 -> 0 | H19: Interal | I19: Farina
B20: YEAST FRESH 0.5 KG | C20: PCS | E20: =2.25*1.1 -> 2.475 | F20: =E20*9000 -> 22275 | G20: =D20*F20 -> 0 | H20: AYA FOODS
B21: CHEESE ROLLS DOUGH | C21: PACK | E21: 1.5 | F21: =E21*9000 -> 13500 | G21: =D21*F21 -> 0 | H21: TONYS FOOD | I21: TONYS FOOD
B22: PAIN DE MIE 12mm FRAIS | C22: Loaf | E22: =(14.49/2)*1.1 -> 7.9695 | F22: =E22*9000 -> 71725.5 | G22: =D22*F22 -> 0 | H22: Delifrance | I22: Delifrance
B23: PAIN DE MIE 12mm | C23: Loaf | E23: =1.1*7.59 -> 8.349 | F23: =E23*9000 -> 75141 | G23: =D23*F23 -> 0 | H23: Delifrance
B24: PAIN CAMPAGNE RUSTIQUE (4x650GRSx18S) | C24: Loaf | E24: =13.8*1.1 -> 15.18 | F24: =E24*9000 -> 136620 | G24: =D24*F24 -> 0 | H24: Delifrance
B25: PAIN AU LAIT FRAIS 12 PCS | C25: Loaf | E25: =2.1*1.1 -> 2.31 | F25: =E25*9000 -> 20790 | G25: =D25*F25 -> 0 | H25: Delifrance
B26: PUFF PASTRY KG 12*400G | C26: BOX | E26: =25*1.1 -> 27.5 | F26: =E26*9000 -> 247500 | G26: =D26*F26 -> 0 | H26: PLEIN SOLIEL | I26: PLEIN SOLIEL
B27: SUBMARINE BUN 5 PCS | C27: BAG | E27: 3.3 | F27: =E27*9000 -> 29700 | G27: =D27*F27 -> 0 | H27: Delifrance | I27: Delifrance
B28: TORTILLA 6" CORN 12 KG | C28: Box | E28: 65 | F28: =E28*9000 -> 585000 | G28: =D28*F28 -> 0 | H28: POMO | I28: POMO
B29: TORTILLA 6" FLOUR 12 KG | C29: Box | E29: 65 | F29: =E29*9000 -> 585000 | G29: =D29*F29 -> 0 | H29: POMO | I29: POMO
B30: TORTILLA 12" FLOUR 12 KG | C30: Box | E30: 60 | F30: =E30*9000 -> 540000 | G30: =D30*F30 -> 0 | H30: POMO | I30: POMO
B31: CANNED | F31: =E31*9000 -> 0
B32: ANCHOIX 80 GR KG | C32: PCS | E32: =3.75*1.1 -> 4.125 | F32: =E32*9000 -> 37125 | G32: =F32*D32 -> 0 | H32: GENERAL PROMOTION | I32: Robo
B33: CORN FLOWER 340 gr | C33: PCS | E33: 2.5 | F33: =E33*9000 -> 22500 | G33: =F33*D33 -> 0 | H33: PC FOODS | I33: DOMO
B34: ARTICHAUT 390 GR | C34: PCS | E34: 4.2 | F34: =E34*9000 -> 37800 | G34: =F34*D34 -> 0
B35: CHEDDAR DIP KG (3.01KG) | C35: PCS | E35: =11*1.1 -> 12.1 | F35: =E35*9000 -> 108900 | G35: =F35*D35 -> 0 | H35: AYA FOODS
B36: CAPERS KG 950 GRS | C36: Box | E36: =9.5*1.1 -> 10.45 | F36: =E36*9000 -> 94050 | G36: =F36*D36 -> 0 | H36: GENERAL PROMOTION | I36: MARLY
B37: DEMI GLASS (0.925 KG) | C37: PCS | E37: =26*1.1 -> 28.6 | F37: =E37*9000 -> 257400 | G37: =F37*D37 -> 0 | H37: AYA FOODS | I37: KNORR
B38: CONDENSED MILK KG (395GR) | C38: PCS | E38: 0.98 | F38: =E38*9000 -> 8820 | G38: =F38*D38 -> 0 | H38: PC FOODS | I38: Nestle
B39: PEANUT BUTTER 340 GRS | C39: PCS | E39: =1.3*1.1 -> 1.43 | F39: =E39*9000 -> 12870 | G39: =F39*D39 -> 0 | H39: GENERAL PROMOTION | I39: PNUT
B40: JALAPENOS KG (2KG) | C40: PCS | E40: =6.5*1.1 -> 7.15 | F40: =E40*9000 -> 64350 | G40: =F40*D40 -> 0 | H40: AYA FOODS
B41: JUNAL LEMON 1 L *16 | C41: Box | E41: =1.5*1.1 -> 1.65 | F41: =E41*9000 -> 14850 | G41: =F41*D41 -> 0 | H41: U FOOD | I41: Junal
B42: MAGGI CUBES CHICKEN 2.16KG | C42: Pack | E42: =2.5*1.1 -> 2.75 | F42: =E42*9000 -> 24750 | G42: =F42*D42 -> 0 | H42: AYA FOODS | I42: Maggi
B43: OLIVE OIL 13KG | C43: Gallon | E43: 55 | F43: =E43*9000 -> 495000 | G43: =F43*D43 -> 0 | H43: Asaad | I43: Asaad
B44: OLIVES BLACK SLICED 10 KG | C44: KG | E44: 26 | F44: =E44*9000 -> 234000 | G44: =F44*D44 -> 0 | H44: MAISON KOZAILY | I44: MAISON KOZAILY
B45: OLIVES BLACK WHOLE KG | C45: KG | E45: 4 | F45: =E45*9000 -> 36000 | G45: =F45*D45 -> 0 | H45: Asaad | I45: Asaad
B46: PEELED TOMATO 3 kg *6 | C46: PCS | E46: =9*1.1 -> 9.9 | F46: =E46*9000 -> 89100 | G46: =F46*D46 -> 0 | H46: AYA FOODS
B47: PIZZA SAUCE 2.55 Kg * 6 | C47: PCS | E47: =5*1.1 -> 5.5 | F47: =E47*9000 -> 49500 | G47: =F47*D47 -> 0 | H47: AYA FOODS
B48: COOKING SPRAY VEGI OIL | C48: PCS | F48: =E48*9000 -> 0 | G48: =F48*D48 -> 0 | H48: MANY FOOD | I48: SHOPRITE
B49: PICKLES KG*10 | C49: Gallon | E49: 15 | F49: =E49*9000 -> 135000 | G49: =F49*D49 -> 0 | H49: MAISON KOZAILY | I49: MAISON KOZAILY
B50: REB EL 7AR KG | C50: KG | E50: 3 | F50: =E50*9000 -> 27000 | G50: =F50*D50 -> 0 | H50: MAISON KOZAILY | I50: MAISON KOZAILY
B51: HONEY ORANGE SPRING 800 GRS | C51: JAR | E51: =2.5*1.1 -> 2.75 | F51: =E51*9000 -> 24750 | G51: =F51*D51 -> 0 | H51: AYA FOODS | I51: KOUROM
B52: STEAK SAUCE (3.79 LT * 4) | C52: PCS | E52: =1.1*14.5 -> 15.95 | F52: =E52*9000 -> 143550 | G52: =F52*D52 -> 0 | H52: GENERAL PROMOTION | I52: MIRINA
B53: SRIRACHA SAUCE 440 ML | C53: PCS | E53: =3.9*1.1 -> 4.29 | F53: =E53*9000 -> 38610 | G53: =F53*D53 -> 0 | H53: GENERAL PROMOTION | I53: THAIGER
B54: SHORTENING OIL CREAMY 18 L | C54: Gallon | E54: 41 | F54: =E54*9000 -> 369000 | G54: =F54*D54 -> 0 | H54: WAFIC IDRISS | I54: OKI
B55: SHORTENING OIL CLEAR 18 L | C55: Gallon | E55: 54 | F55: =E55*9000 -> 486000 | G55: =F55*D55 -> 0 | H55: GENERAL PROMOTION | I55: AMERICAN
B56: POMI TOMATO PASTE 1000 GR | C56: PCS | E56: =2.25*1.1 -> 2.475 | F56: =E56*9000 -> 22275 | G56: =F56*D56 -> 0 | H56: AYA FOODS | I56: POMI
B57: SUNFLOWER OIL 8L | C57: Gallon | E57: =(7.5*1.1)*2 -> 16.5 | F57: =E57*9000 -> 148500 | G57: =F57*D57 -> 0 | H57: UNITED FISHERIES | I57: OCEAN GARDENS
B58: LIQUID SMOKE | C58: Gallon | E58: 12 | F58: =E58*9000 -> 108000 | G58: =F58*D58 -> 0 | H58: UAE - DUABI | I58: KENS
B59: BLACK BEANS CAN 15OZ | C59: CAN | E59: =2.5*1.1 -> 2.75 | F59: =E59*9000 -> 24750 | G59: =F59*D59 -> 0 | H59: AYA FOODS
B60: SWEET CORN KG 340 GRS | C60: PCS | E60: =1*1.1 -> 1.1 | F60: =E60*9000 -> 9900 | G60: =F60*D60 -> 0 | H60: UNITED FISHERIES | I60: OCEAN GARDENS
B61: TAHINE 5 KG | C61: Tin | E61: 25 | F61: =E61*9000 -> 225000 | G61: =F61*D61 -> 0 | H61: BISAT | I61: BISAT
B62: TOMATO PASTE KG (1.25KG) 6 | C62: BOX | E62: =4.25*1.1 -> 4.675 | F62: =E62*9000 -> 42075 | G62: =F62*D62 -> 0 | H62: AMIN AOUR | I62: Tawoos
B63: FOUL & CHICK PEAS 400 GRS | C63: CAN | E63: 0.99 | F63: =E63*9000 -> 8910 | G63: =F63*D63 -> 0 | H63: FATTAL | I63: CALIFORNIA GARDENS
B64: CHICK PEAS 400 GRS | C64: CAN | E64: 1.08 | F64: =E64*9000 -> 9720 | G64: =F64*D64 -> 0 | H64: FATTAL | I64: CALIFORNIA GARDENS
B65: TUNA CANNED 200 GRS * 48 | C65: Box | E65: =1*1.1 -> 1.1 | F65: =E65*9000 -> 9900 | G65: =F65*D65 -> 0 | H65: UNITED FISHERIES | I65: CAPTIN FISHER
B66: AROM PATRELLE 1 L | C66: KG | E66: =42*1.1 -> 46.2 | F66: =E66*9000 -> 415800 | G66: =F66*D66 -> 0 | H66: AYA FOODS
B67: FROZEN | F67: =E67*9000 -> 0
B68: FRENCH FRIES 9X9 KG | C68: Box | E68: 21.85 | F68: =E68*9000 -> 196650 | G68: =F68*D68 -> 0 | H68: Marina Frozen | I68: Super Fries
B69: WEDGES KG | C69: Box | E69: 21.85 | F69: =E69*9000 -> 196650 | G69: =F69*D69 -> 0 | H69: Marina Frozen | I69: Super Fries
B70: TWISTER FRIES 2.5 KG*4 | C70: Box | E70: =49.6*1.1 -> 54.56 | F70: =E70*9000 -> 491040 | G70: =F70*D70 -> 0 | H70: AYA FOODS | I70: Lamb Western
B71: CRISS CUT 2.5 KG*5 | C71: Box | E71: =49.6*1.1 -> 54.56 | F71: =E71*9000 -> 491040 | G71: =F71*D71 -> 0 | H71: AYA FOODS | I71: Lamb Western
B72: BURGER 130 GR 15.6 KGS (D) | C72: Box | E72: =133/15.6 -> 8.525641 | F72: =E72*9000 -> 76730.769 | G72: =F72*D72 -> 0 | H72: DEKERCO
B73: BURGER 170 GR - | C73: PCS | E73: 10 | F73: =E73*9000 -> 90000 | G73: =F73*D73 -> 0 | H73: DEKERCO
B74: EDAMAME 400 GR | C74: PCS | E74: 3.01 | F74: =E74*9000 -> 27090 | G74: =F74*D74 -> 0
B75: STRAWBERRY FROZEN 10 KG | C75: Box | E75: 20 | F75: =E75*9000 -> 180000 | G75: =F75*D75 -> 0 | H75: E. JABRA
B76: DAIRY | F76: =E76*9000 -> 0 | H76: E. JABRA
B77: GOAT CHEESE KG | C77: Kg | E77: 15.7 | F77: =E77*9000 -> 141300 | G77: =F77*D77 -> 0 | H77: AYA FOODS
B78: BLUE CHEESE 3.14 KG | C78: Kg | E78: 13 | F78: =E78*9000 -> 117000 | G78: =F78*D78 -> 0 | H78: AYA FOODS | I78: CASTELLO
B79: BUTTER 25KG | C79: BLOCK | E79: 39 | F79: =E79*9000 -> 351000 | G79: =F79*D79 -> 0 | H79: ZAKHER | I79: COULEUR FONCEE
B80: CHEDDAR CHEESE YELLOW BLOCK (5KG) | C80: KG | E80: 11.5 | F80: =E80*9000 -> 103500 | G80: =F80*D80 -> 0 | H80: ZAKHER | I80: COULEUR FONCEE
B81: CHEDDAR SLICED 200 GR | C81: PCS | E81: 1.9 | F81: =E81*9000 -> 17100 | G81: =F81*D81 -> 0 | H81: AYA FOODS | I81: Happy Cow
B82: AKKAWI CHEESE SHREDDED 2 KG | C82: KG | E82: 7 | F82: =E82*9000 -> 63000 | G82: =F82*D82 -> 0 | H82: HOSPI
B83: CREAM SPRAY 250 GRS | C83: PCS | E83: =3*1.1 -> 3.3 | F83: =E83*9000 -> 29700 | G83: =F83*D83 -> 0 | H83: AYA FOODS | I83: Roselle
B84: EGGS 30PCS | C84: PCS | E84: 4.33 | F84: =E84*9000 -> 38970 | G84: =F84*D84 -> 0 | H84: HAWA CHICKEN | I84: Egg
B85: EMMENTAL CHEESE 2.78 $/KG | C85: KG | E85: 14.35 | F85: =E85*9000 -> 129150 | G85: =F85*D85 -> 0 | H85: ZAKHER | I85: GRAND'OR
B86: FETTA CHEESE 1 KG | C86: KG | E86: 4.95 | F86: =E86*9000 -> 44550 | G86: =F86*D86 -> 0 | H86: CHTAURA | I86: Flechard
B87: FRESH CREAM MATILDE 1 KG*12 | C87: PCS | E87: =6.5 -> 6.5 | F87: =E87*9000 -> 58500 | G87: =F87*D87 -> 0 | H87: AMINE AOUR | I87: CRISTIS
B88: FRESH CREAM MATILDE 1 KG*13 | C88: PCS | E88: =4.1*1.1 -> 4.51 | F88: =E88*9000 -> 40590 | G88: =F88*D88 -> 0 | H88: ZAKHER | I88: MARTINI
B89: NABOLSIYE CHEESE 1 KG | C89: KG | E89: 11.11 | F89: =E89*9000 -> 99990 | G89: =F89*D89 -> 0 | H89: JEDITA | I89: JEDITA
B90: HALLOUM CHEESE | C90: KG | E90: 12 | F90: =E90*9000 -> 108000 | G90: =F90*D90 -> 0 | H90: JEDITA | I90: JEDITA
B91: MOZZARELLA FRESH CERISES KG | C91: KG | E91: =3.33*4 -> 13.32 | F91: =E91*9000 -> 119880 | G91: =F91*D91 -> 0 | H91: FATTORIA TRADE | I91: FATTORIA TRADE
B92: BURRATA CHEESE KG | C92: KG | E92: =6.6*4 -> 26.4 | F92: =E92*9000 -> 237600 | G92: =F92*D92 -> 0 | H92: U FOOD | I92: GRANAROLO
B93: BUFALA CHEESE KG | C93: KG | E93: =3.08*4 -> 12.32 | F93: =E93*9000 -> 110880 | G93: =F93*D93 -> 0 | H93: FATTORIA TRADE | I93: FATTORIA TRADE
B94: LABAN 2 KG | C94: Kg | E94: 3 | F94: =E94*9000 -> 27000 | G94: =F94*D94 -> 0 | H94: JEDITA | I94: JEDITA
B95: LABNEH 5KG | C95: PAIL | E95: 15 | F95: =E95*9000 -> 135000 | G95: =F95*D95 -> 0 | H95: JEDITA | I95: JEDITA
B96: MILK 12 L | C96: BOX | E96: 1.45 | F96: =E96*9000 -> 13050 | G96: =F96*D96 -> 0 | H96: CANDIA | I96: CANDIA
B97: MOZZARELLA BLOCK 18.4 KG PIZZA | C97: KG | E97: 11.25 | F97: =E97*9000 -> 101250 | G97: =F97*D97 -> 0 | H97: U FOOD
B98: MOZZARELLA BLOCK 18.4 KG STICKS | C98: KG | E98: 8.5 | F98: =E98*9000 -> 76500 | G98: =F98*D98 -> 0 | H98: AYA FOODS | I98: 3 COWS
B99: MOZZARELLA SHREDDED 12 KG | C99: BOX | E99: =7*12 -> 84 | F99: =E99*9000 -> 756000 | G99: =F99*D99 -> 0 | H99: AYA FOODS | I99: SUPRANO
B100: MOZZARELLA SHREDDED 12 KG | C100: BOX | E100: 67 | F100: =E100*9000 -> 603000 | G100: =F100*D100 -> 0 | H100: WALID KAYROUZ | I100: MASTERLLA
...

Sheet SAUCES
A1: Caesar Sauce | B1: 8.6 | C1: KG | D1: =D15/B1 -> 75709.953 | E1: =D1/90000 -> 0.8412217 | I1: Lemon Mustard | J1: 9.12 | K1: KG | L1: =L15/J1 -> 13999.178 | M1: =L1/90000 -> 0.15554642
A2: Name | B2: Qty | C2: Unit Price | D2: Total Cost | I2: Name | J2: Qty | K2: Unit Price | L2: Total Cost
A3: Anchoix | B3: 2 | C3: ='F&B'!$F$32 -> 37125 | D3: =B3*C3 -> 74250 | I3: Djion Mustard | J3: 1.25 | K3: =$C$9 -> 51480 | L3: =J3*K3 -> 64350
A4: Mayonnaise | B4: 4 | C4: ='F&B'!$F$250 -> 108900 | D4: =B4*C4 -> 435600 | I4: Sunflower Oil | J4: 5 | K4: ='F&B'!$F$57/18 -> 8250 | L4: =J4*K4 -> 41250
A5: Fresh Cream | B5: 1 | C5: ='F&B'!$F$87 -> 58500 | D5: =B5*C5 -> 58500 | I5: Salt | J5: 0.1 | K5: =$C$11 -> 58500 | L5: =J5*K5 -> 5850
A6: Parmesan Cheese | B6: 0.2 | C6: ='F&B'!$F$103 -> 148500 | D6: =B6*C6 -> 29700
A7: Garlic | B7: 0.2 | C7: ='F&B'!$F$292 -> 19800 | D7: =B7*C7 -> 3960 | I7: Lemon Juice | J7: 1.25 | K7: ='F&B'!$F$287*1.5 -> 12150 | L7: =J7*K7 -> 15187.5
A8: Worchester Sauce | B8: 0.2 | C8: ='F&B'!$F$260/3.8 -> 41684.211 | D8: =B8*C8 -> 8336.8421 | I8: Water | J8: 1.5 | L8: =J8*K8 -> 0
A9: Mustard Dijon | B9: 0.25 | C9: ='F&B'!$F$247/5 -> 51480 | D9: =B9*C9 -> 12870 | I9: Black Pepper | J9: 0.02 | K9: =C12 -> 51750 | L9: =J9*K9 -> 1035
A10: Milk | B10: 0.5 | C10: ='F&B'!$F$96 -> 13050 | D10: =B10*C10 -> 6525
A11: Salt | B11: 0.25 | C11: ='F&B'!$F$143 -> 58500 | D11: =B11*C11 -> 14625
A12: Black Pepper | B12: 0.005 | C12: ='F&B'!$F$148 -> 51750 | D12: =B12*C12 -> 258.75
A13: Lemon Juice | B13: 0.4 | C13: ='F&B'!F287*2 -> 16200 | D13: =B13*C13 -> 6480
D14: =B14*C14 -> 0
A15: TOTAL | D15: =SUM(D3:D14) -> 651105.59 | I15: TOTAL | L15: =IF(SUM(L3:L14)=0,"",SUM(L3:L14)) -> 127672.5
A16: Selling Price 45 Grs | B16: =IF(D16="","",IF(ISBLANK(C16),"",D16/C16)) -> 0.11748096 | C16: 29000 | D16: =D1*0.045 -> 3406.9479 | I16: Selling Price 45 Grs | J16: =IF(L16="","",IF(ISBLANK(K16),"",L16/K16)) -> 0.028634682 | K16: 22000 | L16: =L1*0.045 -> 629.96299
A20: Cocktail Sauce | B20: 4.7 | C20: KG | D20: =D33/B20 -> 26573.761 | E20: =D20/90000 -> 0.29526401 | I20: Garlic Dip | J20: 1.2 | K20: KG | L20: =L33/J20 -> 10676.625
A21: Name | B21: Qty | C21: Unit Price | D21: Total Cost | I21: Name | J21: Qty | K21: Unit Price | L21: Total Cost
A22: Mayonnaise | B22: 1 | C22: =$C$4 -> 108900 | D22: =B22*C22 -> 108900 | I22: Garlic | J22: 0.1 | K22: =$C$7 -> 19800 | L22: =J22*K22 -> 1980
A23: Ketchup | B23: 0.5 | C23: ='F&B'!$F$249/13 -> 3946.1538 | D23: =B23*C23 -> 1973.0769 | I23: Egg | J23: 1 | K23: ='F&B'!$F$84/30 -> 1299 | L23: =J23*K23 -> 1299
A24: Salt | B24: 0.007 | C24: =C11 -> 58500 | D24: =B24*C24 -> 409.5 | I24: Salt | J24: 0.001 | K24: =C11 -> 58500 | L24: =J24*K24 -> 58.5
A25: White Pepper | B25: 0.001 | C25: ='F&B'!$F$172 -> 89820 | D25: =B25*C25 -> 89.82 | I25: Sunflower Oil | J25: 1 | K25: =$K$4 -> 8250 | L25: =J25*K25 -> 8250
A26: Tabasco | B26: 0.006 | C26: ='F&B'!$F$253 -> 24750 | D26: =B26*C26 -> 148.5 | I26: Lemon Juice | J26: 0.075 | K26: =$K$7 -> 12150 | L26: =J26*K26 -> 911.25
A27: Worcestershire Sauce | B27: 0.025 | C27: =C8 -> 41684.211 | D27: =B27*C27 -> 1042.1053 | I27: Lamoud Layoun | J27: 0.04 | K27: ='F&B'!$F$161 -> 7830 | L27: =J27*K27 -> 313.2
A28: Water | B28: 0.1 | D28: =B28*C28 -> 0
A29: Lousiana Wings Sauce | B29: 0.12 | C29: ='F&B'!$F$258/3.75 -> 55440 | D29: =B29*C29 -> 6652.8
A30: Junal | B30: 0.08 | C30: ='F&B'!$F$41 -> 14850 | D30: =B30*C30 -> 1188
A31: BBQ | B31: 0.08 | C31: ='F&B'!$F$246/3.79 -> 56160.95 | D31: =B31*C31 -> 4492.876
A32: American Mustard | B32: 0.1
A33: TOTAL | D33: =IF(SUM(D22:D32)=0,"",SUM(D22:D32)) -> 124896.68 | I33: TOTAL | L33: =IF(SUM(L22:L32)=0,"",SUM(L22:L32)) -> 12811.95
A34: Selling Price 45 Grs | B34: =IF(D34="","",IF(ISBLANK(C34),"",D34/C34)) -> 0.04783277 | C34: 25000 | D34: =D20*0.045 -> 1195.8193 | I34: Selling Price 45 Grs | J34: =IF(L34="","",IF(ISBLANK(K34),"",L34/K34)) -> 0.032029875 | K34: 15000 | L34: =L20*0.045 -> 480.44813
A36: Balsamic Sauce | B36: 0.826 | C36: KG | D36: =D45/B36 -> 21446.564 | E36: =D36/90000 -> 0.23829515 | I36: Garnish
A37: Name | B37: Qty | C37: Unit Price | D37: Total Cost | I37: Name | J37: Qty | K37: Unit Price | L37: Total Cost
A38: Dijon Mustard | B38: 0.04 | C38: =K3 -> 51480 | D38: =B38*C38 -> 2059.2 | I38: Pickles | J38: 0.002 | K38: ='F&B'!$F$49 -> 135000 | L38: =J38*K38 -> 270
A39: Sunflower Oil | B39: 0.215 | C39: =K25 -> 8250 | D39: =B39*C39 -> 1773.75 | I39: Lolo Lettuce | J39: 0.01 | K39: ='F&B'!F297 -> 16650 | L39: =J39*K39 -> 166.5
A40: Balsamic Vinegar | B40: 0.13 | C40: ='F&B'!$F$255/5 -> 35640 | D40: =B40*C40 -> 4633.2 | I40: Tomato | J40: 0.06 | K40: ='F&B'!$F$279 -> 7200 | L40: =J40*K40 -> 432
A41: Olive Oil | B41: 0.24 | C41: ='F&B'!$F$43/13 -> 38076.923 | D41: =B41*C41 -> 9138.4615 | I41: Onion | J41: 0.02 | K41: ='F&B'!$F$290 -> 6300 | L41: =J41*K41 -> 126
A42: Salt | B42: 0.001 | C42: =K24 -> 58500 | D42: =B42*C42 -> 58.5
A43: Black Pepper | B43: 0.001 | C43: =K9 -> 51750 | D43: =B43*C43 -> 51.75
A44: Water | B44: 0.2
A45: TOTAL | D45: =IF(SUM(D38:D44)=0,"",SUM(D38:D44)) -> 17714.862 | I45: TOTAL | L45: =SUM(L38:L44) -> 994.5
A46: Selling Price 45 Grs | B46: =IF(D46="","",IF(ISBLANK(C46),"",D46/C46)) -> 0.043867971 | C46: 22000 | D46: =D36*0.045 -> 965.09536
A48: Breaded | B48: 100 | C48: PCS | D48: =D57/B48 -> 563.76 | E48: 1 | I48: Coleslaw | J48: 6 | K48: KG | L48: =L57/J48 -> 20516.64 | M48: =L48/90000 -> 0.22796267
A49: Name | B49: Qty | C49: Unit Price | D49: Total Cost | I49: Name | J49: Qty | K49: Unit Price | L49: Total Cost
A50: Flour | B50: 0.5 | C50: ='F&B'!$F$17/50 -> 5295.6 | D50: =B50*C50 -> 2647.8 | E50: =$E$48*B50/$B$48 -> 0.005 | I50: Cabbage | J50: 2 | K50: ='F&B'!$F$294 -> 6750 | L50: =J50*K50 -> 13500
A51: Eggs | B51: 15 | C51: =$K$23 -> 1299 | D51: =B51*C51 -> 19485 | E51: =$E$48*B51/$B$48 -> 0.15 | I51: Carrot | J51: 0.1 | K51: ='F&B'!F293 -> 6750 | L51: =J51*K51 -> 675
A52: Panco | B52: 1 | C52: ='F&B'!$F$7 -> 18000 | D52: =B52*C52 -> 18000 | E52: =$E$48*B52/$B$48 -> 0.01 | I52: Mayonnaise | J52: 1 | K52: =$C$4 -> 108900 | L52: =J52*K52 -> 108900
A53: Salt | B53: 0.02 | C53: =C42 -> 58500 | D53: =B53*C53 -> 1170 | E53: =$E$48*B53/$B$48 -> 0.0002 | I53: Sugar | J53: 0.003 | K53: ='F&B'!$F$145 -> 8280 | L53: =J53*K53 -> 24.84
A54: White Pepper | B54: 0.01 | C54: =$C$25 -> 89820 | D54: =B54*C54 -> 898.2 | E54: =$E$48*B54/$B$48 -> 0.0001 | I54: Red Cabbage | J54: 0.2
A55: Milk | B55: 1 | C55: ='F&B'!$F$96 -> 13050 | D55: =B55*C55 -> 13050 | E55: =$E$48*B55/$B$48 -> 0.01
A56: White Vinegar | B56: 0.125 | C56: ='F&B'!$F$256 -> 9000 | D56: =B56*C56 -> 1125 | E56: =$E$48*B56/$B$48 -> 0.00125
A57: TOTAL | D57: =IF(SUM(D50:D56)=0,"",SUM(D50:D56)) -> 56376 | E57: =$E$48*B57/$B$48 -> 0 | I57: TOTAL | L57: =SUM(L50:L56) -> 123099.84
I58: Selling Price 45 Grs | J58: =IF(L58="","",IF(ISBLANK(K58),"",L58/K58)) -> 0.041965855 | K58: 22000 | L58: =L48*0.045 -> 923.2488
A60: Green Salad | I60: Pizza Sauce | J60: 7.75 | K60: KG | L60: =L68/J60 -> 19698.45 | M60: =L60/90000 -> 0.21887166
A61: Name | B61: Qty | C61: Unit Price | D61: Total Cost | I61: Name | J61: Qty | K61: Unit Price | L61: Total Cost
A62: Argula | B62: 0.25 | C62: ='F&B'!F302 -> 10800 | D62: =B62*C62 -> 2700 | I62: Peeled Tomato 3 KG | J62: 3 | K62: ='F&B'!$F$46 -> 89100 | L62: =K62 -> 89100
A63: Cherry Tomato | B63: 0.001 | C63: ='F&B'!F283 -> 9000 | D63: =B63*C63 -> 9 | I63: Tomato Sauce 2.55 KG | J63: 2.55 | K63: ='F&B'!$F$47 -> 49500 | L63: =K63 -> 49500
A64: Lemon Sauce | B64: 0.02 | C64: =L122 -> 28970.238 | D64: =B64*C64 -> 579.40477 | I64: Basil Fresh | J64: 2 | K64: ='F&B'!$F$298 -> 2970 | L64: =J64*K64 -> 5940
A65: Rocket | B65: 0.01 | C65: ='F&B'!F280 -> 2970 | D65: =B65*C65 -> 29.7 | I65: Olive Oil | J65: 0.2 | K65: ='F&B'!F43/13 -> 38076.923 | L65: =J65*K65 -> 7615.3846
A66: Red Cabbage | B66: 0.1 | C66: ='F&B'!F295 -> 4500 | D66: =B66*C66 -> 450 | I66: White Pepper | J66: 0.005 | K66: =C54 -> 89820 | L66: =J66*K66 -> 449.1
I67: Salt | J67: 0.001 | K67: =C53 -> 58500 | L67: =J67*K67 -> 58.5
A68: TOTAL | D68: =IF(SUM(D62:D67)=0,"",SUM(D62:D67)) -> 3768.1048 | I68: TOTAL | L68: =IF(SUM(L62:L67)=0,"",SUM(L62:L67)) -> 152662.98
A70: Honey Citrus | C70: KG | D70: =D79/B70 -> #DIV/0! | I70: Lemon Mayo | J70: 3.81 | K70: KG | L70: =L76/J70 -> 28957.087 | M70: =L70/90000 -> 0.32174541
A71: Name | B71: Qty | C71: Unit Price | D71: Total Cost | I71: Name | J71: Qty | K71: Unit Price | L71: Total Cost
A72: Mustard Dijon | C72: =$K$3 -> 51480 | D72: =B72*C72 -> 0 | I72: Mayonnaise | J72: 1 | K72: =K52 -> 108900 | L72: =J72*K72 -> 108900
A73: Lime Juice | C73: ='F&B'!#REF! -> #ERROR! | I73: Lemon Juice | J73: 0.04 | K73: ='F&B'!F287 -> 8100 | L73: =J73*K73 -> 324
A74: Sunflower Oil | C74: =C39 -> 8250 | D74: =B74*C74 -> 0 | I74: Black Pepper | J74: 0.01 | K74: ='F&B'!F148 -> 51750 | L74: =J74*K74 -> 517.5
A75: Water | C75: 0 | I75: Salt | J75: 0.01 | K75: =C53 -> 58500 | L75: =J75*K75 -> 585
A76: Paprika | C76: ='F&B'!$F$168 -> 42300 | I76: TOTAL | L76: =IF(SUM(L72:L75)=0,"",SUM(L72:L75)) -> 110326.5
A77: Dry Coriander | C77: ='F&B'!$F$177 -> 33075 | I77: Selling Price 45 Grs | J77: =IF(L77="","",IF(ISBLANK(K77),"",L77/K77)) -> 0.052122756 | K77: 25000 | L77: =L70*0.045 -> 1303.0689
A78: Cajun Spices | C78: ='F&B'!F188 -> 47250
A79: TOTAL | D79: =IF(SUM(D72:D78)=0,"",SUM(D72:D78)) | I79: Mushroom Sauce | J79: =SUM(J81:J89) -> 11.082 | K79: KG | L79: =L91/J79 -> 55154.894 | M79: =L79/90000 -> 0.61283216
A80: Selling Price 45 Grs | B80: =IF(D80="","",IF(ISBLANK(C80),"",D80/C80)) -> #DIV/0! | C80: 40000 | D80: =D70*0.045 -> #DIV/0! | I80: Name | J80: Qty | K80: Unit Price | L80: Total Cost
I81: Fresh Cream | J81: 6 | K81: ='F&B'!$F$87 -> 58500 | L81: =J81*K81 -> 351000
A82: Dough | B82: 7.92 | C82: KG | D82: =D91/B82 -> 6006.1538 | E82: =D82/90000 -> 0.066735043 | I82: Fresh Mushroom | J82: 1 | K82: ='F&B'!$F$278 -> 103500 | L82: =J82*K82 -> 103500
A83: Name | B83: Qty | C83: Unit Price | D83: Total Cost | I83: Butter | J83: 0.08 | K83: ='F&B'!$F$79/25 -> 14040 | L83: =J83*K83 -> 1123.2
A84: Flour T65 | B84: 5 | C84: ='F&B'!$F$18/25 -> 6840 | D84: =B84*C84 -> 34200 | I84: Crafts | J84: 0.1 | K84: ='F&B'!$F$310 -> 15030 | L84: =J84*K84 -> 1503
A85: Sunflower Oil | B85: 0.15 | C85: =K4 -> 8250 | D85: =B85*C85 -> 1237.5 | I85: Corn Strach | J85: 0.1 | K85: ='F&B'!$F$33 -> 22500 | L85: =J85*K85 -> 2250
A86: Salt | B86: 0.1 | C86: =K67 -> 58500 | D86: =B86*C86 -> 5850 | I86: Black Pepper | J86: 0.01 | K86: =$C$12 -> 51750 | L86: =J86*K86 -> 517.5
A87: Sugar | B87: 0.015 | C87: =K53 -> 8280 | D87: =B87*C87 -> 124.2 | I87: Salt | J87: 0.03 | K87: =C86 -> 58500 | L87: =J87*K87 -> 1755
A88: Yeast | B88: 0.02 | C88: ='F&B'!$F$20 -> 22275 | D88: =B88*C88 -> 445.5 | I88: White Pepper | J88: 0.012 | K88: =C54 -> 89820 | L88: =J88*K88 -> 1077.84
A89: Water | B89: 2.5 | D89: =B89*C89 -> 0 | I89: Water | J89: 3.75 | L89: =J89*K89 -> 0
A90: Olive Oil | B90: 0.15 | C90: =K65 -> 38076.923 | D90: =B90*C90 -> 5711.5385 | I90: Chicken Cubes | J90: 6 | K90: ='F&B'!$F$42 -> 24750 | L90: =J90*K90 -> 148500
A91: TOTAL | D91: =IF(SUM(D84:D90)=0,"",SUM(D84:D90)) -> 47568.738 | I91: TOTAL | L91: =IF(SUM(L81:L90)=0,"",SUM(L81:L90)) -> 611226.54
A92: Selling Price 45 Grs | B92: =IF(D92="","",IF(ISBLANK(C92),"",D92/C92)) -> 0.022523077 | C92: 40000 | D92: =D82*0.15 -> 900.92308 | I92: Selling Price 45 Grs | J92: =IF(L92="","",IF(ISBLANK(K92),"",L92/K92)) -> 0.027577447 | K92: =1*90000 -> 90000 | L92: =L79*0.045 -> 2481.9702
K93: 1
A95: Sour Cream | B95: 1.493 | C95: KG | D95: =D104/B95 -> 59148.024 | E95: =D95/90000 -> 0.65720027 | I95: Mexican | J95: 3.91 | K95: KG | L95: =L104/J95 -> 24243.146 | M95: =L95/90000 -> 0.26936829
A96: Name | B96: Qty | C96: Unit Price | D96: Total Cost | I96: Name | J96: Qty | K96: Unit Price | L96: Total Cost
A97: Fresh Cream | B97: 1 | C97: =$K$81 -> 58500 | D97: =B97*C97 -> 58500 | I97: Peeled Tomato 3 KG | J97: 1 | K97: =$K$62 -> 89100 | L97: =J97*K97 -> 89100
A98: Labneh | B98: 0.22 | C98: ='F&B'!$F$95/5 -> 27000 | D98: =B98*C98 -> 5940 | I98: Onions | J98: 0.3 | K98: ='F&B'!$F$290 -> 6300 | L98: =J98*K98 -> 1890
A99: Salt | B99: 0.02 | C99: =C86 -> 58500 | D99: =B99*C99 -> 1170 | I99: Green Peppers | J99: 0.06 | K99: ='F&B'!$F$296 -> 9000 | L99: =J99*K99 -> 540
A100: Lemon | B100: 0.25 | C100: ='F&B'!F287*1.5 -> 12150 | D100: =B99*C100 -> 243 | I100: Coriander | J100: 0.5 | K100: ='F&B'!$F$311 -> 2970 | L100: =J100*K100 -> 1485
A101: White Pepper | B101: 0.003 | C101: =$K$88 -> 89820 | D101: =B100*C101 -> 22455 | I101: Cummin Powder | J101: 0.01 | K101: ='F&B'!$F$158 -> 81000 | L101: =J101*K101 -> 810
D102: =B102*C102 -> 0 | I102: Red Chili Flakes | J102: 0.01 | K102: ='F&B'!$F$186 -> 52020 | L102: =J102*K102 -> 520.2
D103: =B101*C103 -> 0 | I103: Junal | J103: 0.03 | K103: ='F&B'!$F$41 -> 14850 | L103: =J103*K103 -> 445.5
A104: TOTAL | D104: =IF(SUM(D97:D103)=0,"",SUM(D97:D103)) -> 88308 | I104: TOTAL | L104: =IF(SUM(L97:L103)=0,"",SUM(L97:L103)) -> 94790.7
A105: Selling Price 45 Grs | B105: =IF(D105="","",IF(ISBLANK(C105),"",D105/C105)) -> 0.088722036 | C105: 30000 | D105: =D95*0.045 -> 2661.6611 | I105: Selling Price 45 Grs | J105: =IF(L105="","",IF(ISBLANK(K105),"",L105/K105)) -> 0.054547078 | K105: 20000 | L105: =L95*0.045 -> 1090.9416
A107: Garlic Butter | B107: 8.99 | C107: KG | D107: =D119/B107 -> 13438.658 | I107: Tartar | J107: 4.5 | K107: KG | L107: =L119/J107 -> 30314.179 | M107: =L107/90000 -> 0.33682421
A108: Name | B108: Qty | C108: Unit Price | D108: Total Cost | I108: Name | J108: Qty | K108: Unit Price | L108: Total Cost
A109: Butter | B109: 7 | C109: =K83 -> 14040 | D109: =B109*C109 -> 98280 | I109: Mayonnaise | J109: 1 | K109: =K72 -> 108900 | L109: =J109*K109 -> 108900
...

Sheet UTL COST
A1: UTILITY AND PREP. COST | C1: =#REF! -> #REF! | E1: Gas Count
A2: DEKWANEH | D2: Total Cost | E2: 10 KG | F2: Qty | G2: 35 KG | H2: Qty | I2: Total
A3: Shorenting Oil | B3: ='F&B'!$F$54 -> 369000 | C3: 0.0075 | D3: =B3*C3 -> 2767.5
A4: Gas | B4: =$I$4*($C$1) -> #REF! | C4: 7000 | D4: =B4/C4 -> #REF! | E4: 13 | F4: 10 | G4: 38 | H4: 30 | I4: =E4*F4+G4*H4 -> 1270
A5: Electricity | B5: =3260*C1 -> #REF! | C5: 45000 | D5: =B5/C5 -> #REF!
A6: Wood | B6: =180*C1 -> #REF! | C6: =350+175 -> 525 | D6: =B6/C6 -> #REF!
A7: Gas Pizza | B7: =I7*$C$1 -> #REF! | C7: 450 | D7: =B7/C7 -> #REF! | G7: 35 | H7: 4 | I7: =G7*H7 -> 140
A8: TOTAL | D8: =IF(SUM(D3:D6)=0,"",SUM(D3:D6)) -> #REF!
A9: Labor Cost | B9: 180000000 | C9: 22000 | D9: =B9/C9 -> 8181.8182

Sheet Prep
A1: Croutons | B1: 4 | C1: KG | D1: =D13/B1 -> 0 | G1: Sambousik | H1: 115 | I1: PCS | J1: =J13/H1 -> 1482.0651 | K1: =J1/#REF! -> #REF!
A2: Name | B2: Qty | C2: Unit Price | D2: Total Cost | G2: Name | H2: Qty | I2: Unit Price | J2: Total Cost
G3: Dough | H3: 1.5 | I3: =SAUCES!D82 -> 6006.1538 | J3: =I3*H3 -> 9009.2308
G4: Minced Beef | H4: 1.5 | I4: ='F&B'!F209 -> 99000 | J4: =I4*H4 -> 148500
G5: Onions | H5: 1.5 | I5: ='F&B'!F290 -> 6300 | J5: =I5*H5 -> 9450
G6: Label Cost | H6: =H1 -> 115 | I6: 400000 | J6: =I6/H6 -> 3478.2609
G7: Frying Oil | H7: 0.25 | I7: =C6 | J7: =H7*I7 -> 0
A13: TOTAL | D13: =IF(SUM(D3:D12)=0,"",SUM(D3:D12)) | G13: TOTAL | J13: =IF(SUM(J3:J12)=0,"",SUM(J3:J12)) -> 170437.49
A14: Selling Price 45 Grs | B14: =IF(D14="","",IF(ISBLANK(C14),"",D14/C14)) -> 0 | C14: 22000 | D14: =D1*0.045 -> 0 | G14: Selling Price 45 Grs | H14: =IF(J14="","",IF(ISBLANK(I14),"",J14/I14)) -> 0.0030314969 | I14: 22000 | J14: =J1*0.045 -> 66.692932
A17: Kibbeh Krass | B17: 240 | C17: PCS | D17: =D29/B17 -> 2246.7023 | E17: =D17/#REF! -> #REF! | G17: Cheese Rolls | H17: 115 | I17: PCS | J17: =J29/H17 -> 3103.3055 | K17: =J17/#REF! -> #REF!
A18: Name | B18: Qty | C18: Unit Price | D18: Total Cost | G18: Name | H18: Qty | I18: Unit Price | J18: Total Cost
A19: Minced Beef | B19: 5 | C19: =$I$4 -> 99000 | D19: =B19*C19 -> 495000 | G19: Akawi | H19: 0.6 | I19: ='F&B'!$F$82 -> 63000 | J19: =I19*H19 -> 37800
A20: Borghol | B20: 2.5 | C20: ='F&B'!F126 -> 11700 | D20: =B20*C20 -> 29250 | G20: Mozzarella | H20: 2 | I20: ='F&B'!$F$99/6 -> 126000 | J20: =I20*H20 -> 252000
A21: Onions | B21: 2 | C21: =$I$5 -> 6300 | D21: =B21*C21 -> 12600 | G21: Fetta | H21: 0.2 | I21: ='F&B'!$F$86 -> 44550 | J21: =I21*H21 -> 8910
A22: Label Cost | B22: =B17 -> 240 | C22: 400000 | D22: =C22/B22 -> 1666.6667 | G22: Rakaket Dough | H22: 4 | I22: ='F&B'!$F$21 -> 13500 | J22: =I22*H22 -> 54000
A23: Frying Oil | B23: 0.25 | C23: ='UTL COST'!D3 -> 2767.5 | D23: =B23*C23 -> 691.875 | G23: Label Cost | H23: =H17 -> 115 | I23: 400000 | J23: =I23/H23 -> 3478.2609
G24: Frying Oil | H24: 0.25 | I24: =C23 -> 2767.5 | J24: =H24*I24 -> 691.875
A29: TOTAL | D29: =IF(SUM(D19:D28)=0,"",SUM(D19:D28)) -> 539208.54 | G29: TOTAL | J29: =IF(SUM(J19:J28)=0,"",SUM(J19:J28)) -> 356880.14
A30: Selling Price 45 Grs | B30: =IF(D30="","",IF(ISBLANK(C30),"",D30/C30)) -> 0.0045955273 | C30: 22000 | D30: =D17*0.045 -> 101.1016 | G30: Selling Price 45 Grs | H30: =IF(J30="","",IF(ISBLANK(I30),"",J30/I30)) -> 0.0063476704 | I30: 22000 | J30: =J17*0.045 -> 139.64875
A32: Cheese Cake | B32: 8 | C32: PCS | D32: =D44/B32 -> 12991.335 | E32: =D32/#REF! -> #REF! | G32: Lahme Baajin | H32: 4.08 | I32: PCS | J32: =J44/H32 -> 30194.118
A33: Name | B33: Qty | C33: Unit Price | D33: Total Cost | G33: Name | H33: Qty | I33: Unit Price | J33: Total Cost
A34: Cream Cheese | B34: 0.55 | C34: ='F&B'!$F$101/8 -> 117450 | D34: =B34*C34 -> 64597.5 | G34: Minced Beef | H34: 1 | I34: ='F&B'!$F$209 -> 99000 | J34: =I34*H34 -> 99000
A35: Eggs | B35: 4 | C35: ='F&B'!$F$84/30 -> 1299 | D35: =B35*C35 -> 5196 | G35: Tomatoes | H35: 2 | I35: ='F&B'!$F$279 -> 7200 | J35: =I35*H35 -> 14400
A36: Sugar | B36: 0.3 | C36: ='F&B'!F145/50 -> 165.6 | D36: =B36*C36 -> 49.68 | G36: Onions | H36: 1 | I36: ='F&B'!$F$290 -> 6300 | J36: =I36*H36 -> 6300
A37: Cream Fresh | B37: 0.3 | C37: ='F&B'!$F$87 -> 58500 | D37: =B37*C37 -> 17550 | G37: Black Pepper | H37: 0.02 | I37: ='F&B'!$F$148 -> 51750 | J37: =I37*H37 -> 1035
A38: Vanilla Powder | B38: 0.05 | C38: ='F&B'!$F$178 -> 330750 | D38: =B38*C38 -> 16537.5 | G38: Debis El Roman | H38: 0.04 | I38: ='F&B'!$F$245 -> 32175 | J38: =I38*H38 -> 1287
G39: Salt | H39: 0.02 | I39: ='F&B'!$F$143 -> 58500 | J39: =I39*H39 -> 1170
A44: TOTAL | D44: =IF(SUM(D34:D43)=0,"",SUM(D34:D43)) -> 103930.68 | G44: TOTAL | J44: =IF(SUM(J34:J43)=0,"",SUM(J34:J43)) -> 123192
B45: =IF(D45="","",IF(ISBLANK(C45),"",D45/C45)) | G45: Selling Price 45 Grs | H45: =IF(J45="","",IF(ISBLANK(I45),"",J45/I45)) -> 0.061760695 | I45: 22000 | J45: =J32*0.045 -> 1358.7353
A48: Vine Leaves Ready | B48: 215 | C48: Grs | D48: =B48*C50/1000 -> 59985 | G48: Ajenet Knefe | H48: 14 | I48: PCS | J48: =J60/H48 -> #REF!
A49: Name | B49: Qty | C49: Unit Price | D49: Total Cost | G49: Name | H49: Qty | I49: Unit Price | J49: Total Cost
A50: Vine Leaves | B50: 4.06 | C50: 279000 | D50: =B50*C50 -> 1132740 | G50: Smid 1200kg | H50: 1.2 | I50: =1.3*#REF! -> #REF! | J50: =H50*I50 -> #REF! | K50: =J50/$J$60 -> #REF!
G51: Thin ferkha 160g | H51: 0.16 | I51: ='F&B'!$F$17/25 -> 10591.2 | J51: =H51*I51 -> 1694.592 | K51: =J51/$J$60 -> #REF!
G52: White sugar 400g | H52: 0.4 | I52: ='F&B'!$F$145/50 -> 165.6 | J52: =H52*I52 -> 66.24 | K52: =J52/$J$60 -> #REF!
G53: Misca 2 pcs | H53: 2 | I53: =0.02*#REF! -> #REF! | J53: =H53*I53 -> #REF! | K53: =J53/$J$60 -> #REF!
G54: Milk 3 liter | H54: 3 | I54: ='F&B'!$F$96 -> 13050 | J54: =H54*I54 -> 39150 | K54: =J54/$J$60 -> #REF!
G55: May zaher 50g | H55: 0.05 | I55: =0.4*#REF! -> #REF! | J55: =H55*I55 -> #REF! | K55: =J55/$J$60 -> #REF!
G56: May wared 30g | H56: 0.03 | I56: =0.4*#REF! -> #REF! | J56: =H56*I56 -> #REF! | K56: =J56/$J$60 -> #REF!
G57: Butter 400g | H57: 0.4 | I57: ='F&B'!$F$79/25 -> 14040 | J57: =H57*I57 -> 5616 | K57: =J57/$J$60 -> #REF!
A60: TOTAL | D60: =IF(SUM(D50:D59)=0,"",SUM(D50:D59)) -> 1132740 | G60: TOTAL | J60: =IF(SUM(J50:J59)=0,"",SUM(J50:J59)) -> #REF!
B61: =IF(D61="","",IF(ISBLANK(C61),"",D61/C61)) | G61: Selling Price 45 Grs | H61: =IF(J61="","",IF(ISBLANK(I61),"",J61/I61)) -> #REF! | I61: 22000 | J61: =J48*0.045 -> #REF!
A64: Waffle Dough | B64: 5 | C64: PCS | D64: =D76/B64 -> 5964.5532 | E64: =D64/90000 -> 0.066272813 | G64: Crepe Dough | H64: 8 | I64: PCS | J64: =J76/H64 -> 2138.95 | K64: =J64/90000 -> 0.023766111
A65: Name | B65: Qty | C65: Unit Price | D65: Total Cost | G65: Name | H65: Qty | I65: Unit Price | J65: Total Cost
A66: Flour | B66: =0.24*2 -> 0.48 | C66: ='F&B'!F17/50 -> 5295.6 | D66: =B66*C66 -> 2541.888 | G66: Flour | H66: 0.25 | I66: ='F&B'!F17/50 -> 5295.6 | J66: =H66*I66 -> 1323.9
A67: Salt | B67: =4.2/1000 -> 0.0042 | C67: ='F&B'!F143/25 -> 2340 | D67: =B67*C67 -> 9.828 | G67: Eggs | H67: 3 | I67: ='F&B'!F84/30 -> 1299 | J67: =H67*I67 -> 3897
A68: Baking Powder | B68: =B67*4 -> 0.0168 | C68: ='F&B'!$F$163 -> 40500 | D68: =B68*C68 -> 680.4 | G68: Milk | H68: 0.125 | I68: ='F&B'!F96 -> 13050 | J68: =H68*I68 -> 1631.25
A69: Eggs | B69: 2 | C69: =$C$35 -> 1299 | D69: =B69*C69 -> 2598 | G69: Water | H69: 0.125 | I69: 10000 | J69: =H69*I69 -> 1250
A70: Milk | B70: =0.24*1.5 -> 0.36 | C70: ='F&B'!$F$96 -> 13050 | D70: =B70*C70 -> 4698 | G70: Salt | H70: 0.05 | I70: ='F&B'!F143/25 -> 2340 | J70: =H70*I70 -> 117
A71: Butter | B71: =0.24*0.75 -> 0.18 | C71: ='F&B'!F79/25 -> 14040 | D71: =B71*C71 -> 2527.2 | G71: Butter | H71: 0.28 | I71: ='F&B'!$F$79/25 -> 14040 | J71: =H71*I71 -> 3931.2
A72: Vanilla | B72: =B67*3 -> 0.0126 | C72: =$C$38 -> 330750 | D72: =B72*C72 -> 4167.45 | G72: Vanilla Powder | H72: 0.015 | I72: =C72 -> 330750 | J72: =H72*I72 -> 4961.25
A73: Startch | B73: 0.1 | C73: ='F&B'!F170 -> 126000 | D73: =B73*C73 -> 12600
A76: TOTAL | D76: =IF(SUM(D66:D75)=0,"",SUM(D66:D75)) -> 29822.766 | G76: TOTAL | J76: =IF(SUM(J66:J75)=0,"",SUM(J66:J75)) -> 17111.6
A77: Selling Price 45 Grs | B77: =IF(D77="","",IF(ISBLANK(C77),"",D77/C77)) -> 0.012200222 | C77: 22000 | D77: =D64*0.045 -> 268.40489 | G77: Selling Price 45 Grs | H77: =IF(J77="","",IF(ISBLANK(I77),"",J77/I77)) | I77: 22000
A80: Pico de Galo | B80: 1.46 | C80: PCS | D80: =D92/B80 -> 7101.5753 | E80: 0.2 | G80: Croutons | H80: 1.2 | I80: PCS | J80: =J92/H80 -> 71480.654
A81: Name | B81: Qty | C81: Unit Price | D81: Total Cost | G81: Name | H81: Qty | I81: Unit Price | J81: Total Cost
A82: Tomato | B82: 1 | C82: ='F&B'!F279 -> 7200 | D82: =B82*C82 -> 7200 | G82: Pain de Mie | H82: 1 | I82: ='F&B'!F23 -> 75141 | J82: =H82*I82 -> 75141
A83: Onions | B83: 0.1 | C83: ='F&B'!F290 -> 6300 | D83: =B83*C83 -> 630 | G83: Olive Oil | H83: 0.2 | I83: ='F&B'!F43/13 -> 38076.923 | J83: =H83*I83 -> 7615.3846
A84: Granulated Garlic | B84: 0.02 | C84: ='F&B'!F191 -> 56700 | D84: =B84*C84 -> 1134 | G84: Salt | H84: 0.04 | I84: ='F&B'!F143/25 -> 2340 | J84: =H84*I84 -> 93.6
A85: Chili Pepper | B85: 0.05 | C85: ='F&B'!F296 -> 9000 | D85: =B85*C85 -> 450 | G85: Oregano | H85: 0.03 | I85: ='F&B'!F167 -> 37800 | J85: =H85*I85 -> 1134
A86: Salt | B86: 0.02 | C86: =C67 -> 2340 | D86: =B86*C86 -> 46.8 | G86: Garlic Powder | H86: 0.02 | I86: ='F&B'!F160 -> 47340 | J86: =H86*I86 -> 946.8
A87: Sunflower Oil | B87: 0.02 | C87: =SAUCES!C39 -> 8250 | D87: =B87*C87 -> 165 | G87: Paprika | H87: 0.02 | I87: ='F&B'!F168 -> 42300 | J87: =H87*I87 -> 846
A88: Corinder | B88: 0.25 | C88: ='F&B'!F311 -> 2970 | D88: =B88*C88 -> 742.5
A92: TOTAL | D92: =IF(SUM(D82:D91)=0,"",SUM(D82:D91)) -> 10368.3 | G92: TOTAL | J92: =IF(SUM(J82:J91)=0,"",SUM(J82:J91)) -> 85776.785
A93: Selling Price 45 Grs | B93: =IF(D93="","",IF(ISBLANK(C93),"",D93/C93)) -> 0.01452595 | C93: 22000 | D93: =D80*0.045 -> 319.57089 | G93: Selling Price 45 Grs | H93: =IF(J93="","",IF(ISBLANK(I93),"",J93/I93)) -> 0.14621043 | I93: 22000 | J93: =J80*0.045 -> 3216.6294
A96: Pancake Dough | B96: 10 | C96: PCS | D96: =D108/B96 -> 3941.3592 | G96: Brownie | H96: 15 | I96: PCS | J96: =J108/H96 -> 8925.999
A97: Name | B97: Qty | C97: Unit Price | D97: Total Cost | G97: Name | H97: Qty | I97: Unit Price | J97: Total Cost
A98: Flour | B98: 0.76 | C98: =C66 -> 5295.6 | D98: =B98*C98 -> 4024.656 | G98: Cocoa | H98: 0.46 | I98: ='F&B'!F107 -> 166500 | J98: =H98*I98 -> 76590
A99: Baking Powder | B99: 0.028 | C99: =C68 -> 40500 | D99: =B99*C99 -> 1134 | G99: Butter | H99: 0.9 | I99: =C104 -> 14040 | J99: =H99*I99 -> 12636
A100: Salt | B100: 0.03 | C100: =C67 -> 2340 | D100: =B100*C100 -> 70.2 | G100: Salt | H100: 0.015 | I100: =I67 -> 1299 | J100: =H100*I100 -> 19.485
A101: Sugar | B101: 0.06 | C101: =C36 -> 165.6 | D101: =B101*C101 -> 9.936 | G101: Sugar | H101: 1.8 | I101: =I36 -> 6300 | J101: =H101*I101 -> 11340
A102: Eggs | B102: 4 | C102: =I67 -> 1299 | D102: =B102*C102 -> 5196 | G102: Eggs | H102: 18 | I102: =C102 -> 1299 | J102: =H102*I102 -> 23382
A103: Milk | B103: 1.2 | C103: =C70 -> 13050 | D103: =B103*C103 -> 15660 | G103: Vanilla | H103: 0.03 | I103: =C105 -> 330750 | J103: =H103*I103 -> 9922.5
A104: Butter | B104: 0.21 | C104: =C71 -> 14040 | D104: =B104*C104 -> 2948.4 | J104: =H104*I104 -> 0
A105: Vanilla | B105: 0.02 | C105: =C72 -> 330750 | D105: =B105*C105 -> 6615 | J105: =H105*I105 -> 0
A106: Honey | B106: 0.12 | C106: ='F&B'!F51*1.22 -> 30195 | D106: =B106*C106 -> 3623.4
A107: Lemon Zest | B107: 0.0022 | C107: 60000 | D107: =B107*C107 -> 132
A108: TOTAL | D108: =IF(SUM(D98:D107)=0,"",SUM(D98:D107)) -> 39413.592 | G108: TOTAL | J108: =IF(SUM(J98:J107)=0,"",SUM(J98:J107)) -> 133889.98
A112: Spinach Dip | B112: 5 | C112: KG | D112: =D127/B112 -> 85473.903 | G112: Chicken Quesadillas | H112: 1.55 | I112: KG | J112: =J129/10 -> 14106.983
A113: Name | B113: Qty | C113: Unit Price | D113: Total Cost | G113: Name | H113: Qty | I113: Unit Price | J113: Total Cost
A114: Flour | B114: 0.28 | C114: =C82 -> 7200 | D114: =B114*C114 -> 2016 | G114: Chicken Breast | H114: 1.5 | I114: ='F&B'!F228 -> 81000 | J114: =H114*I114 -> 121500
A115: Butter | B115: 0.45 | C115: =I99 -> 14040 | D115: =B115*C115 -> 6318 | G115: Green Pepper | H115: 0.3 | I115: ='F&B'!F296 -> 9000 | J115: =H115*I115 -> 2700
A116: Olive Oil | B116: 0.1 | C116: =I83 -> 38076.923 | D116: =B116*C116 -> 3807.6923 | G116: Red Pepper | H116: 0.2 | I116: ='F&B'!F309 -> 22500 | J116: =H116*I116 -> 4500
A117: Onions | B117: 0.8 | C117: ='F&B'!F290 -> 6300 | D117: =B117*C117 -> 5040 | G117: Indian Onions | H117: 0.45 | I117: ='F&B'!F290 -> 6300 | J117: =H117*I117 -> 2835
A118: Garlic | B118: 0.025 | C118: ='F&B'!F292 -> 19800 | D118: =B118*C118 -> 495 | G118: Coriander | H118: 0.08 | I118: ='F&B'!F311 -> 2970 | J118: =H118*I118 -> 237.6
A119: Cream Fresh | B119: 1.8 | C119: ='F&B'!F87 -> 58500 | D119: =B119*C119 -> 105300 | G119: Sunflower Oil | H119: 0.2 | I119: =C87 -> 8250 | J119: =H119*I119 -> 1650
A120: Salt | B120: 0.075 | C120: =I100 -> 1299 | D120: =B120*C120 -> 97.425 | G120: Salt | H120: 0.02 | I120: =C100 -> 2340 | J120: =H120*I120 -> 46.8
A121: Sugar | B121: 0.03 | C121: =I101 -> 6300 | D121: =B121*C121 -> 189 | G121: Black Pepper | H121: 0.03 | I121: =I37 -> 51750 | J121: =H121*I121 -> 1552.5
A122: Lousiana WS | B122: 0.06 | C122: ='F&B'!F258/3.75 -> 55440 | D122: =B122*C122 -> 3326.4 | G122: Coriander Powder | H122: 0.05 | I122: ='F&B'!F159 -> 16560 | J122: =H122*I122 -> 828
A123: Parmesan Cheese | B123: 0.6 | C123: ='F&B'!F103 -> 148500 | D123: =B123*C123 -> 89100 | G123: Paprika | H123: 0.03 | I123: ='F&B'!F168 -> 42300 | J123: =H123*I123 -> 1269
A124: Lemon Juice | B124: 0.09 | C124: =C107 -> 60000 | D124: =B124*C124 -> 5400 | G124: Cumin | H124: 0.01 | I124: ='F&B'!F158 -> 81000 | J124: =H124*I124 -> 810
A125: Spinach | B125: 2.4 | C125: ='F&B'!F306 -> 7200 | D125: =B125*C125 -> 17280 | G125: Fahjita Pepper | H125: 0.01 | I125: ='F&B'!F164 -> 35460 | J125: =H125*I125 -> 354.6
A126: Artichaut | B126: 5 | C126: ='F&B'!F34 -> 37800 | D126: =B126*C126 -> 189000 | G126: Soya Sauce | H126: 0.05 | I126: ='F&B'!F252/3.8 -> 25401.316 | J126: =H126*I126 -> 1270.0658
A127: TOTAL | D127: =IF(SUM(D114:D123)=0,"",SUM(D114:D126)) -> 427369.52 | G127: Balsamic Sauce | H127: 0.025 | I127: ='F&B'!F255/5 -> 35640 | J127: =H127*I127 -> 891
G128: Worchester Sauce | H128: 0.015 | I128: ='F&B'!F260/3.8 -> 41684.211 | J128: =H128*I128 -> 625.26316
G129: TOTAL | J129: =sum(J114:J128) -> 141069.83
G130: 10 PORTIONS
A133: Caramel Sauce | B133: 1.5 | C133: KG | D133: =D140/B133 -> 41520
A134: Name | B134: Qty | C134: Unit Price | D134: Total Cost
A135: Sugar | B135: 0.6 | C135: =C121 -> 6300 | D135: =B135*C135 -> 3780
A136: Fresh Cream | B136: 1 | C136: =C37 -> 58500 | D136: =B136*C136 -> 58500
...

Sheet COMBOS
A1: COMBO DEALS FOR 2 - 3 - 4 - Family
A2: For 2
B3: Selling P | C3: Cost P | D3: Combo P | H3: NO FRIES | I3: Pepsi | J3: Water B
A4: Baked Potato | B4: 2.5 | C4: =#REF! -> #REF! | H4: =50000/90000 -> 0.55555556 | I4: =50000/90000 -> 0.55555556 | J4: 0.35
A5: Caesar Salad | B5: 7.5 | C5: =#REF! -> #REF!
A6: Light Chicken sand | B6: 10.5 | C6: =#REF! -> #REF!
A7: SOFT x2 | B7: 3.6 | C7: =I4*2 -> 1.1111111
A8: -0.09 | B8: 24.1 | C8: 5.47 | D8: 22
B9: 0.23 | C9: -2.1 | D9: =C8/D8 -> 0.24863636
A11: For 2 | G11: For 2
B12: Selling P | C12: Cost P | D12: Combo P | H12: Selling P | I12: Cost P | J12: Combo P
A13: Half Fries | B13: 2.5 | C13: =#REF!/2 -> #REF! | G13: Half Fries | H13: 2.5 | I13: =C13 -> #REF!
A14: Tangy B | B14: 13.5 | C14: =#REF!-H4 -> #REF! | D14: No Fries | G14: Pepp. Piz | H14: 11 | I14: =#REF! -> #REF!
A15: CHICK SUB | B15: 10 | C15: =#REF!-H4 -> #REF! | D15: No Fries | G15: Caesar Salad | H15: 7.5 | I15: =C5 -> #REF!
A16: Garlic Ch Br | B16: 4 | C16: =#REF! -> #REF! | G16: Garlic Ch Br | H16: 4 | I16: =C16 -> #REF!
A17: SOFT x2 | B17: 3.6 | C17: =I4*2 -> 1.1111111 | G17: SOFT x2 | H17: 3.6 | I17: =I4*2 -> 1.1111111
A18: -0.35 | B18: 33.6 | C18: 9.38 | D18: 25 | G18: -0.23 | H18: 28.6 | I18: 7.63 | J18: 22
B19: 0.28 | C19: -11.6 | D19: =C18/D18 -> 0.3752 | H19: 0.27 | I19: -6.6 | J19: =I18/J18 -> 0.34681818
A22: For 3 | G22: For 3
B23: Selling P | C23: Cost P | D23: Combo P | H23: Selling P | I23: Cost P | J23: Combo P
A24: 2 Half Fries | B24: 3.5 | C24: =#REF! -> #REF! | G24: 2 Half Fries | H24: 3.5 | I24: =C24 -> #REF!
A25: SWISS BURG | B25: 11.5 | C25: =#REF!-H4 -> #REF! | D25: No Fries | G25: Pep. Pizza | H25: 11 | I25: =I14 -> #REF!
A26: CHICK SUB | B26: 10 | C26: =C15 -> #REF! | D26: No Fries | G26: CHICK SUB | H26: 10 | I26: =C26 -> #REF! | J26: No Fries
A27: SOFT x3 | B27: 5.4 | C27: =I4*3 -> 1.6666667 | G27: SOFT x3 | H27: 5.4 | I27: =I4*3 -> 1.6666667
A28: Faj. Sand | B28: 11.5 | C28: =#REF!-H4 -> #REF! | D28: No Fries | G28: Caesar Salad | H28: 7.5 | I28: =C5 -> #REF!
A29: -0.21 | B29: 41.9 | C29: 11.34 | D29: 33 | G29: -0.12 | H29: 37.4 | I29: 10.31 | J29: 33
B30: 0.27 | C30: -8.9 | D30: =C29/D29 -> 0.34363636 | H30: 0.28 | I30: -4.4 | J30: =I29/J29 -> 0.31242424
A33: For 4 | G33: For 4
B34: Selling P | C34: Cost P | D34: Combo P | H34: Selling P | I34: Cost P | J34: Combo P
A35: COMBO | B35: 17 | C35: =#REF!/2.5 -> #REF! | D35: HALF | G35: COMBO | H35: 17 | I35: =C35 -> #REF! | J35: HALF
A36: Tangy B | B36: 13.5 | C36: =C14 -> #REF! | D36: No Fries | G36: Caesar Salad | H36: 7.5 | I36: =I28 -> #REF!
A37: CLASSIC B | B37: 8.5 | C37: =#REF!-H4 -> #REF! | D37: No Fries | G37: Tag. Pasta | H37: 11.5 | I37: =#REF! -> #REF!
A38: CHICK SUB | B38: 10 | C38: =C15 -> #REF! | D38: No Fries | G38: Reg. Pizza | H38: 11 | I38: =#REF! -> #REF!
A39: SOFT x4 | B39: 7.2 | C39: =I4*4 -> 2.2222222 | G39: SOFT x4 | H39: 7.2 | I39: =I4*4 -> 2.2222222
A40: Faj. Sand | B40: 11.5 | C40: =C28 -> #REF! | D40: No Fries | G40: Pepp. Piz | H40: 11 | I40: =I25 -> #REF!
A41: -0.35 | B41: 67.7 | C41: 16.78 | D41: 44 | G41: -0.33 | H41: 65.2 | I41: 17.64 | J41: 44
B42: 0.25 | C42: -23.7 | D42: =C41/D41 -> 0.38136364 | H42: 0.27 | I42: -21.2 | J42: =I41/J41 -> 0.40090909
A45: FAMILY | G45: FAMILY
B46: Selling P | C46: Cost P | D46: Combo P | H46: Selling P | I46: Cost P | J46: Combo P
A47: Half Fries | B47: 2.5 | C47: =C13 -> #REF! | G47: Half Fries | H47: 2.5 | I47: =C13 -> #REF!
A48: NUGGETS M | B48: 8 | C48: =#REF! -> #REF! | G48: NUGGETS M | H48: 8 | I48: =C48 -> #REF!
A49: COMBO | B49: 17 | C49: =C35 -> #REF! | D49: HALF | G49: COMBO | H49: 17 | I49: =C35 -> #REF! | J49: HALF
A50: CLASSIC BUR | B50: 8.5 | C50: =C37 -> #REF! | D50: No Fries | G50: Reg. Pizza | H50: 11 | I50: =I38 -> #REF!
A51: CHICK SUB | B51: 10 | C51: =C26 -> #REF! | D51: No Fries | G51: Pepp. Piz | H51: 11 | I51: =I40 -> #REF!
A52: Water B | B52: 1.8 | C52: =J4 -> 0.35 | G52: Water B | H52: 1.8 | I52: =J4 -> 0.35
A53: SOFT x4 | B53: 3.6 | C53: =I4*4 -> 2.2222222 | G53: SOFT x2 | H53: 3.6 | I53: =I4*4 -> 2.2222222
A54: -0.36 | B54: 51.4 | C54: 10.38 | D54: 33 | G54: -0.4 | H54: 54.9 | I54: 12.74 | J54: 33
B55: 0.2 | C55: -18.4 | D55: =C54/D54 -> 0.31454545 | H55: 0.23 | I55: -21.9 | J55: =I54/J54 -> 0.38606061

Sheet BAR
A1: Items | B1: USD / Box | C1: =#REF! -> #REF! | D1: Price / Box | E1: Qty / Box | F1: Unit Price | G1: Elec. Cost | H1: Extra | I1: Unit Price | J1: Selling Price | K1: > 30 % | P1: =#REF! -> #REF!
A2: Water Big | B2: =3.3*1.1 -> 3.63 | C2: =B2*$C$1 -> #REF! | D2: =77*1515 -> 116655 | E2: 12 | F2: =(C2/E2)/$C$1 -> #REF! | G2: ='UTL COST'!$D$5/$C$1 -> #REF! | I2: =F2+G2+H2 -> #REF! | J2: 1.25 | K2: =I2/J2 -> #REF! | L2: =30*B2 -> 108.9 | N2: Latte | P2: =Q2/$P$1 -> #REF! | Q2: =Q4+Q5 -> #REF!
A3: Water Small | B3: =3.3*1.1 -> 3.63 | C3: =B3*$C$1 -> #REF! | D3: =77*1515 -> 116655 | E3: 24 | F3: =(C3/E3)/$C$1 -> #REF! | G3: ='UTL COST'!$D$5/$C$1 -> #REF! | I3: =F3+G3+H3 -> #REF! | J3: 0.75 | K3: =I3/J3 -> #REF! | L3: =20*B3 -> 72.6 | O3: Qty | P3: Unit Price | Q3: Total
A4: Soft Drinks | B4: =4.75*1.1 -> 5.225 | C4: =B4*$C$1 -> #REF! | D4: 178000 | E4: 12 | F4: =(C4/E4)/$C$1 -> #REF! | G4: ='UTL COST'!$D$5/$C$1 -> #REF! | I4: =F4+G4+H4 -> #REF! | J4: 1.25 | K4: =I4/J4 -> #REF! | L4: =B4*30 -> 156.75 | N4: Espresso | O4: 1 | P4: =$F$12 -> #REF! | Q4: =P4*O4 -> #REF!
A5: Engery Drinks | B5: 8 | C5: =B5*$C$1 -> #REF! | D5: 580000 | E5: 24 | F5: =(C5/E5)/$C$1 -> #REF! | G5: ='UTL COST'!$D$5/$C$1 -> #REF! | I5: =F5+G5+H5 -> #REF! | J5: 1.5 | K5: =I5/J5 -> #REF! | L5: =B5*2 -> 16 | N5: Milk | O5: 0.375 | P5: ='F&B'!$F$96 -> 13050 | Q5: =P5*O5 -> 4893.75
A6: Nescafe | B6: 4.01 | C6: =B6*$C$1 -> #REF! | D6: 250000 | E6: 35 | F6: =(C6/E6)/$C$1 -> #REF! | G6: ='UTL COST'!$D$5/$C$1 -> #REF! | I6: =F6+G6+H6 -> #REF! | J6: 1 | K6: =I6/J6 -> #REF! | L6: =B6*10 -> 40.1
A7: Tea | B7: 3.03 | C7: =B7*$C$1 -> #REF! | D7: 115000 | E7: 100 | F7: =(C7/E7)/$C$1 -> #REF! | G7: ='UTL COST'!$D$5/$C$1 -> #REF! | I7: =F7+G7+H7 -> #REF! | J7: 1 | K7: =I7/J7 -> #REF! | L7: =B7*2 -> 6.06
A8: Mix Tea | B8: 1.58 | C8: =B8*$C$1 -> #REF! | D8: 60000 | E8: 20 | F8: =(C8/E8)/$C$1 -> #REF! | G8: ='UTL COST'!$D$5/$C$1 -> #REF! | I8: =F8+G8+H8 -> #REF! | J8: 1 | K8: =I8/J8 -> #REF! | L8: =B8*2 -> 3.16 | N8: Mocha | P8: =Q8/$P$1 -> #REF! | Q8: =Q10+Q12+Q11 -> #REF!
A9: Latte | B9: =D9/38000 -> 0 | C9: - | D9: 0 | E9: 0 | F9: =$Q$2/$C$1 -> #REF! | G9: ='UTL COST'!$D$5/$C$1 -> #REF! | I9: =F9+G9+H9 -> #REF! | J9: 1.5 | K9: =I9/J9 -> #REF! | L9: =B9*2 -> 0 | O9: Qty | P9: Unit Price | Q9: Total
A10: Mocha | B10: =D10/38000 -> 0 | C10: - | D10: 0 | E10: 0 | F10: =$Q$8/$C$1 -> #REF! | G10: ='UTL COST'!$D$5/$C$1 -> #REF! | I10: =F10+G10+H10 -> #REF! | J10: 2 | K10: =I10/J10 -> #REF! | L10: =B10*2 -> 0 | N10: Espresso | O10: 1 | P10: =$F$12 -> #REF! | Q10: =P10*O10 -> #REF!
A11: Hot Chocolate | B11: =D11/38000 -> 0 | C11: - | D11: 0 | E11: 0 | F11: =$Q$14/$C$1 -> #REF! | G11: ='UTL COST'!$D$5/$C$1 -> #REF! | I11: =F11+G11+H11 -> #REF! | J11: 1.75 | K11: =I11/J11 -> #REF! | L11: =B11*2 -> 0 | N11: Chocolate Syrup | O11: 0.03 | P11: ='F&B'!$F$111/1.2 -> 56250 | Q11: =P11*O11 -> 1687.5
A12: Espresso | B12: 12 | C12: =B12*$C$1 -> #REF! | D12: 480000 | E12: 70 | F12: =(C12/E12)/$C$1 -> #REF! | G12: ='UTL COST'!$D$5/$C$1 -> #REF! | I12: =F12+G12+H12 -> #REF! | J12: 0.75 | K12: =I12/J12 -> #REF! | L12: =B12*5 -> 60 | N12: Milk | O12: 0.375 | P12: ='F&B'!$F$96 -> 13050 | Q12: =P12*O12 -> 4893.75
A13: Turkish Coffee | B13: 8.42 | C13: =B13*$C$1 -> #REF! | D13: 320000 | E13: 100 | F13: =(C13/E13)/$C$1 -> #REF! | G13: ='UTL COST'!$D$5/$C$1 -> #REF! | I13: =F13+G13+H13 -> #REF! | J13: 0.75 | K13: =I13/J13 -> #REF! | L13: =B13*2 -> 16.84
A14: Almaza | B14: =17.5*1.1 -> 19.25 | C14: =B14*$C$1 -> #REF! | D14: 640000 | E14: 24 | F14: =(C14/E14)/$C$1 -> #REF! | G14: ='UTL COST'!$D$5/$C$1 -> #REF! | H14: =$B$18 -> 0.18 | I14: =F14+G14+H14 -> #REF! | J14: 2 | K14: =I14/J14 -> #REF! | L14: =B14*3 -> 57.75 | N14: Hot Chocolate | P14: =Q14/P1 -> #REF! | Q14: =Q16+Q18+Q17 -> #REF!
A15: Perrier | B15: =17.01*1.1 -> 18.711 | C15: =B15*$C$1 -> #REF! | D15: 590000 | E15: 24 | F15: =(C15/E15)/$C$1 -> #REF! | G15: ='UTL COST'!$D$5/$C$1 -> #REF! | I15: =F15+G15+H15 -> #REF! | J15: 2 | K15: =I15/J15 -> #REF! | L15: =B15*2 -> 37.422 | O15: Qty | P15: Unit Price | Q15: Total
A16: Laziza | B16: 12.63 | C16: =B16*$C$1 -> #REF! | D16: 480000 | E16: 24 | F16: =(C16/E16)/$C$1 -> #REF! | G16: ='UTL COST'!$D$5/$C$1 -> #REF! | H16: =$B$18 -> 0.18 | I16: =F16+G16+H16 -> #REF! | J16: 2 | K16: =I16/J16 -> #REF! | L16: =B16*0.5 -> 6.315 | N16: Chocolate Powder | O16: 0.02 | P16: =(15.9*1.1)*C1 -> #REF! | Q16: =P16*O16 -> #REF!
A17: Iced Tea | B17: =3.07*4*1.1 -> 13.508 | C17: =B17*$C$1 -> #REF! | D17: 440000 | E17: 24 | F17: =(C17/E17)/$C$1 -> #REF! | G17: ='UTL COST'!$D$5/$C$1 -> #REF! | I17: =F17+G17+H17 -> #REF! | J17: 1.5 | K17: =I17/J17 -> #REF! | L17: =B17*2 -> 27.016 | N17: Chocolate Syrup | O17: 0.03 | P17: ='F&B'!$F$111/1.2 -> 56250 | Q17: =P17*O17 -> 1687.5
A18: Nuts | B18: 0.18 | C18: =B18*$C$1 -> #REF! | D18: 7000 | E18: 1 | F18: =(C18/E18)/$C$1 -> #REF! | G18: ='UTL COST'!$D$5/$C$1 -> #REF! | I18: =F18+G18+H18 -> #REF! | J18: 0.75 | K18: =I18/J18 -> #REF! | L18: =B18*100 -> 18 | N18: Milk | O18: 0.375 | P18: ='F&B'!$F$96 -> 13050 | Q18: =P18*O18 -> 4893.75
A19: 1 Syrup Cocktail | C19: - | F19: =Q20/$C$1 -> #REF! | G19: ='UTL COST'!$D$5/$C$1 -> #REF! | I19: =F19+G19+H19 -> #REF! | J19: 2 | K19: =I19/J19 -> #REF! | L19: =B19*2 -> 0
A20: 2 Syrup Cocktail | C20: - | F20: =Q26/$C$1 -> #REF! | G20: ='UTL COST'!$D$5/$C$1 -> #REF! | I20: =F20+G20+H20 -> #REF! | J20: 2 | K20: =I20/J20 -> #REF! | L20: =B20*2 -> 0 | N20: Cocktail 1 Syrup | P20: =Q20/$P$1 -> #REF! | Q20: =Q22+Q23+Q24 -> #REF!
A21: Perrier Large | B21: =19.49*1.1 -> 21.439 | C21: =B21*$C$1 -> #REF! | D21: 590000 | E21: 12 | F21: =(C21/E21)/$C$1 -> #REF! | G21: ='UTL COST'!$D$5/$C$1 -> #REF! | I21: =F21+G21+H21 -> #REF! | J21: 5 | K21: =I21/J21 -> #REF! | L21: =B21*1 -> 21.439 | O21: Qty | P21: Unit Price | Q21: Total
A22: Almaza KEG | B22: 33 | C22: =B22*$C$1 -> #REF! | D22: 590000 | E22: 55 | F22: =(C22/E22)/$C$1 -> #REF! | G22: ='UTL COST'!$D$5/$C$1 -> #REF! | I22: =F22+G22+H22 -> #REF! | J22: 2 | K22: =I22/J22 -> #REF! | L22: =B22*1 -> 33 | N22: Syrup 1883 | O22: 0.02 | P22: =7.6*1.1*($P$1) -> #REF! | Q22: =P22*O22 -> #REF!
N23: Juice 1 | O23: 0.06 | P23: 170000 | Q23: =P23*O23 -> 10200
N24: Juice 2 | O24: 0.06 | P24: =$P$23 -> 170000 | Q24: =P24*O24 -> 10200
N26: Cocktail 2 Syrups | P26: =Q26/$P$1 -> #REF! | Q26: =Q28+Q29+Q30+Q31 -> #REF!
O27: Qty | P27: Unit Price | Q27: Total
N28: Syrup 1883 | O28: 0.02 | P28: =P22 -> #REF! | Q28: =P28*O28 -> #REF!
N29: Juice 1 | O29: 0.06 | P29: =$P$23 -> 170000 | Q29: =P29*O29 -> 10200
N30: Juice 2 | O30: 0.06 | P30: =$P$23 -> 170000 | Q30: =P30*O30 -> 10200
N31: Syrup 1883 | O31: 0.02 | P31: =P28 -> #REF! | Q31: =P31*O31 -> #REF!

Sheet KIDS MENU
A1: KIDS MENU
I4: DISH NAME | J4: Chicken Tenders
B5: DISH NAME | C5: French Fries Side
I6: EST. SALE PPRICE | J6: 120000
B7: EST. SALE PPRICE | C7: =3.5*100000 -> 350000
I8: TOTAL COST | J8: =IF(SUM(L20,L35,L43)=0,"",SUM(L20,L35,L43)) -> #REF! | L8: =J8/90000 -> #REF!
B9: TOTAL COST | C9: =IF(SUM(E21,E36,E44)=0,"",SUM(E21,E36,E44)) -> #REF! | E9: =C9/90000 -> #REF!
I10: COST MARGIN | J10: =IF(J8="","",IF(ISBLANK(J6),"",J8/J6)) -> #REF!
B11: COST MARGIN | C11: =IF(C9="","",IF(ISBLANK(C7),"",C9/C7)) -> #REF!
I12: NET PROFIT | J12: =J6-J8 -> #REF!
B13: NET PROFIT | C13: =C7-C9 -> #REF!
I15: PRIMARY INGREDIENTS
B16: PRIMARY INGREDIENTS | I16: Product Name | J16: Qty. | K16: Cost (per unit) | L16: Total Cost
B17: Product Name | C17: Qty. | D17: Cost (per unit) | E17: Total Cost | I17: Chicken Breast | J17: 0.2 | K17: ='F&B'!$F$229 -> 81000 | L17: =IF(OR(ISBLANK(J17),ISBLANK(K17)),"",K17*J17) -> 16200
B18: French Fries | C18: 0.2 | D18: ='F&B'!$F$68/10 -> 19665 | E18: =IF(OR(ISBLANK(C18),ISBLANK(D18)),"",D18*C18) -> 3933
I19: Ketchup | J19: 0.05 | K19: ='F&B'!F249/4 -> 12825 | L19: =IF(OR(ISBLANK(J19),ISBLANK(K19)),"",K19*J19) -> 641.25
E20: =IF(OR(ISBLANK(C20),ISBLANK(D20)),"",D20*C20) | I20: TOTAL | L20: =IF(SUM(L17:L19)=0,"",SUM(L17:L19)) -> 16841.25
B21: TOTAL | E21: =IF(SUM(E18:E20)=0,"",SUM(E18:E20)) -> 3933
I22: SECONDARY INGREDIENTS
B23: SECONDARY INGREDIENTS | I23: Product Name | J23: Qty | K23: Cost | L23: Total Cost
B24: Product Name | C24: Qty | D24: Cost | E24: Total Cost
I25: Breaded | J25: 2 | K25: =SAUCES!D48 -> 563.76 | L25: =K25*J25 -> 1127.52
E26: =D26*C26 -> 0
E27: =D27*C27 -> 0
E28: =D28*C28 -> 0
E29: =D29*C29 -> 0
E30: =D30*C30 -> 0
E31: =D31*C31 -> 0
E32: =D32*C32 -> 0
E33: =D33*C33 -> 0
E34: =D34*C34 -> 0
E35: =D35*C35 -> 0 | I35: TOTAL | L35: =SUM(L25:L34) -> 1127.52
B36: TOTAL | E36: =IF(SUM(E26:E35)=0,"",SUM(E26:E35))
I37: UTILITY AND PREP. COST
B38: UTILITY AND PREP. COST | I38: Name | L38: Total Cost
B39: Name | E39: Total Cost | I39: Shorenting Oil | J39: ='UTL COST'!$B$3 -> 369000 | K39: ='UTL COST'!$C$3 -> 0.0075 | L39: ='UTL COST'!$D$3 -> 2767.5
B40: Shorenting Oil | C40: ='UTL COST'!$B$3 -> 369000 | D40: ='UTL COST'!$C$3 -> 0.0075 | E40: ='UTL COST'!$D$3 -> 2767.5 | I40: Gas | J40: ='UTL COST'!$B$4 -> #REF! | K40: ='UTL COST'!$C$4 -> 7000 | L40: ='UTL COST'!$D$4 -> #REF!
B41: Gas | C41: ='UTL COST'!$B$4 -> #REF! | D41: ='UTL COST'!$C$4 -> 7000 | E41: ='UTL COST'!$D$4 -> #REF! | I41: Electricity | J41: ='UTL COST'!$B$5 -> #REF! | K41: ='UTL COST'!$C$5 -> 45000 | L41: ='UTL COST'!$D$5 -> #REF!
B42: Electricity | C42: ='UTL COST'!$B$5 -> #REF! | D42: ='UTL COST'!$C$5 -> 45000 | E42: ='UTL COST'!$D$5 -> #REF! | I42: Water | J42: ='UTL COST'!$B$6 -> #REF! | K42: ='UTL COST'!$C$6 -> 525 | L42: 0.1
B43: Water | C43: ='UTL COST'!$B$6 -> #REF! | D43: ='UTL COST'!$C$6 -> 525 | E43: 0.1 | I43: TOTAL | L43: =IF(SUM(L39:L42)=0,"",SUM(L39:L42)) -> #REF!
B44: TOTAL | E44: =IF(SUM(E40:E43)=0,"",SUM(E40:E43)) -> #REF!
B50: DISH NAME | C50: Butter Penne | I50: DISH NAME | J50: Margherita
B52: EST. SALE PPRICE | C52: =3.5*100000 -> 350000 | I52: EST. SALE PPRICE | J52: 135000
B54: TOTAL COST | C54: =IF(SUM(E66,E81,E89)=0,"",SUM(E66,E81,E89)) -> #REF! | E54: =C54/90000 -> #REF! | I54: TOTAL COST | J54: =IF(SUM(L66,L81,L89)=0,"",SUM(L66,L81,L89)) -> #REF! | L54: =J54/90000 -> #REF!
B56: COST MARGIN | C56: =IF(C54="","",IF(ISBLANK(C52),"",C54/C52)) -> #REF! | I56: COST MARGIN | J56: =IF(J54="","",IF(ISBLANK(J52),"",J54/J52)) -> #REF!
B58: NET PROFIT | C58: =C52-C54 -> #REF! | I58: NET PROFIT | J58: =J52-J54 -> #REF!
B61: PRIMARY INGREDIENTS | I61: PRIMARY INGREDIENTS
B62: Product Name | C62: Qty. | D62: Cost (per unit) | E62: Total Cost | I62: Product Name | J62: Qty. | K62: Cost (per unit) | L62: Total Cost
B63: Penne | C63: 0.166 | D63: =PASTA!D19 -> 787.5 | E63: =IF(OR(ISBLANK(C63),ISBLANK(D63)),"",D63*C63) -> 130.725 | I63: Mozzarella Cheese | J63: 0.075 | K63: ='F&B'!F99/12 -> 63000 | L63: =IF(OR(ISBLANK(J63),ISBLANK(K63)),"",K63*J63) -> 4725
B64: Butter | C64: 0.05 | D64: ='F&B'!F79/25 -> 14040 | E64: =IF(OR(ISBLANK(C64),ISBLANK(D64)),"",D64*C64) -> 702 | I64: Tomato Sauce | J64: 0.038 | K64: =SAUCES!$L$60 -> 19698.45 | L64: =IF(OR(ISBLANK(J64),ISBLANK(K64)),"",K64*J64) -> 748.54109
E65: =IF(OR(ISBLANK(C65),ISBLANK(D65)),"",D65*C65) | I65: Dough | J65: 0.5 | K65: =SAUCES!$D$92 -> 900.92308 | L65: =IF(OR(ISBLANK(J65),ISBLANK(K65)),"",K65*J65) -> 450.46154
B66: TOTAL | E66: =IF(SUM(E63:E65)=0,"",SUM(E63:E65)) -> 832.725 | I66: TOTAL | L66: =IF(SUM(L63:L65)=0,"",SUM(L63:L65)) -> 5924.0026
B68: SECONDARY INGREDIENTS | I68: SECONDARY INGREDIENTS
B69: Product Name | C69: Qty | D69: Cost | E69: Total Cost | I69: Product Name | J69: Qty | K69: Cost | L69: Total Cost
E71: =D71*C71 -> 0 | I71: Oregano | J71: 0.005 | K71: ='F&B'!$F$167 -> 37800 | L71: =K71*J71 -> 189
E72: =D72*C72 -> 0 | L72: =K72*J72 -> 0
E73: =D73*C73 -> 0 | L73: =K73*J73 -> 0
E74: =D74*C74 -> 0 | L74: =K74*J74 -> 0
E75: =D75*C75 -> 0 | L75: =K75*J75 -> 0
E76: =D76*C76 -> 0 | L76: =K76*J76 -> 0
E77: =D77*C77 -> 0 | L77: =K77*J77 -> 0
E78: =D78*C78 -> 0 | L78: =K78*J78 -> 0
E79: =D79*C79 -> 0 | L79: =K79*J79 -> 0
E80: =D80*C80 -> 0 | L80: =K80*J80 -> 0
B81: TOTAL | E81: =IF(SUM(E71:E80)=0,"",SUM(E71:E80)) | I81: TOTAL | L81: =IF(SUM(L71:L80)=0,"",SUM(L71:L80)) -> 189
B83: UTILITY AND PREP. COST | I83: UTILITY AND PREP. COST
B84: Name | E84: Total Cost | I84: Name | L84: Total Cost
B85: Shorenting Oil | C85: ='UTL COST'!$B$3 -> 369000 | D85: ='UTL COST'!$C$3 -> 0.0075 | E85: ='UTL COST'!$D$3 -> 2767.5 | I85: Shorenting Oil | J85: ='UTL COST'!$B$3 -> 369000 | K85: ='UTL COST'!$C$3 -> 0.0075 | L85: 0
B86: Gas | C86: ='UTL COST'!$B$4 -> #REF! | D86: ='UTL COST'!$C$4 -> 7000 | E86: ='UTL COST'!$D$4 -> #REF! | I86: ='UTL COST'!$A$7 -> Gas Pizza | J86: ='UTL COST'!$B$7 -> #REF! | K86: ='UTL COST'!$C$7 -> 450 | L86: ='UTL COST'!$D$7 -> #REF!
B87: Electricity | C87: ='UTL COST'!$B$5 -> #REF! | D87: ='UTL COST'!$C$5 -> 45000 | E87: ='UTL COST'!$D$5 -> #REF! | I87: Electricity | J87: ='UTL COST'!$B$5 -> #REF! | K87: ='UTL COST'!$C$5 -> 45000 | L87: ='UTL COST'!$D$5 -> #REF!
B88: Water | C88: ='UTL COST'!$B$6 -> #REF! | D88: ='UTL COST'!$C$6 -> 525 | E88: 0.1 | I88: ='UTL COST'!H50 | J88: ='UTL COST'!$B$6 -> #REF! | K88: ='UTL COST'!$C$6 -> 525 | L88: 0
B89: TOTAL | E89: =IF(SUM(E85:E88)=0,"",SUM(E85:E88)) -> #REF! | I89: TOTAL | L89: =IF(SUM(L85:L88)=0,"",SUM(L85:L88)) -> #REF!
B95: DISH NAME | C95: Nuggets | I95: DISH NAME | J95: Kids Meal Nuggets
B97: EST. SALE PPRICE | C97: 85000 | I97: EST. SALE PPRICE | J97: 85000
B99: TOTAL COST | C99: =IF(SUM(E111,E126,E134)=0,"",SUM(E111,E126,E134)) -> #REF! | E99: =C99/90000 -> #REF! | I99: TOTAL COST | J99: =IF(SUM(L111,L126,L134)=0,"",SUM(L111,L126,L134)) -> #REF! | L99: =J99/90000 -> #REF!
B101: COST MARGIN | C101: =IF(C99="","",IF(ISBLANK(C97),"",C99/C97)) -> #REF! | I101: COST MARGIN | J101: =IF(J99="","",IF(ISBLANK(J97),"",J99/J97)) -> #REF!
B103: NET PROFIT | C103: =C97-C99 -> #REF! | I103: NET PROFIT | J103: =J97-J99 -> #REF!
B106: PRIMARY INGREDIENTS | I106: PRIMARY INGREDIENTS
B107: Product Name | C107: Qty. | D107: Cost (per unit) | E107: Total Cost | I107: Product Name | J107: Qty. | K107: Cost (per unit) | L107: Total Cost
B108: Nuggets 6 Pcs 17.5 Grs | C108: =17.5*6/1000 -> 0.105 | D108: ='F&B'!$F$235 -> 47250 | E108: =IF(OR(ISBLANK(C108),ISBLANK(D108)),"",D108*C108) -> 4961.25 | I108: Nuggets 5 Pcs 17.5 Grs | J108: 0.0875 | K108: ='F&B'!$F$235 -> 47250 | L108: =IF(OR(ISBLANK(J108),ISBLANK(K108)),"",K108*J108) -> 4134.375
B109: French Fries | C109: 0.1 | D109: ='F&B'!$F$235 -> 47250 | E109: =IF(OR(ISBLANK(C109),ISBLANK(D109)),"",D109*C109) -> 4725 | I109: French Fries | J109: 0.1 | K109: ='F&B'!$F$235 -> 47250 | L109: =IF(OR(ISBLANK(J109),ISBLANK(K109)),"",K109*J109) -> 4725
E110: =IF(OR(ISBLANK(C110),ISBLANK(D110)),"",D110*C110) | L110: =IF(OR(ISBLANK(J110),ISBLANK(K110)),"",K110*J110)
B111: TOTAL | E111: =IF(SUM(E108:E110)=0,"",SUM(E108:E110)) -> 9686.25 | I111: TOTAL | L111: =IF(SUM(L108:L110)=0,"",SUM(L108:L110)) -> 8859.375
B113: SECONDARY INGREDIENTS | I113: SECONDARY INGREDIENTS
B114: Product Name | C114: Qty | D114: Cost | E114: Total Cost | I114: Product Name | J114: Qty | K114: Cost | L114: Total Cost
E116: 0 | I116: Mr Juicy | J116: 1 | K116: =0.16*90000 -> 14400 | L116: =IF(OR(ISBLANK(J116),ISBLANK(K116)),"",K116*J116) -> 14400
E117: =D117*C117 -> 0 | I117: Toy | J117: 1 | K117: =0.7*90000 -> 63000 | L117: =IF(OR(ISBLANK(J117),ISBLANK(K117)),"",K117*J117) -> 63000
E118: =D118*C118 -> 0 | L118: =K118*J118 -> 0
E119: =D119*C119 -> 0 | L119: =K119*J119 -> 0
E120: =D120*C120 -> 0 | L120: =K120*J120 -> 0
E121: =D121*C121 -> 0 | L121: =K121*J121 -> 0
E122: =D122*C122 -> 0 | L122: =K122*J122 -> 0
E123: =D123*C123 -> 0 | L123: =K123*J123 -> 0
E124: =D124*C124 -> 0 | L124: =K124*J124 -> 0
E125: =D125*C125 -> 0 | L125: =K125*J125 -> 0
B126: TOTAL | E126: =IF(SUM(E116:E125)=0,"",SUM(E116:E125)) | I126: TOTAL | L126: =IF(SUM(L116:L125)=0,"",SUM(L116:L125)) -> 77400
B128: UTILITY AND PREP. COST | I128: UTILITY AND PREP. COST
B129: Name | E129: Total Cost | I129: Name | L129: Total Cost
B130: Shorenting Oil | C130: ='UTL COST'!$B$3 -> 369000 | D130: ='UTL COST'!$C$3 -> 0.0075 | E130: ='UTL COST'!$D$3 -> 2767.5 | I130: Shorenting Oil | J130: ='UTL COST'!$B$3 -> 369000 | K130: ='UTL COST'!$C$3 -> 0.0075 | L130: ='UTL COST'!$D$3 -> 2767.5
B131: Gas | C131: ='UTL COST'!$B$4 -> #REF! | D131: ='UTL COST'!$C$4 -> 7000 | E131: ='UTL COST'!$D$3 -> 2767.5 | I131: Gas | J131: ='UTL COST'!$B$4 -> #REF! | K131: ='UTL COST'!$C$4 -> 7000 | L131: ='UTL COST'!$D$3 -> 2767.5
...

Sheet BIRTHDAYS
A1: 19
A2: Birthdays Formula | B2: Qty | C2: Cost Price | D2: Total | F2: Qty | G2: SP | I2: Mini Sandwiches | J2: Qty | K2: UP | L2: Total
A3: Greek Salad - 8 Prs | B3: 8 | C3: =#REF! -> #REF! | D3: =B3*C3 -> #REF! | F3: 1 | G3: =D3*F3 -> #REF! | I3: Turkey | J3: 0.12 | K3: ='F&B'!$E$223 -> 15.88 | L3: =J3*K3 -> 1.9056
A4: Chicken Ceasar Salad - 8 Prs | B4: 8 | C4: =#REF! -> #REF! | D4: =B4*C4 -> #REF! | F4: 1 | G4: =D4*F4 -> #REF! | I4: Chicken | J4: =0.16*10 -> 1.6 | K4: ='F&B'!$E$229 -> 9 | L4: =J4*K4 -> 14.4
A5: Chicken Tenders - Pcs | B5: 50 | C5: =#REF!/4 -> #REF! | D5: =B5*C5 -> #REF! | F5: 50 | G5: =D5*F5 -> #REF! | I5: Emmental | J5: 0.12 | K5: ='F&B'!$E$85 -> 14.35 | L5: =J5*K5 -> 1.722
A6: Mini Sandwiches - Pcs | B6: 50 | C6: =L10 -> #REF! | D6: =B6*C6 -> #REF! | E6: =L11 -> #REF! | F6: 50 | G6: =F6*E6 -> #REF! | I6: Bread | J6: 40 | K6: =1.45/6 -> 0.24166667 | L6: =J6*K6 -> 9.6666667
A7: Nuggets - Pcs | C7: =#REF!/5 -> #REF! | D7: =B7*C7 -> #REF! | E7: 0.7 | F7: 50 | G7: =F7*E7 -> 35 | I7: Iceberg | J7: 0.75 | K7: ='F&B'!$E$277 -> 1.5 | L7: =J7*K7 -> 1.125
A8: Mini Burgers - Pcs | B8: 75 | C8: =M29 -> #REF! | D8: =B8*C8 -> #REF! | E8: 2.25 | F8: 50 | G8: =D8*F8 -> #REF! | I8: Honey Mustard | J8: 0.2 | K8: =SAUCES!$D$122/#REF! -> #REF! | L8: =J8*K8 -> #REF!
A9: Fries | B9: 6 | C9: =#REF! -> #REF! | D9: =B9*C9 -> #REF! | F9: 8 | G9: =D9*F9 -> #REF! | K9: 40 | L9: =SUM(L3:L8) -> #REF!
A10: Pizza Mini - Pcs | B10: 50 | C10: =#REF!/9 -> #REF! | D10: =B10*C10 -> #REF! | E10: 0.8 | F10: 50 | G10: =E10*F10 -> 40 | L10: =L9/K9 -> #REF!
D11: =SUM(D3:D10) -> #REF! | G11: =SUM(G3:G10) -> #REF! | L11: =L10*3 -> #REF!
A12: Penne Pasta | B12: 8 | C12: =#REF! -> #REF! | D12: =B12*C12 -> #REF!
A13: Tag. Pasta | B13: 8 | C13: =#REF! -> #REF! | D13: =B13*C13 -> #REF!
A14: Drinks | B14: 10 | C14: =200000/89000 -> 2.247191 | D14: =B14*C14 -> 22.47191
A15: Hommos | B15: 8 | C15: =#REF! -> #REF! | D15: =B15*C15 -> #REF!
A16: Water Big | B16: 15 | C16: 0.26 | D16: =B16*C16 -> 3.9
D17: =SUM(D11:D16) -> #REF!
B18: =18*50 -> 900 | D18: =D17/B18 -> #REF!
J22: Mini Burgers | K22: Qty | L22: UP | M22: Total
E23: 250 | F23: 310 | G23: 390 | J23: Burger Patty 80 Grs | K23: 1 | L23: 0.8 | M23: =K23*L23 -> 0.8
E24: 25-30 | F24: 30-35 | G24: 35-40 | J24: Burger Bun | K24: 1 | L24: =2.1/12 -> 0.175 | M24: =K24*L24 -> 0.175
J25: Ketchup | K25: 0.002 | L25: ='F&B'!F249/#REF! -> #REF! | M25: =K25*L25 -> #REF!
L29: 1 | M29: =SUM(M23:M28) -> #REF!
M30: =M29/L29 -> #REF! | N30: =M30+0.13+0.5 -> #REF!
M31: =M30*2 -> #REF!

Sheet RICE MEALS
A1: RICE MEALS FOOD COST
B6: DISH NAME | C6: White Rice | J6: DISH NAME | K6: Green Salad
B8: EST. SALE PPRICE | J8: EST. SALE PPRICE
E9: 18 Portions
B10: TOTAL COST | C10: =IF(SUM(E22,E37,E45)=0,"",SUM(E22,E37,E45)) -> #REF! | E10: =C10/18 -> #REF! | J10: TOTAL COST | K10: =IF(SUM(M22,M37,M45)=0,"",SUM(M22,M37,M45)) -> 7515.063
B12: COST MARGIN | C12: =IF(C10="","",IF(ISBLANK(C8),"",C10/C8)) -> #REF! | J12: COST MARGIN | K12: =IF(K10="","",IF(ISBLANK(K8),"",K10/K8))
B14: NET PROFIT | C14: =C8-C10 -> #REF! | J14: NET PROFIT | K14: =K8-K10 -> -7515.063
B17: PRIMARY INGREDIENTS | J17: PRIMARY INGREDIENTS
B18: Product Name | C18: Qty. | D18: Cost (per unit) | E18: Total Cost | J18: Product Name | K18: Qty. | L18: Cost (per unit) | M18: Total Cost
B19: Rice | C19: 1.08 | D19: ='F&B'!F141/20 -> 12150 | E19: =IF(OR(ISBLANK(C19),ISBLANK(D19)),"",D19*C19) -> 13122 | J19: Iceberg | K19: 0.2 | L19: ='F&B'!F277 -> 13500 | M19: =IF(OR(ISBLANK(K19),ISBLANK(L19)),"",L19*K19) -> 2700
B20: Magi Cubes | C20: 1 | D20: ='F&B'!F42/12 -> 2062.5 | E20: =IF(OR(ISBLANK(C20),ISBLANK(D20)),"",D20*C20) -> 2062.5 | J20: Red Cabbage | K20: 0.15 | L20: ='F&B'!F294 -> 6750 | M20: =IF(OR(ISBLANK(K20),ISBLANK(L20)),"",L20*K20) -> 1012.5
B21: Sunflower Oil | C21: 0.02 | D21: ='F&B'!F57/8 -> 18562.5 | E21: =IF(OR(ISBLANK(C21),ISBLANK(D21)),"",D21*C21) -> 371.25 | J21: Carrots | K21: 0.15 | L21: ='F&B'!F293 -> 6750 | M21: =IF(OR(ISBLANK(K21),ISBLANK(L21)),"",L21*K21) -> 1012.5
B22: TOTAL | E22: =IF(SUM(E19:E21)=0,"",SUM(E19:E21)) -> 15555.75 | J22: TOTAL | M22: =IF(SUM(M19:M21)=0,"",SUM(M19:M21)) -> 4725
B24: SECONDARY INGREDIENTS | J24: SECONDARY INGREDIENTS
B25: Product Name | C25: Qty | D25: Cost | E25: Total Cost | J25: Product Name | K25: Qty | L25: Cost | M25: Total Cost
B27: Butter | C27: 0.015 | D27: ='F&B'!F79/25 -> 14040 | E27: =D27*C27 -> 210.6 | J27: Argula | K27: 0.2 | L27: ='F&B'!F302 -> 10800 | M27: =L27*K27 -> 2160
B28: Salt | C28: 0.03 | D28: ='F&B'!F143/25 -> 2340 | E28: =D28*C28 -> 70.2 | J28: Sauce | K28: 1 | L28: =SAUCES!L16 -> 629.96299 | M28: =L28*K28 -> 629.96299
B29: Black Pepper | C29: 0.005 | D29: ='F&B'!F148 -> 51750 | E29: =D29*C29 -> 258.75 | M29: =L29*K29 -> 0
B30: Bay leaves | C30: 1 | D30: ='F&B'!F153/50 -> 540 | E30: =D30*C30 -> 540 | M30: =L30*K30 -> 0
E31: =D31*C31 -> 0 | M31: =L31*K31 -> 0
E32: =D32*C32 -> 0 | M32: =L32*K32 -> 0
E33: =D33*C33 -> 0 | M33: =L33*K33 -> 0
E34: =D34*C34 -> 0 | M34: =L34*K34 -> 0
E35: =D35*C35 -> 0 | M35: =L35*K35 -> 0
E36: =D36*C36 -> 0 | M36: =L36*K36 -> 0
B37: TOTAL | E37: =IF(SUM(E27:E36)=0,"",SUM(E27:E36)) -> 1079.55 | J37: TOTAL | M37: =IF(SUM(M27:M36)=0,"",SUM(M27:M36)) -> 2789.963
B39: UTILITY AND PREP. COST | J39: UTILITY AND PREP. COST
B40: Name | E40: Total Cost | J40: Name | M40: Total Cost
B41: Shorenting Oil | C41: ='UTL COST'!$B$3 -> 369000 | D41: ='UTL COST'!$C$3 -> 0.0075 | E41: 0 | J41: Shorenting Oil | K41: ='UTL COST'!$B$3 -> 369000 | L41: ='UTL COST'!$C$3 -> 0.0075 | M41: 0
B42: Gas | C42: ='UTL COST'!$B$4 -> #REF! | D42: ='UTL COST'!$C$4 -> 7000 | E42: ='UTL COST'!$D$4 -> #REF! | J42: Gas | K42: ='UTL COST'!$B$4 -> #REF! | L42: ='UTL COST'!$C$4 -> 7000 | M42: 0
B43: Electricity | C43: ='UTL COST'!$B$5 -> #REF! | D43: ='UTL COST'!$C$5 -> 45000 | E43: 0 | J43: Electricity | K43: ='UTL COST'!$B$5 -> #REF! | L43: ='UTL COST'!$C$5 -> 45000 | M43: 0
B44: Water | C44: ='UTL COST'!$B$6 -> #REF! | D44: ='UTL COST'!$C$6 -> 525 | E44: 0.1 | J44: Water | K44: ='UTL COST'!$B$6 -> #REF! | L44: ='UTL COST'!$C$6 -> 525 | M44: 0.1
B45: TOTAL | E45: =IF(SUM(E41:E44)=0,"",SUM(E41:E44)) -> #REF! | J45: TOTAL | M45: =IF(SUM(M41:M44)=0,"",SUM(M41:M44)) -> 0.1
B51: DISH NAME | C51: Chicken & CHicken | J51: DISH NAME | K51: Meat and Rice
B53: EST. SALE PPRICE | C53: 11 | J53: EST. SALE PPRICE | K53: 12
B55: TOTAL COST | C55: =IF(SUM(E67,E82,E90)=0,"",SUM(E67,E82,E90)) -> #REF! | J55: TOTAL COST | K55: =IF(SUM(M67,M82,M90)=0,"",SUM(M67,M82,M90)) -> #REF! | M55: =K55/90000 -> #REF!
B57: COST MARGIN | C57: =IF(C55="","",IF(ISBLANK(C53),"",C55/C53)) -> #REF! | J57: COST MARGIN | K57: =IF(K55="","",IF(ISBLANK(K53),"",K55/K53)) -> #REF!
B59: NET PROFIT | C59: =C53-C55 -> #REF! | J59: NET PROFIT | K59: =K53-K55 -> #REF!
B62: PRIMARY INGREDIENTS | J62: PRIMARY INGREDIENTS
B63: Product Name | C63: Qty. | D63: Cost (per unit) | E63: Total Cost | J63: Product Name | K63: Qty. | L63: Cost (per unit) | M63: Total Cost
B64: Rice | C64: 1 | D64: =E10 -> #REF! | E64: =IF(OR(ISBLANK(C64),ISBLANK(D64)),"",D64*C64) -> #REF! | J64: Rice | K64: 1 | L64: =D64 -> #REF! | M64: =IF(OR(ISBLANK(K64),ISBLANK(L64)),"",L64*K64) -> #REF!
B65: Chicken Breast | C65: 0.18 | D65: ='F&B'!F228 -> 81000 | E65: =IF(OR(ISBLANK(C65),ISBLANK(D65)),"",D65*C65) -> 14580 | J65: Meat Filet | K65: 0.16 | L65: ='F&B'!F212 -> 117000 | M65: =IF(OR(ISBLANK(K65),ISBLANK(L65)),"",L65*K65) -> 18720
B66: Sunflower Oil | C66: 0.015 | D66: ='F&B'!F106/8 -> 23107.5 | E66: =IF(OR(ISBLANK(C66),ISBLANK(D66)),"",D66*C66) -> 346.6125 | J66: Fresh Mushrooms | K66: 0.07 | L66: =D73 -> 103500 | M66: =IF(OR(ISBLANK(K66),ISBLANK(L66)),"",L66*K66) -> 7245
B67: TOTAL | E67: =IF(SUM(E64:E66)=0,"",SUM(E64:E66)) -> #REF! | J67: TOTAL | M67: =IF(SUM(M64:M66)=0,"",SUM(M64:M66)) -> #REF!
B69: SECONDARY INGREDIENTS | J69: SECONDARY INGREDIENTS
B70: Product Name | C70: Qty | D70: Cost | E70: Total Cost | J70: Product Name | K70: Qty | L70: Cost | M70: Total Cost
B72: Paprika | C72: 0.005 | D72: ='F&B'!F168 -> 42300 | E72: =D72*C72 -> 211.5 | J72: Cream Fresh | K72: 0.1 | L72: =D74 -> 58500 | M72: =L72*K72 -> 5850
B73: Fresh Mushrooms | C73: 0.05 | D73: ='F&B'!F278 -> 103500 | E73: =D73*C73 -> 5175 | J73: Green Salad | K73: 1 | L73: =D75 -> 7515.063 | M73: =L73*K73 -> 7515.063
B74: Cream Fresh | C74: 0.08 | D74: ='F&B'!F87 -> 58500 | E74: =D74*C74 -> 4680 | M74: 0
B75: Green Salad | C75: 1 | D75: =K10 -> 7515.063 | E75: =D75*C75 -> 7515.063 | L75: =T10 | M75: =L75*K75 -> 0
B76: Tomato Paste | C76: 0.015 | D76: ='F&B'!F62 -> 42075 | E76: =D76*C76 -> 631.125 | L76: ='F&B'!M62 | M76: =L76*K76 -> 0
M77: =L77*K77 -> 0
M78: =L78*K78 -> 0
E79: =D79*C79 -> 0 | M79: =L79*K79 -> 0
E80: =D80*C80 -> 0 | M80: =L80*K80 -> 0
E81: =D81*C81 -> 0 | M81: =L81*K81 -> 0
B82: TOTAL | E82: =IF(SUM(E72:E81)=0,"",SUM(E72:E81)) -> 18212.688 | J82: TOTAL | M82: =IF(SUM(M72:M81)=0,"",SUM(M72:M81)) -> 13365.063
B84: UTILITY AND PREP. COST | J84: UTILITY AND PREP. COST
B85: Name | E85: Total Cost | J85: Name | M85: Total Cost
B86: Shorenting Oil | C86: ='UTL COST'!$B$3 -> 369000 | D86: ='UTL COST'!$C$3 -> 0.0075 | E86: 22950 | J86: Shorenting Oil | K86: ='UTL COST'!$B$3 -> 369000 | L86: ='UTL COST'!$C$3 -> 0.0075 | M86: 0
B87: Gas | C87: ='UTL COST'!$B$4 -> #REF! | D87: ='UTL COST'!$C$4 -> 7000 | E87: ='UTL COST'!$D$4 -> #REF! | J87: Gas | K87: ='UTL COST'!$B$4 -> #REF! | L87: ='UTL COST'!$C$4 -> 7000 | M87: ='UTL COST'!$D$4 -> #REF!
B88: Electricity | C88: ='UTL COST'!$B$5 -> #REF! | D88: ='UTL COST'!$C$5 -> 45000 | E88: ='UTL COST'!$D$5 -> #REF! | J88: Electricity | K88: ='UTL COST'!$B$5 -> #REF! | L88: ='UTL COST'!$C$5 -> 45000 | M88: ='UTL COST'!$D$5 -> #REF!
B89: Water | C89: ='UTL COST'!$B$6 -> #REF! | D89: ='UTL COST'!$C$6 -> 525 | E89: 0.1 | J89: Water | K89: ='UTL COST'!$B$6 -> #REF! | L89: ='UTL COST'!$C$6 -> 525 | M89: 0.1
B90: TOTAL | E90: =IF(SUM(E86:E89)=0,"",SUM(E86:E89)) -> #REF! | J90: TOTAL | M90: =IF(SUM(M86:M89)=0,"",SUM(M86:M89)) -> #REF!
B97: DISH NAME | C97: Chicken Crispy and Rice
B99: EST. SALE PPRICE | C99: 11
B101: TOTAL COST | C101: =IF(SUM(E113,E128,E136)=0,"",SUM(E113,E128,E136)) -> #REF!
B103: COST MARGIN | C103: =IF(C101="","",IF(ISBLANK(C99),"",C101/C99)) -> #REF!
B105: NET PROFIT | C105: =C99-C101 -> #REF!
B108: PRIMARY INGREDIENTS
B109: Product Name | C109: Qty. | D109: Cost (per unit) | E109: Total Cost
B110: Rice | C110: 1 | D110: =D64 -> #REF! | E110: =IF(OR(ISBLANK(C110),ISBLANK(D110)),"",D110*C110) -> #REF!
B111: Chicken Breast | C111: 0.18 | D111: ='F&B'!F278 -> 103500 | E111: =IF(OR(ISBLANK(C111),ISBLANK(D111)),"",D111*C111) -> 18630
B112: Sunflower Oil | C112: 0.015 | D112: ='F&B'!F158/8 -> 10125 | E112: =IF(OR(ISBLANK(C112),ISBLANK(D112)),"",D112*C112) -> 151.875
B113: TOTAL | E113: =IF(SUM(E110:E112)=0,"",SUM(E110:E112)) -> #REF!
B115: SECONDARY INGREDIENTS
B116: Product Name | C116: Qty | D116: Cost | E116: Total Cost
B118: Paprika | C118: 0.005 | D118: ='F&B'!F217 -> 108000 | E118: =D118*C118 -> 540
B121: Green Salad | C121: 1 | D121: =K56 | E121: =D121*C121 -> 0
B122: Tomato Paste | C122: 0.015 | D122: ='F&B'!F113 -> 67500 | E122: =D122*C122 -> 1012.5
B123: Honey Mustard Sauce | C123: 1 | D123: =SAUCES!D179 -> 9000 | E123: =D123*C123 -> 9000
B124: Breading | C124: 1 | D124: =SAUCES!D94 | E124: =D124*C124 -> 0
E125: =D125*C125 -> 0
E126: =D126*C126 -> 0
E127: =D127*C127 -> 0
B128: TOTAL | E128: =IF(SUM(E118:E127)=0,"",SUM(E118:E127)) -> 10552.5
B130: UTILITY AND PREP. COST
B131: Name | E131: Total Cost
B132: Shorenting Oil | C132: ='UTL COST'!$B$3 -> 369000 | D132: ='UTL COST'!$C$3 -> 0.0075 | E132: 22950
B133: Gas | C133: ='UTL COST'!$B$4 -> #REF! | D133: ='UTL COST'!$C$4 -> 7000 | E133: ='UTL COST'!$D$4 -> #REF!
B134: Electricity | C134: ='UTL COST'!$B$5 -> #REF! | D134: ='UTL COST'!$C$5 -> 45000 | E134: ='UTL COST'!$D$5 -> #REF!
B135: Water | C135: ='UTL COST'!$B$6 -> #REF! | D135: ='UTL COST'!$C$6 -> 525 | E135: 0.1
B136: TOTAL | E136: =IF(SUM(E132:E135)=0,"",SUM(E132:E135)) -> #REF!

Sheet STARTERS
A1: STARTERS FOOD COST
B6: DISH NAME | C6: French Fries Large | K6: DISH NAME | L6: Wedges
B8: EST. SALE PPRICE | C8: =3.5*100000 -> 350000 | K8: EST. SALE PPRICE | L8: 70000
B10: TOTAL COST | C10: =IF(SUM(E22,E37,E45)=0,"",SUM(E22,E37,E45)) -> #REF! | E10: =C10/90000 -> #REF! | K10: TOTAL COST | L10: =IF(SUM(N22,N37,N45)=0,"",SUM(N22,N37,N45)) -> #REF!
B12: COST MARGIN | C12: =IF(C10="","",IF(ISBLANK(C8),"",C10/C8)) -> #REF! | K12: COST MARGIN | L12: =IF(L10="","",IF(ISBLANK(L8),"",L10/L8)) -> #REF!
B14: NET PROFIT | C14: =C8-C10 -> #REF! | K14: NET PROFIT | L14: =L8-L10 -> #REF!
B17: PRIMARY INGREDIENTS | K17: PRIMARY INGREDIENTS
B18: Product Name | C18: Qty. | D18: Cost (per unit) | E18: Total Cost | K18: Product Name | L18: Qty. | M18: Cost (per unit) | N18: Total Cost
B19: French Fries | C19: 0.4 | D19: ='F&B'!$F$68/10 -> 19665 | E19: =IF(OR(ISBLANK(C19),ISBLANK(D19)),"",D19*C19) -> 7866 | K19: French Fries | L19: 0.4 | M19: =D19 -> 19665 | N19: =IF(OR(ISBLANK(L19),ISBLANK(M19)),"",M19*L19) -> 7866
E21: =IF(OR(ISBLANK(C21),ISBLANK(D21)),"",D21*C21) | N21: =IF(OR(ISBLANK(L21),ISBLANK(M21)),"",M21*L21)
B22: TOTAL | E22: =IF(SUM(E19:E21)=0,"",SUM(E19:E21)) -> 7866 | K22: TOTAL | N22: =IF(SUM(N19:N21)=0,"",SUM(N19:N21)) -> 7866
B24: SECONDARY INGREDIENTS | K24: SECONDARY INGREDIENTS
B25: Product Name | C25: Qty | D25: Cost | E25: Total Cost | K25: Product Name | L25: Qty | M25: Cost | N25: Total Cost
E27: =D27*C27 -> 0 | K27: BBq Sauce | L27: 0.05 | M27: ='F&B'!$F$246/3.79 -> 56160.95 | N27: =M27*L27 -> 2808.0475
E28: =D28*C28 -> 0 | N28: =M28*L28 -> 0
E29: =D29*C29 -> 0 | N29: =M29*L29 -> 0
E30: =D30*C30 -> 0 | N30: =M30*L30 -> 0
E31: =D31*C31 -> 0 | N31: =M31*L31 -> 0
E32: =D32*C32 -> 0 | N32: =M32*L32 -> 0
E33: =D33*C33 -> 0 | N33: =M33*L33 -> 0
E34: =D34*C34 -> 0 | N34: =M34*L34 -> 0
E35: =D35*C35 -> 0 | N35: =M35*L35 -> 0
E36: =D36*C36 -> 0 | N36: =M36*L36 -> 0
B37: TOTAL | E37: =IF(SUM(E27:E36)=0,"",SUM(E27:E36)) | K37: TOTAL | N37: =IF(SUM(N27:N36)=0,"",SUM(N27:N36)) -> 2808.0475
B39: UTILITY AND PREP. COST | K39: UTILITY AND PREP. COST
B40: Name | E40: Total Cost | K40: Name | N40: Total Cost
B41: Shorenting Oil | C41: ='UTL COST'!$B$3 -> 369000 | D41: ='UTL COST'!$C$3 -> 0.0075 | E41: ='UTL COST'!$D$3 -> 2767.5 | K41: Shorenting Oil | L41: ='UTL COST'!$B$3 -> 369000 | M41: ='UTL COST'!$C$3 -> 0.0075 | N41: ='UTL COST'!$D$3 -> 2767.5
B42: Gas | C42: ='UTL COST'!$B$4 -> #REF! | D42: ='UTL COST'!$C$4 -> 7000 | E42: ='UTL COST'!$D$4 -> #REF! | K42: Gas | L42: ='UTL COST'!$B$4 -> #REF! | M42: ='UTL COST'!$C$4 -> 7000 | N42: ='UTL COST'!$D$4 -> #REF!
B43: Electricity | C43: ='UTL COST'!$B$5 -> #REF! | D43: ='UTL COST'!$C$5 -> 45000 | E43: ='UTL COST'!$D$5 -> #REF! | K43: Electricity | L43: ='UTL COST'!$B$5 -> #REF! | M43: ='UTL COST'!$C$5 -> 45000 | N43: ='UTL COST'!$D$5 -> #REF!
B44: Water | C44: ='UTL COST'!$B$6 -> #REF! | D44: ='UTL COST'!$C$6 -> 525 | E44: 0.1 | K44: Water | L44: ='UTL COST'!$B$6 -> #REF! | M44: ='UTL COST'!$C$6 -> 525 | N44: 0.1
B45: TOTAL | E45: =IF(SUM(E41:E44)=0,"",SUM(E41:E44)) -> #REF! | K45: TOTAL | N45: =IF(SUM(N41:N44)=0,"",SUM(N41:N44)) -> #REF!
B50: DISH NAME | C50: Baked Potato | K50: DISH NAME | L50: Cheese Garlic
B52: EST. SALE PPRICE | C52: 53000 | K52: EST. SALE PPRICE | L52: 82000
B54: TOTAL COST | C54: =IF(SUM(E66,E81,E89)=0,"",SUM(E66,E81,E89)) -> #REF! | K54: TOTAL COST | L54: =IF(SUM(N66,N81,N89)=0,"",SUM(N66,N81,N89)) -> #REF!
B56: COST MARGIN | C56: =IF(C54="","",IF(ISBLANK(C52),"",C54/C52)) -> #REF! | K56: COST MARGIN | L56: =IF(L54="","",IF(ISBLANK(L52),"",L54/L52)) -> #REF!
B58: NET PROFIT | C58: =C52-C54 -> #REF! | K58: NET PROFIT | L58: =L52-L54 -> #REF!
B61: PRIMARY INGREDIENTS | K61: PRIMARY INGREDIENTS
B62: Product Name | C62: Qty. | D62: Cost (per unit) | E62: Total Cost | K62: Product Name | L62: Qty. | M62: Cost (per unit) | N62: Total Cost
B63: Potato | C63: 0.4 | D63: ='F&B'!$F$281 -> 5400 | E63: =IF(OR(ISBLANK(C63),ISBLANK(D63)),"",D63*C63) -> 2160 | K63: Mozzarella Cheese | L63: 0.06 | M63: ='F&B'!$F$99/12 -> 63000 | N63: =IF(OR(ISBLANK(L63),ISBLANK(M63)),"",M63*L63) -> 3780
K64: Garlic Butter | L64: 0.08 | M64: =SAUCES!D107 -> 13438.658 | N64: =IF(OR(ISBLANK(L64),ISBLANK(M64)),"",M64*L64) -> 1075.0927
E65: =IF(OR(ISBLANK(C65),ISBLANK(D65)),"",D65*C65) | K65: Ciabatta Bread | L65: 0.5 | M65: ='F&B'!$F$15/40 -> 5296.5 | N65: =IF(OR(ISBLANK(L65),ISBLANK(M65)),"",M65*L65) -> 2648.25
B66: TOTAL | E66: =IF(SUM(E63:E65)=0,"",SUM(E63:E65)) -> 2160 | K66: TOTAL | N66: =IF(SUM(N63:N65)=0,"",SUM(N63:N65)) -> 7503.3427
B68: SECONDARY INGREDIENTS | K68: SECONDARY INGREDIENTS
B69: Product Name | C69: Qty | D69: Cost | E69: Total Cost | K69: Product Name | L69: Qty | M69: Cost | N69: Total Cost
B71: Sour Cream | C71: 1 | D71: =SAUCES!D105 -> 2661.6611 | E71: =D71*C71 -> 2661.6611 | N71: =M71*L71 -> 0
E72: =D72*C72 -> 0 | N72: =M72*L72 -> 0
E73: =D73*C73 -> 0 | N73: =M73*L73 -> 0
E74: =D74*C74 -> 0 | N74: =M74*L74 -> 0
E75: =D75*C75 -> 0 | N75: =M75*L75 -> 0
E76: =D76*C76 -> 0 | N76: =M76*L76 -> 0
E77: =D77*C77 -> 0 | N77: =M77*L77 -> 0
E78: =D78*C78 -> 0 | N78: =M78*L78 -> 0
E79: =D79*C79 -> 0 | N79: =M79*L79 -> 0
E80: =D80*C80 -> 0 | N80: =M80*L80 -> 0
B81: TOTAL | E81: =IF(SUM(E71:E80)=0,"",SUM(E71:E80)) -> 2661.6611 | K81: TOTAL | N81: =IF(SUM(N71:N80)=0,"",SUM(N71:N80))
B83: UTILITY AND PREP. COST | K83: UTILITY AND PREP. COST
B84: Name | E84: Total Cost | K84: Name | N84: Total Cost
B85: Shorenting Oil | C85: ='UTL COST'!$B$3 -> 369000 | D85: ='UTL COST'!$C$3 -> 0.0075 | E85: 0 | K85: Shorenting Oil | L85: ='UTL COST'!$B$3 -> 369000 | M85: ='UTL COST'!$C$3 -> 0.0075 | N85: 0
B86: Gas | C86: ='UTL COST'!$B$4 -> #REF! | D86: ='UTL COST'!$C$4 -> 7000 | E86: ='UTL COST'!$D$4 -> #REF! | K86: Gas | L86: ='UTL COST'!$B$4 -> #REF! | M86: ='UTL COST'!$C$4 -> 7000 | N86: ='UTL COST'!$D$4 -> #REF!
B87: Electricity | C87: ='UTL COST'!$B$5 -> #REF! | D87: ='UTL COST'!$C$5 -> 45000 | E87: ='UTL COST'!$D$5 -> #REF! | K87: Electricity | L87: ='UTL COST'!$B$5 -> #REF! | M87: ='UTL COST'!$C$5 -> 45000 | N87: ='UTL COST'!$D$5 -> #REF!
B88: Water | C88: ='UTL COST'!$B$6 -> #REF! | D88: ='UTL COST'!$C$6 -> 525 | E88: 0.1 | K88: Water | L88: ='UTL COST'!$B$6 -> #REF! | M88: ='UTL COST'!$C$6 -> 525 | N88: 0.1
B89: TOTAL | E89: =IF(SUM(E85:E88)=0,"",SUM(E85:E88)) -> #REF! | K89: TOTAL | N89: =IF(SUM(N85:N88)=0,"",SUM(N85:N88)) -> #REF!
B95: DISH NAME | C95: Cheese Nachos | K95: DISH NAME | L95: Chicken Wings
B97: EST. SALE PPRICE | C97: 135000 | K97: EST. SALE PPRICE | L97: 90000
B99: TOTAL COST | C99: =IF(SUM(E111,E126,E134)=0,"",SUM(E111,E126,E134)) -> #REF! | K99: TOTAL COST | L99: =IF(SUM(N111,N126,N134)=0,"",SUM(N111,N126,N134)) -> #REF! | N99: =L99/90000 -> #REF!
B101: COST MARGIN | C101: =IF(C99="","",IF(ISBLANK(C97),"",C99/C97)) -> #REF! | K101: COST MARGIN | L101: =IF(L99="","",IF(ISBLANK(L97),"",L99/L97)) -> #REF!
B103: NET PROFIT | C103: =C97-C99 -> #REF! | K103: NET PROFIT | L103: =L97-L99 -> #REF!
B106: PRIMARY INGREDIENTS | K106: PRIMARY INGREDIENTS
B107: Product Name | C107: Qty. | D107: Cost (per unit) | E107: Total Cost | K107: Product Name | L107: Qty. | M107: Cost (per unit) | N107: Total Cost
B108: Tortilla Bread | C108: 0.12 | D108: ='F&B'!$F$28/10 -> 58500 | E108: =IF(OR(ISBLANK(C108),ISBLANK(D108)),"",D108*C108) -> 7020 | K108: Wings | L108: 0.3 | M108: ='F&B'!F232 -> 27810 | N108: =IF(OR(ISBLANK(L108),ISBLANK(M108)),"",M108*L108) -> 8343
B109: Cheddar Cheese | C109: 0.05 | D109: ='F&B'!F80 -> 103500 | E109: =IF(OR(ISBLANK(C109),ISBLANK(D109)),"",D109*C109) -> 5175
B110: Mozzarella Cheese | C110: 0.1 | D110: =M63 -> 63000 | E110: =IF(OR(ISBLANK(C110),ISBLANK(D110)),"",D110*C110) -> 6300 | N110: =IF(OR(ISBLANK(L110),ISBLANK(M110)),"",M110*L110)
B111: TOTAL | E111: =IF(SUM(E108:E110)=0,"",SUM(E108:E110)) -> 18495 | K111: TOTAL | N111: =IF(SUM(N108:N110)=0,"",SUM(N108:N110)) -> 8343
B113: SECONDARY INGREDIENTS | K113: SECONDARY INGREDIENTS
B114: Product Name | C114: Qty | D114: Cost | E114: Total Cost | K114: Product Name | L114: Qty | M114: Cost | N114: Total Cost
B116: Sour Cream Sauce | C116: 1 | D116: =SAUCES!D105 -> 2661.6611 | E116: =D116*C116 -> 2661.6611 | K116: BBQ Sauce | L116: 0.05 | M116: ='F&B'!$F$246/3.79 -> 56160.95 | N116: 0
B117: Mexican Sauce | C117: 1 | D117: =SAUCES!$L$105 -> 1090.9416 | E117: =D117*C117 -> 1090.9416 | K117: Buffalo Sauce | L117: 0.1 | M117: ='F&B'!$F$258/3.75 -> 55440 | N117: =M117*L117 -> 5544
E118: =D118*C118 -> 0 | N118: 0
E119: =D119*C119 -> 0 | N119: =M119*L119 -> 0
E120: =D120*C120 -> 0 | N120: =M120*L120 -> 0
E121: =D121*C121 -> 0 | N121: =M121*L121 -> 0
E122: =D122*C122 -> 0 | N122: =M122*L122 -> 0
E123: =D123*C123 -> 0 | N123: =M123*L123 -> 0
E124: =D124*C124 -> 0 | N124: =M124*L124 -> 0
E125: =D125*C125 -> 0 | N125: =M125*L125 -> 0
B126: TOTAL | E126: =IF(SUM(E116:E125)=0,"",SUM(E116:E125)) -> 3752.6026 | K126: TOTAL | N126: =IF(SUM(N116:N125)=0,"",SUM(N116:N125)) -> 5544
B128: UTILITY AND PREP. COST | K128: UTILITY AND PREP. COST
B129: Name | E129: Total Cost | K129: Name | N129: Total Cost
B130: Shorenting Oil | C130: ='UTL COST'!$B$3 -> 369000 | D130: ='UTL COST'!$C$3 -> 0.0075 | E130: ='UTL COST'!$D$3/5 -> 553.5 | K130: Shorenting Oil | L130: ='UTL COST'!$B$3 -> 369000 | M130: ='UTL COST'!$C$3 -> 0.0075 | N130: ='UTL COST'!$D$3 -> 2767.5
B131: Gas | C131: ='UTL COST'!$B$4 -> #REF! | D131: ='UTL COST'!$C$4 -> 7000 | E131: ='UTL COST'!$D$3/5 -> 553.5 | K131: Gas | L131: ='UTL COST'!$B$4 -> #REF! | M131: ='UTL COST'!$C$4 -> 7000 | N131: ='UTL COST'!$D$4 -> #REF!
B132: Electricity | C132: ='UTL COST'!$B$5 -> #REF! | D132: ='UTL COST'!$C$5 -> 45000 | E132: ='UTL COST'!$D$5 -> #REF! | K132: Electricity | L132: ='UTL COST'!$B$5 -> #REF! | M132: ='UTL COST'!$C$5 -> 45000 | N132: ='UTL COST'!$D$5 -> #REF!
B133: Water | C133: ='UTL COST'!$B$6 -> #REF! | D133: ='UTL COST'!$C$6 -> 525 | E133: 0.1 | K133: Water | L133: ='UTL COST'!$B$6 -> #REF! | M133: ='UTL COST'!$C$6 -> 525 | N133: 0.1
B134: TOTAL | E134: =IF(SUM(E130:E133)=0,"",SUM(E130:E133)) -> #REF! | K134: TOTAL | N134: =IF(SUM(N130:N133)=0,"",SUM(N130:N133)) -> #REF!
B140: DISH NAME | C140: Chicken Tenders | K140: DISH NAME | L140: Mozzarella Sticks
B142: EST. SALE PPRICE | C142: 120000 | K142: EST. SALE PPRICE | L142: 190000
B144: TOTAL COST | C144: =IF(SUM(E156,E171,E179)=0,"",SUM(E156,E171,E179)) -> #REF! | H144: =C144/90000 -> #REF! | I144: =L144/90000 -> #REF! | K144: TOTAL COST | L144: =IF(SUM(N156,N171,N179)=0,"",SUM(N156,N171,N179)) -> #REF!
B146: COST MARGIN | C146: =IF(C144="","",IF(ISBLANK(C142),"",C144/C142)) -> #REF! | K146: COST MARGIN | L146: =IF(L144="","",IF(ISBLANK(L142),"",L144/L142)) -> #REF!
B148: NET PROFIT | C148: =C142-C144 -> #REF! | K148: NET PROFIT | L148: =L142-L144 -> #REF!
B151: PRIMARY INGREDIENTS | K151: PRIMARY INGREDIENTS
B152: Product Name | C152: Qty. | D152: Cost (per unit) | E152: Total Cost | K152: Product Name | L152: Qty. | M152: Cost (per unit) | N152: Total Cost
...

Sheet MAINS
A1: MAINS FOOD COST
B6: DISH NAME | C6: Escalope | K6: DISH NAME | L6: Grilled Chicken
B8: EST. SALE PPRICE | C8: 205000 | K8: EST. SALE PPRICE | L8: 245000
B10: TOTAL COST | C10: =IF(SUM(E22,E37,E45)=0,"",SUM(E22,E37,E45)) -> #REF! | K10: TOTAL COST | L10: =IF(SUM(N22,N37,N45)=0,"",SUM(N22,N37,N45)) -> #REF! | N10: =L10/90000 -> #REF!
B12: COST MARGIN | C12: =IF(C10="","",IF(ISBLANK(C8),"",C10/C8)) -> #REF! | K12: COST MARGIN | L12: =IF(L10="","",IF(ISBLANK(L8),"",L10/L8)) -> #REF!
B14: NET PROFIT | C14: =C8-C10 -> #REF! | K14: NET PROFIT | L14: =L8-L10 -> #REF!
B17: PRIMARY INGREDIENTS | K17: PRIMARY INGREDIENTS
B18: Product Name | C18: Qty. | D18: Cost (per unit) | E18: Total Cost | K18: Product Name | L18: Qty. | M18: Cost (per unit) | N18: Total Cost
B19: Grilled Chicken | C19: 0.28 | D19: =SANDWICHES!$D$19 -> 81000 | E19: =IF(OR(ISBLANK(C19),ISBLANK(D19)),"",D19*C19) -> 22680 | H19: =E19/90000 -> 0.252 | K19: Grilled Chicken | L19: 0.28 | M19: =SANDWICHES!$D$19 -> 81000 | N19: =IF(OR(ISBLANK(L19),ISBLANK(M19)),"",M19*L19) -> 22680
B20: French Fries | C20: 0.16 | D20: =STARTERS!$D$19 -> 19665 | E20: =IF(OR(ISBLANK(C20),ISBLANK(D20)),"",D20*C20) -> 3146.4 | K20: French Fries | L20: 0.2 | M20: =STARTERS!$D$19 -> 19665 | N20: =IF(OR(ISBLANK(L20),ISBLANK(M20)),"",M20*L20) -> 3933
B22: TOTAL | E22: =IF(SUM(E19:E21)=0,"",SUM(E19:E21)) -> 25826.4 | K22: TOTAL | N22: =IF(SUM(N19:N21)=0,"",SUM(N19:N21)) -> 26613
B24: SECONDARY INGREDIENTS | K24: SECONDARY INGREDIENTS
B25: Product Name | C25: Qty | D25: Cost | E25: Total Cost | K25: Product Name | L25: Qty | M25: Cost | N25: Total Cost
B27: Coleslaw | C27: 1 | D27: =SAUCES!$L$58 -> 923.2488 | E27: =D27*C27 -> 923.2488 | K27: Green Salad | L27: 0.3 | M27: =SAUCES!$D$68 -> 3768.1048 | N27: =M27*L27 -> 1130.4314
B28: Garnish | C28: 1 | D28: =SAUCES!$L$44 | E28: =D28*C28 -> 0 | N28: =M28*L28 -> 0
B29: Breaded | C29: 0.5 | D29: =SAUCES!$D$48 -> 563.76 | E29: =D29*C29 -> 281.88 | N29: =M29*L29 -> 0
B30: Pickles | C30: 0.02 | D30: ='F&B'!$F$49/10 -> 13500 | E30: =D30*C30 -> 270 | N30: =M30*L30 -> 0
E31: =D31*C31 -> 0 | N31: =M31*L31 -> 0
E32: =D32*C32 -> 0 | N32: =M32*L32 -> 0
E33: =D33*C33 -> 0 | N33: =M33*L33 -> 0
E34: =D34*C34 -> 0 | N34: =M34*L34 -> 0
E35: =D35*C35 -> 0 | N35: =M35*L35 -> 0
E36: =D36*C36 -> 0 | N36: =M36*L36 -> 0
B37: TOTAL | E37: =IF(SUM(E27:E36)=0,"",SUM(E27:E36)) -> 1475.1288 | K37: TOTAL | N37: =IF(SUM(N27:N36)=0,"",SUM(N27:N36)) -> 1130.4314
B39: UTILITY AND PREP. COST | K39: UTILITY AND PREP. COST
B40: Name | E40: Total Cost | K40: Name | N40: Total Cost
B41: Shorenting Oil | C41: ='UTL COST'!$B$3 -> 369000 | D41: ='UTL COST'!$C$3 -> 0.0075 | E41: ='UTL COST'!$D$3 -> 2767.5 | K41: Shorenting Oil | L41: ='UTL COST'!$B$3 -> 369000 | M41: ='UTL COST'!$C$3 -> 0.0075 | N41: =E41 -> 2767.5
B42: Gas | C42: ='UTL COST'!$B$4 -> #REF! | D42: ='UTL COST'!$C$4 -> 7000 | E42: ='UTL COST'!$D$4 -> #REF! | K42: Gas | L42: ='UTL COST'!$B$4 -> #REF! | M42: ='UTL COST'!$C$4 -> 7000 | N42: ='UTL COST'!$D$4 -> #REF!
B43: Electricity | C43: ='UTL COST'!$B$5 -> #REF! | D43: ='UTL COST'!$C$5 -> 45000 | E43: ='UTL COST'!$D$5 -> #REF! | K43: Electricity | L43: ='UTL COST'!$B$5 -> #REF! | M43: ='UTL COST'!$C$5 -> 45000 | N43: ='UTL COST'!$D$5 -> #REF!
B44: Water | C44: ='UTL COST'!$B$6 -> #REF! | D44: ='UTL COST'!$C$6 -> 525 | E44: 0.1 | K44: Water | L44: ='UTL COST'!$B$6 -> #REF! | M44: ='UTL COST'!$C$6 -> 525 | N44: 0.1
B45: TOTAL | E45: =IF(SUM(E41:E44)=0,"",SUM(E41:E44)) -> #REF! | K45: TOTAL | N45: =IF(SUM(N41:N44)=0,"",SUM(N41:N44)) -> #REF!
B50: DISH NAME | C50: Taouk | K50: DISH NAME | L50: Grilled Chicken Mushrooms
B52: EST. SALE PPRICE | C52: 190000 | K52: EST. SALE PPRICE | L52: 220000
B54: TOTAL COST | C54: =IF(SUM(E66,E81,E89)=0,"",SUM(E66,E81,E89)) -> #REF! | K54: TOTAL COST | L54: =IF(SUM(N66,N81,N89)=0,"",SUM(N66,N81,N89)) -> #REF!
B56: COST MARGIN | C56: =IF(C54="","",IF(ISBLANK(C52),"",C54/C52)) -> #REF! | K56: COST MARGIN | L56: =IF(L54="","",IF(ISBLANK(L52),"",L54/L52)) -> #REF!
B58: NET PROFIT | C58: =C52-C54 -> #REF! | K58: NET PROFIT | L58: =L52-L54 -> #REF!
B61: PRIMARY INGREDIENTS | K61: PRIMARY INGREDIENTS
B62: Product Name | C62: Qty. | D62: Cost (per unit) | E62: Total Cost | K62: Product Name | L62: Qty. | M62: Cost (per unit) | N62: Total Cost
B63: Grilled Chicken | C63: 0.3 | D63: =SANDWICHES!$D$19 -> 81000 | E63: =IF(OR(ISBLANK(C63),ISBLANK(D63)),"",D63*C63) -> 24300 | K63: Grilled Chicken | L63: 0.3 | M63: =SANDWICHES!$D$19 -> 81000 | N63: =IF(OR(ISBLANK(L63),ISBLANK(M63)),"",M63*L63) -> 24300 | O63: =N63/$L$54 -> #REF!
B64: French Fries | C64: 0.2 | D64: =STARTERS!$D$19 -> 19665 | E64: =IF(OR(ISBLANK(C64),ISBLANK(D64)),"",D64*C64) -> 3933 | K64: French Fries | L64: 0.2 | M64: =STARTERS!$D$19 -> 19665 | N64: =IF(OR(ISBLANK(L64),ISBLANK(M64)),"",M64*L64) -> 3933 | O64: =N64/$L$54 -> #REF!
E65: =IF(OR(ISBLANK(C65),ISBLANK(D65)),"",D65*C65)
B66: TOTAL | E66: =IF(SUM(E63:E65)=0,"",SUM(E63:E65)) -> 28233 | K66: TOTAL | N66: =IF(SUM(N63:N65)=0,"",SUM(N63:N65)) -> 28233
B68: SECONDARY INGREDIENTS | K68: SECONDARY INGREDIENTS
B69: Product Name | C69: Qty | D69: Cost | E69: Total Cost | K69: Product Name | L69: Qty | M69: Cost | N69: Total Cost
B71: Garlic Paste | C71: 1 | D71: =SAUCES!$L$34 -> 480.44813 | E71: =D71*C71 -> 480.44813 | K71: Green Salad | L71: 1 | M71: =M27 -> 3768.1048 | N71: =M71*L71 -> 3768.1048 | O71: =N71/$L$54 -> #REF!
B72: Pickles | C72: 0.01 | D72: ='F&B'!$F$49/10 -> 13500 | E72: =D72*C72 -> 135 | K72: Mushroom Sauce | L72: 2 | M72: =SAUCES!$L$92 -> 2481.9702 | N72: =M72*L72 -> 4963.9405 | O72: =N72/$L$54 -> #REF!
B73: Coleslaw | C73: 1 | D73: =D27 -> 923.2488 | E73: =D73*C73 -> 923.2488 | N73: =M73*L73 -> 0
B74: Arabic Bread | C74: 1 | D74: ='F&B'!F4/9 -> 970 | E74: =D74*C74 -> 970 | N74: =M74*L74 -> 0
B75: Chili Paste | C75: 0.03 | D75: ='F&B'!F50 -> 27000 | E75: =D75*C75 -> 810 | N75: =M75*L75 -> 0
E76: =D76*C76 -> 0 | N76: =M76*L76 -> 0
E77: =D77*C77 -> 0 | N77: =M77*L77 -> 0
E78: =D78*C78 -> 0 | N78: =M78*L78 -> 0
E79: =D79*C79 -> 0 | N79: =M79*L79 -> 0
E80: =D80*C80 -> 0 | N80: =M80*L80 -> 0
B81: TOTAL | E81: =IF(SUM(E71:E80)=0,"",SUM(E71:E80)) -> 3318.6969 | K81: TOTAL | N81: =IF(SUM(N71:N80)=0,"",SUM(N71:N80)) -> 8732.0453
B83: UTILITY AND PREP. COST | K83: UTILITY AND PREP. COST
B84: Name | E84: Total Cost | K84: Name | N84: Total Cost
B85: Shorenting Oil | C85: ='UTL COST'!$B$3 -> 369000 | D85: ='UTL COST'!$C$3 -> 0.0075 | E85: =N85 -> 2767.5 | K85: Shorenting Oil | L85: ='UTL COST'!$B$3 -> 369000 | M85: ='UTL COST'!$C$3 -> 0.0075 | N85: =E41 -> 2767.5 | O85: =N85/$N$89 -> #REF!
B86: Gas | C86: ='UTL COST'!$B$4 -> #REF! | D86: ='UTL COST'!$C$4 -> 7000 | E86: ='UTL COST'!$D$4 -> #REF! | K86: Gas | L86: ='UTL COST'!$B$4 -> #REF! | M86: ='UTL COST'!$C$4 -> 7000 | N86: ='UTL COST'!$D$4 -> #REF! | O86: =N86/$N$89 -> #REF!
B87: Electricity | C87: ='UTL COST'!$B$5 -> #REF! | D87: ='UTL COST'!$C$5 -> 45000 | E87: ='UTL COST'!$D$5 -> #REF! | K87: Electricity | L87: ='UTL COST'!$B$5 -> #REF! | M87: ='UTL COST'!$C$5 -> 45000 | N87: ='UTL COST'!$D$5 -> #REF! | O87: =N87/$N$89 -> #REF!
B88: Water | C88: ='UTL COST'!$B$6 -> #REF! | D88: ='UTL COST'!$C$6 -> 525 | E88: 0.1 | K88: Water | L88: ='UTL COST'!$B$6 -> #REF! | M88: ='UTL COST'!$C$6 -> 525 | N88: 0.1 | O88: =N88/$N$89 -> #REF!
B89: TOTAL | E89: =IF(SUM(E85:E88)=0,"",SUM(E85:E88)) -> #REF! | K89: TOTAL | N89: =IF(SUM(N85:N88)=0,"",SUM(N85:N88)) -> #REF!
B95: DISH NAME | C95: Steak | K95: DISH NAME | L95: Chicken Fajita
B97: EST. SALE PPRICE | C97: 350000 | K97: EST. SALE PPRICE | L97: 210000
B99: TOTAL COST | C99: =IF(SUM(E111,E126,E134)=0,"",SUM(E111,E126,E134)) -> #REF! | K99: TOTAL COST | L99: =IF(SUM(N111,N126,N134)=0,"",SUM(N111,N126,N134)) -> #REF!
F100: =C99/90000 -> #REF!
B101: COST MARGIN | C101: =IF(C99="","",IF(ISBLANK(C97),"",C99/C97)) -> #REF! | K101: COST MARGIN | L101: =IF(L99="","",IF(ISBLANK(L97),"",L99/L97)) -> #REF!
B103: NET PROFIT | C103: =C97-C99 -> #REF! | K103: NET PROFIT | L103: =L97-L99 -> #REF!
B106: PRIMARY INGREDIENTS | K106: PRIMARY INGREDIENTS
B107: Product Name | C107: Qty. | D107: Cost (per unit) | E107: Total Cost | K107: Product Name | L107: Qty. | M107: Cost (per unit) | N107: Total Cost
B108: Beef Filet | C108: 0.22 | D108: ='F&B'!$F$215 -> 198000 | E108: =IF(OR(ISBLANK(C108),ISBLANK(D108)),"",D108*C108) -> 43560 | K108: Grilled Chicken | L108: 0.28 | M108: =SANDWICHES!$D$19 -> 81000 | N108: =IF(OR(ISBLANK(L108),ISBLANK(M108)),"",M108*L108) -> 22680
B109: French Fries | C109: 0.16 | D109: =STARTERS!$D$19 -> 19665 | E109: =IF(OR(ISBLANK(C109),ISBLANK(D109)),"",D109*C109) -> 3146.4 | N109: =IF(OR(ISBLANK(L109),ISBLANK(M109)),"",M109*L109)
B111: TOTAL | E111: =IF(SUM(E108:E110)=0,"",SUM(E108:E110)) -> 46706.4 | K111: TOTAL | N111: =IF(SUM(N108:N110)=0,"",SUM(N108:N110)) -> 22680
B113: SECONDARY INGREDIENTS | K113: SECONDARY INGREDIENTS
B114: Product Name | C114: Qty | D114: Cost | E114: Total Cost | K114: Product Name | L114: Qty | M114: Cost | N114: Total Cost
B116: Caesar Salad | C116: 0.2 | D116: =SALADS!$C$54 -> #REF! | E116: =D116*C116 -> #REF! | K116: Bell Peppers | L116: 0.035 | M116: ='F&B'!$F$296 -> 9000 | N116: =M116*L116 -> 315
B117: Mushroom Sauce | C117: 2 | D117: =SAUCES!$L$92 -> 2481.9702 | E117: =D117*C117 -> 4963.9405 | K117: Onions | L117: 0.035 | M117: ='F&B'!$F$290 -> 6300 | N117: =M117*L117 -> 220.5
C118: 0 | E118: =D118*C118 -> 0 | K118: Fresh Mushrooms | L118: 0.035 | M118: ='F&B'!$F$278 -> 103500 | N118: =M118*L118 -> 3622.5
C119: 0 | E119: =D119*C119 -> 0 | K119: Tortilla Flour Bread | L119: 0.105 | M119: ='F&B'!$F$29/12 -> 48750 | N119: =M119*L119 -> 5118.75
K120: Cheddar Shredded | L120: 0.03 | M120: ='F&B'!$F$80 -> 103500 | N120: =M120*L120 -> 3105
E121: =D121*C121 -> 0 | K121: Sour Cream Sauce | L121: 1 | M121: =SAUCES!$D$105 -> 2661.6611 | N121: =M121*L121 -> 2661.6611
E122: =D122*C122 -> 0 | K122: Mexican Sauce | L122: 1 | M122: =SAUCES!$L$105 -> 1090.9416 | N122: =M122*L122 -> 1090.9416
E123: =D123*C123 -> 0 | K123: Mozzarella Cheese | L123: 0.02 | M123: ='F&B'!F100/12 -> 50250 | N123: =M123*L123 -> 1005
E124: =D124*C124 -> 0 | N124: =M124*L124 -> 0
E125: =D125*C125 -> 0 | N125: =M125*L125 -> 0
B126: TOTAL | E126: =IF(SUM(E116:E125)=0,"",SUM(E116:E125)) -> #REF! | K126: TOTAL | N126: =IF(SUM(N116:N125)=0,"",SUM(N116:N125)) -> 17139.353
B128: UTILITY AND PREP. COST | K128: UTILITY AND PREP. COST
B129: Name | E129: Total Cost | K129: Name | N129: Total Cost
B130: Shorenting Oil | C130: ='UTL COST'!$B$3 -> 369000 | D130: ='UTL COST'!$C$3 -> 0.0075 | E130: ='UTL COST'!$D$3 -> 2767.5 | K130: Shorenting Oil | L130: ='UTL COST'!$B$3 -> 369000 | M130: ='UTL COST'!$C$3 -> 0.0075 | N130: =E130 -> 2767.5
B131: Gas | C131: ='UTL COST'!$B$4 -> #REF! | D131: ='UTL COST'!$C$4 -> 7000 | E131: ='UTL COST'!$D$4 -> #REF! | K131: Gas | L131: ='UTL COST'!$B$4 -> #REF! | M131: ='UTL COST'!$C$4 -> 7000 | N131: ='UTL COST'!$D$4 -> #REF!
B132: Electricity | C132: ='UTL COST'!$B$5 -> #REF! | D132: ='UTL COST'!$C$5 -> 45000 | E132: ='UTL COST'!$D$5 -> #REF! | K132: Electricity | L132: ='UTL COST'!$B$5 -> #REF! | M132: ='UTL COST'!$C$5 -> 45000 | N132: ='UTL COST'!$D$5 -> #REF!
B133: Water | C133: ='UTL COST'!$B$6 -> #REF! | D133: ='UTL COST'!$C$6 -> 525 | E133: 0.1 | K133: Water | L133: ='UTL COST'!$B$6 -> #REF! | M133: ='UTL COST'!$C$6 -> 525 | N133: 0.1
B134: TOTAL | E134: =IF(SUM(E130:E133)=0,"",SUM(E130:E133)) -> #REF! | K134: TOTAL | N134: =IF(SUM(N130:N133)=0,"",SUM(N130:N133)) -> #REF!
B140: DISH NAME | C140: Beef Fajita | K140: DISH NAME | L140: Shrimps Fajita
B142: EST. SALE PPRICE | C142: 200000 | K142: EST. SALE PPRICE | L142: 250000
B144: TOTAL COST | C144: =IF(SUM(E156,E171,E179)=0,"",SUM(E156,E171,E179)) -> #REF! | K144: TOTAL COST | L144: =IF(SUM(N156,N171,N179)=0,"",SUM(N156,N171,N179)) -> #REF!
B146: COST MARGIN | C146: =IF(C144="","",IF(ISBLANK(C142),"",C144/C142)) -> #REF! | K146: COST MARGIN | L146: =IF(L144="","",IF(ISBLANK(L142),"",L144/L142)) -> #REF!
B148: NET PROFIT | C148: =C142-C144 -> #REF! | K148: NET PROFIT | L148: =L142-L144 -> #REF!
B151: PRIMARY INGREDIENTS | K151: PRIMARY INGREDIENTS
B152: Product Name | C152: Qty. | D152: Cost (per unit) | E152: Total Cost | K152: Product Name | L152: Qty. | M152: Cost (per unit) | N152: Total Cost
...

Sheet Ramadan
A1: FOUL & HOMMOS FOOD COST
B6: DISH NAME | C6: Foul | K6: DISH NAME | L6: Veggie Plate
B8: EST. SALE PPRICE | C8: =C10/90000 -> #REF! | K8: EST. SALE PPRICE | L8: =L10/90000 -> 0.086407143
B10: TOTAL COST | C10: =IF(SUM(E22,E37,E45)=0,"",SUM(E22,E37,E45)) -> #REF! | E10: =C10/90000 -> #REF! | K10: TOTAL COST | L10: =IF(SUM(N22,N37,N45)=0,"",SUM(N22,N37,N45)) -> 7776.6429
B12: COST MARGIN | C12: =IF(C10="","",IF(ISBLANK(C8),"",C10/C8)) -> #REF! | K12: COST MARGIN | L12: =IF(L10="","",IF(ISBLANK(L8),"",L10/L8)) -> 90000
B14: NET PROFIT | C14: =C8-C10 -> #REF! | K14: NET PROFIT | L14: =L8-L10 -> -7776.5565
B17: PRIMARY INGREDIENTS | K17: PRIMARY INGREDIENTS
B18: Product Name | C18: Qty. | D18: Cost (per unit) | E18: Total Cost | K18: Product Name | L18: Qty. | M18: Cost (per unit) | N18: Total Cost
B19: Foul and Hommos | C19: 1 | D19: ='F&B'!F63 -> 8910 | E19: =IF(OR(ISBLANK(C19),ISBLANK(D19)),"",D19*C19) -> 8910 | K19: Olives | L19: 0.04 | M19: ='F&B'!F45 -> 36000 | N19: =IF(OR(ISBLANK(L19),ISBLANK(M19)),"",M19*L19) -> 1440
B20: Garlic | C20: 0.01 | D20: ='F&B'!F292 -> 19800 | E20: =IF(OR(ISBLANK(C20),ISBLANK(D20)),"",D20*C20) -> 198 | K20: Cucumber | L20: 0.1 | M20: ='F&B'!F284 -> 7200 | N20: =IF(OR(ISBLANK(L20),ISBLANK(M20)),"",M20*L20) -> 720
B21: Lemon Juice | C21: 0.05 | D21: ='F&B'!F287 -> 8100 | E21: =IF(OR(ISBLANK(C21),ISBLANK(D21)),"",D21*C21) -> 405 | K21: Tomatoes | L21: 0.16 | M21: ='F&B'!F279 -> 7200 | N21: =IF(OR(ISBLANK(L21),ISBLANK(M21)),"",M21*L21) -> 1152
B22: TOTAL | E22: =IF(SUM(E19:E21)=0,"",SUM(E19:E21)) -> 9513 | K22: TOTAL | N22: =IF(SUM(N19:N21)=0,"",SUM(N19:N21)) -> 3312
B24: SECONDARY INGREDIENTS | K24: SECONDARY INGREDIENTS
B25: Product Name | C25: Qty | D25: Cost | E25: Total Cost | K25: Product Name | L25: Qty | M25: Cost | N25: Total Cost
B27: Olive Oil | C27: 0.025 | D27: ='F&B'!F43/13 -> 38076.923 | E27: =D27*C27 -> 951.92308 | K27: Mint | L27: 0.5 | M27: ='F&B'!F315 -> 2970 | N27: =M27*L27 -> 1485
B28: Veggie Plate | C28: 1 | D28: =L10 -> 7776.6429 | E28: =D28*C28 -> 7776.6429 | K28: Pickles | L28: 0.045 | M28: ='F&B'!F49/10 -> 13500 | N28: =M28*L28 -> 607.5
E29: =D29*C29 -> 0 | K29: Bread | L29: 1 | M29: ='F&B'!F4/7 -> 1247.1429 | N29: =M29*L29 -> 1247.1429
E30: =D30*C30 -> 0 | K30: Raddish | L30: 0.25 | M30: ='F&B'!F317 -> 4500 | N30: =M30*L30 -> 1125
E31: =D31*C31 -> 0 | N31: =M31*L31 -> 0
E32: =D32*C32 -> 0 | N32: =M32*L32 -> 0
E33: =D33*C33 -> 0 | N33: =M33*L33 -> 0
E34: =D34*C34 -> 0 | N34: =M34*L34 -> 0
E35: =D35*C35 -> 0 | N35: =M35*L35 -> 0
E36: =D36*C36 -> 0 | N36: =M36*L36 -> 0
B37: TOTAL | E37: =IF(SUM(E27:E36)=0,"",SUM(E27:E36)) -> 8728.5659 | K37: TOTAL | N37: =IF(SUM(N27:N36)=0,"",SUM(N27:N36)) -> 4464.6429
B39: UTILITY AND PREP. COST | K39: UTILITY AND PREP. COST
B40: Name | E40: Total Cost | K40: Name | N40: Total Cost
B41: Shorenting Oil | C41: ='UTL COST'!$B$3 -> 369000 | D41: ='UTL COST'!$C$3 -> 0.0075 | E41: 0 | K41: Shorenting Oil | L41: ='UTL COST'!$B$3 -> 369000 | M41: ='UTL COST'!$C$3 -> 0.0075 | N41: 0
B42: Gas | C42: ='UTL COST'!$B$4 -> #REF! | D42: ='UTL COST'!$C$4 -> 7000 | E42: ='UTL COST'!$D$4 -> #REF! | K42: Gas | L42: ='UTL COST'!$B$4 -> #REF! | M42: ='UTL COST'!$C$4 -> 7000 | N42: 0
B43: Electricity | C43: ='UTL COST'!$B$5 -> #REF! | D43: ='UTL COST'!$C$5 -> 45000 | E43: ='UTL COST'!$D$5 -> #REF! | K43: Electricity | L43: ='UTL COST'!$B$5 -> #REF! | M43: ='UTL COST'!$C$5 -> 45000 | N43: ='UTL COST'!$D$5 -> #REF!
B44: Water | C44: ='UTL COST'!$B$6 -> #REF! | D44: ='UTL COST'!$C$6 -> 525 | E44: 0.1 | K44: Water | L44: ='UTL COST'!$B$6 -> #REF! | M44: ='UTL COST'!$C$6 -> 525 | N44: 0.1
B45: TOTAL | E45: =SUM(E41:E44) -> #REF! | K45: TOTAL | N45: 0
B50: DISH NAME | C50: Fateh bi Laban | K50: DISH NAME | L50: Balila
B52: EST. SALE PPRICE | C52: =C54/90000 -> #REF! | K52: EST. SALE PPRICE | L52: =L54/90000 -> #REF!
B54: TOTAL COST | C54: =IF(SUM(E66,E81,E89)=0,"",SUM(E66,E81,E89)) -> #REF! | E54: =C54/90000 -> #REF! | K54: TOTAL COST | L54: =IF(SUM(N66,N81,N89)=0,"",SUM(N66,N81,N89)) -> #REF!
B56: COST MARGIN | C56: =IF(C54="","",IF(ISBLANK(C52),"",C54/C52)) -> #REF! | K56: COST MARGIN | L56: =IF(L54="","",IF(ISBLANK(L52),"",L54/L52)) -> #REF!
B58: NET PROFIT | C58: =C52-C54 -> #REF! | K58: NET PROFIT | L58: =L52-L54 -> #REF!
B61: PRIMARY INGREDIENTS | K61: PRIMARY INGREDIENTS
B62: Product Name | C62: Qty. | D62: Cost (per unit) | E62: Total Cost | K62: Product Name | L62: Qty. | M62: Cost (per unit) | N62: Total Cost
B63: Hommos | C63: 0.5 | D63: ='F&B'!F64 -> 9720 | E63: =IF(OR(ISBLANK(C63),ISBLANK(D63)),"",D63*C63) -> 4860 | K63: Hommos | L63: 1 | M63: ='F&B'!F64 -> 9720 | N63: =IF(OR(ISBLANK(L63),ISBLANK(M63)),"",M63*L63) -> 9720
B64: Bread | C64: 0.5 | D64: =M29 -> 1247.1429 | E64: =IF(OR(ISBLANK(C64),ISBLANK(D64)),"",D64*C64) -> 623.57143 | K64: Garlic | L64: 0.01 | M64: =D65 -> 19800 | N64: =IF(OR(ISBLANK(L64),ISBLANK(M64)),"",M64*L64) -> 198
B65: Garlic | C65: 0.01 | D65: =D20 -> 19800 | E65: =IF(OR(ISBLANK(C65),ISBLANK(D65)),"",D65*C65) -> 198 | K65: Lemon Juice | L65: 0.05 | M65: =D21 -> 8100 | N65: =IF(OR(ISBLANK(L65),ISBLANK(M65)),"",M65*L65) -> 405
B66: TOTAL | E66: =IF(SUM(E63:E65)=0,"",SUM(E63:E65)) -> 5681.5714 | K66: TOTAL | N66: =IF(SUM(N63:N65)=0,"",SUM(N63:N65)) -> 10323
B68: SECONDARY INGREDIENTS | K68: SECONDARY INGREDIENTS
B69: Product Name | C69: Qty | D69: Cost | E69: Total Cost | K69: Product Name | L69: Qty | M69: Cost | N69: Total Cost
B71: Laban | C71: 0.06 | D71: ='F&B'!F94 -> 27000 | E71: =D71*C71 -> 1620 | K71: Olive Oil | L71: 0.025 | M71: =D27 -> 38076.923 | N71: =M71*L71 -> 951.92308
B72: Butter | C72: 0.015 | D72: ='F&B'!F79/25 -> 14040 | E72: =D72*C72 -> 210.6 | K72: Veggies Plate | L72: 1 | M72: =D28 -> 7776.6429 | N72: =M72*L72 -> 7776.6429
B73: Almonds | C73: 0.012 | D73: ='F&B'!F136 -> 90000 | E73: =D73*C73 -> 1080 | N73: =M73*L73 -> 0
B74: Veggies Plate | C74: 1 | D74: =D28 -> 7776.6429 | E74: =D74*C74 -> 7776.6429 | N74: =M74*L74 -> 0
E75: =D75*C75 -> 0 | N75: =M75*L75 -> 0
E76: =D76*C76 -> 0 | N76: =M76*L76 -> 0
E77: =D77*C77 -> 0 | N77: =M77*L77 -> 0
E78: =D78*C78 -> 0 | N78: =M78*L78 -> 0
E79: =D79*C79 -> 0 | N79: =M79*L79 -> 0
E80: =D80*C80 -> 0 | N80: =M80*L80 -> 0
B81: TOTAL | E81: =IF(SUM(E71:E80)=0,"",SUM(E71:E80)) -> 10687.243 | K81: TOTAL | N81: =IF(SUM(N71:N80)=0,"",SUM(N71:N80)) -> 8728.5659
B83: UTILITY AND PREP. COST | K83: UTILITY AND PREP. COST
B84: Name | E84: Total Cost | K84: Name | N84: Total Cost
B85: Shorenting Oil | C85: ='UTL COST'!$B$3 -> 369000 | D85: ='UTL COST'!$C$3 -> 0.0075 | E85: 0 | K85: Shorenting Oil | L85: ='UTL COST'!$B$3 -> 369000 | M85: ='UTL COST'!$C$3 -> 0.0075 | N85: 0
B86: Gas | C86: ='UTL COST'!$B$4 -> #REF! | D86: ='UTL COST'!$C$4 -> 7000 | E86: ='UTL COST'!$D$4 -> #REF! | K86: Gas | L86: ='UTL COST'!$B$4 -> #REF! | M86: ='UTL COST'!$C$4 -> 7000 | N86: ='UTL COST'!$D$4 -> #REF!
B87: Electricity | C87: ='UTL COST'!$B$5 -> #REF! | D87: ='UTL COST'!$C$5 -> 45000 | E87: ='UTL COST'!$D$5 -> #REF! | K87: Electricity | L87: ='UTL COST'!$B$5 -> #REF! | M87: ='UTL COST'!$C$5 -> 45000 | N87: ='UTL COST'!$D$5 -> #REF!
B88: Water | C88: ='UTL COST'!$B$6 -> #REF! | D88: ='UTL COST'!$C$6 -> 525 | E88: 0.1 | K88: Water | L88: ='UTL COST'!$B$6 -> #REF! | M88: ='UTL COST'!$C$6 -> 525 | N88: 0.1
B89: TOTAL | E89: =SUM(E85:E88) -> #REF! | K89: TOTAL | N89: =SUM(N85:N88) -> #REF!
B96: DISH NAME | C96: Cheese Plate | K96: DISH NAME
B98: EST. SALE PPRICE | C98: 80000 | K98: EST. SALE PPRICE | L98: 150000
B100: TOTAL COST | C100: =IF(SUM(E112,E127,E135)=0,"",SUM(E112,E127,E135)) -> 316419.69 | E100: =C100/90000 -> 3.5157743 | K100: TOTAL COST | L100: =IF(SUM(N112,N127,N135)=0,"",SUM(N112,N127,N135)) -> #REF!
B102: COST MARGIN | C102: =IF(C100="","",IF(ISBLANK(C98),"",C100/C98)) -> 3.9552461 | K102: COST MARGIN | L102: =IF(L100="","",IF(ISBLANK(L98),"",L100/L98)) -> #REF!
B104: NET PROFIT | C104: =C98-C100 -> -236419.69 | K104: NET PROFIT | L104: =L98-L100 -> #REF!
B107: PRIMARY INGREDIENTS | K107: PRIMARY INGREDIENTS
B108: Product Name | C108: Qty. | D108: Cost (per unit) | E108: Total Cost | F108: =F111+F110+F109 -> 1.60704 | K108: Product Name | L108: Qty. | M108: Cost (per unit) | N108: Total Cost
B109: Jaddal | C109: 0.066 | D109: =(41.76/4)*90000 -> 939600 | E109: =IF(OR(ISBLANK(C109),ISBLANK(D109)),"",D109*C109) -> 62013.6 | F109: =E109/90000 -> 0.68904 | N109: =IF(OR(ISBLANK(L109),ISBLANK(M109)),"",M109*L109)
B110: Mechalal | C110: 0.04 | D110: =(39.6/4)*90000 -> 891000 | E110: =IF(OR(ISBLANK(C110),ISBLANK(D110)),"",D110*C110) -> 35640 | F110: =E110/90000 -> 0.396 | N110: =IF(OR(ISBLANK(L110),ISBLANK(M110)),"",M110*L110)
B111: Halloum Roll | C111: 0.05 | D111: =(41.76/4)*90000 -> 939600 | E111: =IF(OR(ISBLANK(C111),ISBLANK(D111)),"",D111*C111) -> 46980 | F111: =E111/90000 -> 0.522 | N111: =IF(OR(ISBLANK(L111),ISBLANK(M111)),"",M111*L111)
B112: TOTAL | E112: =IF(SUM(E109:E111)=0,"",SUM(E109:E111)) -> 144633.6 | K112: TOTAL | N112: =IF(SUM(N109:N111)=0,"",SUM(N109:N111))
B114: SECONDARY INGREDIENTS | K114: SECONDARY INGREDIENTS
B115: Product Name | C115: Qty | D115: Cost | E115: Total Cost | K115: Product Name | L115: Qty | M115: Cost | N115: Total Cost
F116: =F117+F118+F119+F120 -> 1.73592
B117: Makdous | C117: 0.06 | D117: =(22.5/5)*90000 -> 405000 | E117: =D117*C117 -> 24300 | F117: =E117/90000 -> 0.27 | N117: =M117*L117 -> 0
B118: Labneh | C118: 0.11 | D118: =1611900/5 -> 322380 | E118: =D118*C118 -> 35461.8 | F118: =E118/90000 -> 0.39402 | N118: =M118*L118 -> 0
B119: Fetta | C119: 0.09 | D119: =(14.85/3)*90000 -> 445500 | E119: =D119*C119 -> 40095 | F119: =E119/90000 -> 0.4455 | N119: =M119*L119 -> 0
B120: Nabelsiyeh | C120: 0.06 | D120: =(41.76/4)*90000 -> 939600 | E120: =D120*C120 -> 56376 | F120: =E120/90000 -> 0.6264 | N120: =M120*L120 -> 0
B121: Bread | C121: 1 | D121: =M86 -> 7000 | E121: =D122*C121 -> 7776.6429 | N121: =M121*L121 -> 0
B122: Veggie Plate | C122: 1 | D122: =L10 -> 7776.6429 | E122: =D122*C122 -> 7776.6429 | N122: =M122*L122 -> 0
E123: =D123*C123 -> 0 | N123: =M123*L123 -> 0
E124: =D124*C124 -> 0 | N124: =M124*L124 -> 0
E125: =D125*C125 -> 0 | N125: =M125*L125 -> 0
E126: =D126*C126 -> 0 | N126: =M126*L126 -> 0
B127: TOTAL | E127: =IF(SUM(E117:E126)=0,"",SUM(E117:E126)) -> 171786.09 | K127: TOTAL | N127: =IF(SUM(N117:N126)=0,"",SUM(N117:N126))
B129: UTILITY AND PREP. COST | K129: UTILITY AND PREP. COST
B130: Name | E130: Total Cost | K130: Name | N130: Total Cost
B131: Shorenting Oil | C131: ='UTL COST'!$B$3 -> 369000 | D131: ='UTL COST'!$C$3 -> 0.0075 | E131: 0 | K131: Shorenting Oil | L131: ='UTL COST'!$B$3 -> 369000 | M131: ='UTL COST'!$C$3 -> 0.0075 | N131: ='UTL COST'!$D$3 -> 2767.5
B132: Gas | C132: ='UTL COST'!$B$4 -> #REF! | D132: ='UTL COST'!$C$4 -> 7000 | E132: 0 | K132: Gas | L132: ='UTL COST'!$B$4 -> #REF! | M132: ='UTL COST'!$C$4 -> 7000 | N132: ='UTL COST'!$D$4 -> #REF!
B133: Electricity | C133: ='UTL COST'!$B$5 -> #REF! | D133: ='UTL COST'!$C$5 -> 45000 | E133: ='UTL COST'!$D$5 -> #REF! | K133: Electricity | L133: ='UTL COST'!$B$5 -> #REF! | M133: ='UTL COST'!$C$5 -> 45000 | N133: ='UTL COST'!$D$5 -> #REF!
B134: Water | C134: ='UTL COST'!$B$6 -> #REF! | D134: ='UTL COST'!$C$6 -> 525 | E134: 0.1 | K134: Water | L134: ='UTL COST'!$B$6 -> #REF! | M134: ='UTL COST'!$C$6 -> 525 | N134: 0.1
B135: TOTAL | E135: 0 | K135: TOTAL | N135: =IF(SUM(N131:N134)=0,"",SUM(N131:N134)) -> #REF!

Sheet PIZZA
A1: PIZZA FOOD COST
B6: DISH NAME | C6: Margherita | K6: DISH NAME | L6: Regular
B8: EST. SALE PPRICE | C8: 135000 | K8: EST. SALE PPRICE | L8: 200000
B10: TOTAL COST | C10: =IF(SUM(E22,E37,E45)=0,"",SUM(E22,E37,E45)) -> #REF! | K10: TOTAL COST | L10: =IF(SUM(N22,N37,N45)=0,"",SUM(N22,N37,N45)) -> #REF!
B12: COST MARGIN | C12: =IF(C10="","",IF(ISBLANK(C8),"",C10/C8)) -> #REF! | K12: COST MARGIN | L12: =IF(L10="","",IF(ISBLANK(L8),"",L10/L8)) -> #REF!
B14: NET PROFIT | C14: =C8-C10 -> #REF! | K14: NET PROFIT | L14: =L8-L10 -> #REF!
B17: PRIMARY INGREDIENTS | K17: PRIMARY INGREDIENTS
B18: Product Name | C18: Qty. | D18: Cost (per unit) | E18: Total Cost | K18: Product Name | L18: Qty. | M18: Cost (per unit) | N18: Total Cost
B19: Mozzarella Cheese | C19: 0.15 | D19: ='F&B'!$F$98 -> 76500 | E19: =IF(OR(ISBLANK(C19),ISBLANK(D19)),"",D19*C19) -> 11475 | K19: Mozzarella Cheese | L19: 0.15 | M19: ='F&B'!$F$98 -> 76500 | N19: =IF(OR(ISBLANK(L19),ISBLANK(M19)),"",M19*L19) -> 11475
B20: Tomato Sauce | C20: 0.12 | D20: =SAUCES!$L$60 -> 19698.45 | E20: =IF(OR(ISBLANK(C20),ISBLANK(D20)),"",D20*C20) -> 2363.814 | H20: =E20/90000 -> 0.026264599 | K20: Tomato Sauce | L20: 0.12 | M20: =D20 -> 19698.45 | N20: =IF(OR(ISBLANK(L20),ISBLANK(M20)),"",M20*L20) -> 2363.814
B21: Dough | C21: 1 | D21: =SAUCES!$D$92 -> 900.92308 | E21: =IF(OR(ISBLANK(C21),ISBLANK(D21)),"",D21*C21) -> 900.92308 | H21: =E21/90000 -> 0.010010256 | K21: Dough | L21: 1 | M21: =D21 -> 900.92308 | N21: =IF(OR(ISBLANK(L21),ISBLANK(M21)),"",M21*L21) -> 900.92308
B22: TOTAL | E22: =IF(SUM(E19:E21)=0,"",SUM(E19:E21)) -> 14739.737 | K22: TOTAL | N22: =IF(SUM(N19:N21)=0,"",SUM(N19:N21)) -> 14739.737
B24: SECONDARY INGREDIENTS | K24: SECONDARY INGREDIENTS
B25: Product Name | C25: Qty | D25: Cost | E25: Total Cost | K25: Product Name | L25: Qty | M25: Cost | N25: Total Cost
B27: Oregano | C27: 0.005 | D27: ='F&B'!$F$167 -> 37800 | E27: =D27*C27 -> 189 | K27: Oregano | L27: 0.005 | M27: ='F&B'!$F$167 -> 37800 | N27: =M27*L27 -> 189
E28: =D28*C28 -> 0 | I28: =M28/90000 -> 3.1111111 | K28: Mushrooms | L28: 0.03 | M28: =280000 -> 280000 | N28: =M28*L28 -> 8400
E29: =D29*C29 -> 0 | K29: Turkey | L29: 0.05 | M29: ='F&B'!$F$223 -> 142920 | N29: =M29*L29 -> 7146
E30: =D30*C30 -> 0 | K30: Black Olives | L30: 0.06 | M30: ='F&B'!$F$44/10 -> 23400 | N30: =M30*L30 -> 1404
E31: =D31*C31 -> 0 | N31: =M31*L31 -> 0
E32: =D32*C32 -> 0 | N32: =M32*L32 -> 0
E33: =D33*C33 -> 0 | N33: =M33*L33 -> 0
E34: =D34*C34 -> 0 | N34: =M34*L34 -> 0
E35: =D35*C35 -> 0 | N35: =M35*L35 -> 0
E36: =D36*C36 -> 0 | N36: =M36*L36 -> 0
B37: TOTAL | E37: =IF(SUM(E27:E36)=0,"",SUM(E27:E36)) -> 189 | K37: TOTAL | N37: =IF(SUM(N27:N36)=0,"",SUM(N27:N36)) -> 17139
B39: UTILITY AND PREP. COST | K39: UTILITY AND PREP. COST
B40: Name | E40: Total Cost | K40: Name | N40: Total Cost
B41: Shorenting Oil | C41: ='UTL COST'!$B$3 -> 369000 | D41: ='UTL COST'!$C$3 -> 0.0075 | E41: 0 | K41: Shorenting Oil | L41: ='UTL COST'!$B$3 -> 369000 | M41: ='UTL COST'!$C$3 -> 0.0075 | N41: 0
B42: ='UTL COST'!$A$7 -> Gas Pizza | C42: ='UTL COST'!$B$7 -> #REF! | D42: ='UTL COST'!$C$7 -> 450 | E42: ='UTL COST'!$D$7 -> #REF! | K42: ='UTL COST'!$A$7 -> Gas Pizza | L42: ='UTL COST'!$B$7 -> #REF! | M42: ='UTL COST'!$C$7 -> 450 | N42: ='UTL COST'!$D$7 -> #REF!
B43: Electricity | C43: ='UTL COST'!$B$5 -> #REF! | D43: ='UTL COST'!$C$5 -> 45000 | E43: ='UTL COST'!$D$5 -> #REF! | K43: Electricity | L43: ='UTL COST'!$B$5 -> #REF! | M43: ='UTL COST'!$C$5 -> 45000 | N43: ='UTL COST'!$D$5 -> #REF!
B44: ='UTL COST'!A6 -> Wood | C44: ='UTL COST'!$B$6 -> #REF! | D44: ='UTL COST'!$C$6 -> 525 | E44: =C44/D44 -> #REF! | K44: Wood | L44: ='UTL COST'!$B$6 -> #REF! | M44: ='UTL COST'!$C$6 -> 525 | N44: =E44 -> #REF!
B45: TOTAL | E45: =IF(SUM(E41:E44)=0,"",SUM(E41:E44)) -> #REF! | K45: TOTAL | N45: =IF(SUM(N41:N44)=0,"",SUM(N41:N44)) -> #REF!
B50: DISH NAME | C50: Vegetarien | K50: DISH NAME | L50: Pepperoni
B52: EST. SALE PPRICE | C52: 200000 | K52: EST. SALE PPRICE | L52: 200000
B54: TOTAL COST | C54: =IF(SUM(E66,E81,E89)=0,"",SUM(E66,E81,E89)) -> #REF! | K54: TOTAL COST | L54: =IF(SUM(N66,N81,N89)=0,"",SUM(N66,N81,N89)) -> #REF!
B56: COST MARGIN | C56: =IF(C54="","",IF(ISBLANK(C52),"",C54/C52)) -> #REF! | K56: COST MARGIN | L56: =IF(L54="","",IF(ISBLANK(L52),"",L54/L52)) -> #REF!
B58: NET PROFIT | C58: =C52-C54 -> #REF! | K58: NET PROFIT | L58: =L52-L54 -> #REF!
B61: PRIMARY INGREDIENTS | K61: PRIMARY INGREDIENTS
B62: Product Name | C62: Qty. | D62: Cost (per unit) | E62: Total Cost | K62: Product Name | L62: Qty. | M62: Cost (per unit) | N62: Total Cost
B63: Mozzarella Cheese | C63: 0.15 | D63: ='F&B'!$F$98 -> 76500 | E63: =IF(OR(ISBLANK(C63),ISBLANK(D63)),"",D63*C63) -> 11475 | K63: Mozzarella Cheese | L63: 0.15 | M63: ='F&B'!$F$98 -> 76500 | N63: =IF(OR(ISBLANK(L63),ISBLANK(M63)),"",M63*L63) -> 11475
B64: Tomato Sauce | C64: 0.12 | D64: =D20 -> 19698.45 | E64: =IF(OR(ISBLANK(C64),ISBLANK(D64)),"",D64*C64) -> 2363.814 | K64: Tomato Sauce | L64: 0.12 | M64: =D20 -> 19698.45 | N64: =IF(OR(ISBLANK(L64),ISBLANK(M64)),"",M64*L64) -> 2363.814
B65: Dough | C65: 1 | D65: =D21 -> 900.92308 | E65: =IF(OR(ISBLANK(C65),ISBLANK(D65)),"",D65*C65) -> 900.92308 | K65: Dough | L65: 1 | M65: =D21 -> 900.92308 | N65: =IF(OR(ISBLANK(L65),ISBLANK(M65)),"",M65*L65) -> 900.92308
B66: TOTAL | E66: =IF(SUM(E63:E65)=0,"",SUM(E63:E65)) -> 14739.737 | K66: TOTAL | N66: =IF(SUM(N63:N65)=0,"",SUM(N63:N65)) -> 14739.737
B68: SECONDARY INGREDIENTS | K68: SECONDARY INGREDIENTS
B69: Product Name | C69: Qty | D69: Cost | E69: Total Cost | K69: Product Name | L69: Qty | M69: Cost | N69: Total Cost
B71: Black Olives | C71: 0.06 | D71: ='F&B'!$F$44/10 -> 23400 | E71: =D71*C71 -> 1404 | K71: Pepperoni | L71: 0.04 | M71: ='F&B'!$F$219 -> 109890 | N71: =M71*L71 -> 4395.6
B72: Mushrooms | C72: 0.03 | D72: ='F&B'!$F$278 -> 103500 | E72: =D72*C72 -> 3105 | N72: =M72*L72 -> 0
B73: Green Pepper | C73: 0.03 | D73: ='F&B'!$F$296 -> 9000 | E73: =D73*C73 -> 270 | N73: =M73*L73 -> 0
B74: Sweet Corn | C74: 0.04 | D74: ='F&B'!$F$60*3 -> 29700 | E74: =D74*C74 -> 1188 | N74: =M74*L74 -> 0
B75: Red Pepper | E75: =D75*C75 -> 0 | N75: =M75*L75 -> 0
E76: =D76*C76 -> 0 | N76: =M76*L76 -> 0
E77: =D77*C77 -> 0 | N77: =M77*L77 -> 0
E78: =D78*C78 -> 0 | N78: =M78*L78 -> 0
E79: =D79*C79 -> 0 | N79: =M79*L79 -> 0
E80: =D80*C80 -> 0 | N80: =M80*L80 -> 0
B81: TOTAL | E81: =IF(SUM(E71:E80)=0,"",SUM(E71:E80)) -> 5967 | K81: TOTAL | N81: =IF(SUM(N71:N80)=0,"",SUM(N71:N80)) -> 4395.6
B83: UTILITY AND PREP. COST | K83: UTILITY AND PREP. COST
B84: Name | E84: Total Cost | K84: Name | N84: Total Cost
B85: Shorenting Oil | C85: ='UTL COST'!$B$3 -> 369000 | D85: ='UTL COST'!$C$3 -> 0.0075 | E85: 0 | K85: Shorenting Oil | L85: ='UTL COST'!$B$3 -> 369000 | M85: ='UTL COST'!$C$3 -> 0.0075 | N85: 0
B86: ='UTL COST'!$A$7 -> Gas Pizza | C86: ='UTL COST'!$B$7 -> #REF! | D86: ='UTL COST'!$C$7 -> 450 | E86: ='UTL COST'!$D$7 -> #REF! | K86: ='UTL COST'!$A$7 -> Gas Pizza | L86: ='UTL COST'!$B$7 -> #REF! | M86: ='UTL COST'!$C$7 -> 450 | N86: ='UTL COST'!$D$7 -> #REF!
B87: Electricity | C87: ='UTL COST'!$B$5 -> #REF! | D87: ='UTL COST'!$C$5 -> 45000 | E87: ='UTL COST'!$D$5 -> #REF! | K87: Electricity | L87: ='UTL COST'!$B$5 -> #REF! | M87: ='UTL COST'!$C$5 -> 45000 | N87: ='UTL COST'!$D$5 -> #REF!
B88: Wood | C88: ='UTL COST'!$B$6 -> #REF! | D88: ='UTL COST'!$C$6 -> 525 | K88: Wood | L88: ='UTL COST'!$B$6 -> #REF! | M88: ='UTL COST'!$C$6 -> 525
B89: TOTAL | E89: =IF(SUM(E85:E88)=0,"",SUM(E85:E88)) -> #REF! | K89: TOTAL | N89: =IF(SUM(N85:N88)=0,"",SUM(N85:N88)) -> #REF!
B95: DISH NAME | C95: Sundried Tomato | K95: DISH NAME | L95: BBQ Chicken
B97: EST. SALE PPRICE | C97: 220000 | K97: EST. SALE PPRICE | L97: 295000
B99: TOTAL COST | C99: =IF(SUM(E111,E126,E134)=0,"",SUM(E111,E126,E134)) -> 32219.237 | K99: TOTAL COST | L99: =IF(SUM(N111,N126,N134)=0,"",SUM(N111,N126,N134)) -> #REF!
B101: COST MARGIN | C101: =IF(C99="","",IF(ISBLANK(C97),"",C99/C97)) -> 0.14645108 | K101: COST MARGIN | L101: =IF(L99="","",IF(ISBLANK(L97),"",L99/L97)) -> #REF!
B103: NET PROFIT | C103: =C97-C99 -> 187780.76 | K103: NET PROFIT | L103: =L97-L99 -> #REF!
B106: PRIMARY INGREDIENTS | K106: PRIMARY INGREDIENTS
B107: Product Name | C107: Qty. | D107: Cost (per unit) | E107: Total Cost | K107: Product Name | L107: Qty. | M107: Cost (per unit) | N107: Total Cost
B108: Mozzarella Cheese | C108: 0.15 | D108: ='F&B'!$F$98 -> 76500 | E108: =IF(OR(ISBLANK(C108),ISBLANK(D108)),"",D108*C108) -> 11475 | K108: Mozzarella Cheese | L108: 0.15 | M108: ='F&B'!$F$98 -> 76500 | N108: =IF(OR(ISBLANK(L108),ISBLANK(M108)),"",M108*L108) -> 11475
B109: Tomato Sauce | C109: 0.12 | D109: =D20 -> 19698.45 | E109: =IF(OR(ISBLANK(C109),ISBLANK(D109)),"",D109*C109) -> 2363.814 | K109: Tomato Sauce | L109: 0.12 | M109: =D20 -> 19698.45 | N109: =IF(OR(ISBLANK(L109),ISBLANK(M109)),"",M109*L109) -> 2363.814
B110: Dough | C110: 1 | D110: =D21 -> 900.92308 | E110: =IF(OR(ISBLANK(C110),ISBLANK(D110)),"",D110*C110) -> 900.92308 | K110: Dough | L110: 1 | M110: =D21 -> 900.92308 | N110: =IF(OR(ISBLANK(L110),ISBLANK(M110)),"",M110*L110) -> 900.92308
B111: TOTAL | E111: =IF(SUM(E108:E110)=0,"",SUM(E108:E110)) -> 14739.737 | H111: =E111/$C$99 -> 0.4574825 | K111: TOTAL | N111: =IF(SUM(N108:N110)=0,"",SUM(N108:N110)) -> 14739.737
B113: SECONDARY INGREDIENTS | K113: SECONDARY INGREDIENTS
B114: Product Name | C114: Qty | D114: Cost | E114: Total Cost | K114: Product Name | L114: Qty | M114: Cost | N114: Total Cost
B116: Parmesan Cheese | C116: =30/1000 -> 0.03 | D116: ='F&B'!$F$103 -> 148500 | E116: =D116*C116 -> 4455 | K116: Chicken Breast | L116: 0.14 | M116: ='F&B'!$F$229 -> 81000 | N116: =M116*L116 -> 11340
B117: Rocket Leaves | C117: 0.25 | D117: ='F&B'!$F$280 -> 2970 | E117: =D117*C117 -> 742.5 | K117: BBQ Sauce | L117: 0.09 | M117: ='F&B'!$F$246/3.79 -> 56160.95 | N117: =M117*L117 -> 5054.4855
B118: Mushrooms | C118: 0.06 | D118: ='F&B'!$F$278 -> 103500 | E118: =D118*C118 -> 6210 | K118: Sweet Corn | L118: 0.04 | M118: ='F&B'!$F$60*3 -> 29700 | N118: =M118*L118 -> 1188
B119: Sundried Tomato | C119: 0.04 | D119: ='F&B'!$F$251/3 -> 151800 | E119: =D119*C119 -> 6072 | K119: Cheddar Cheese | N119: =M119*L119 -> 0
E120: =D120*C120 -> 0 | N120: =M120*L120 -> 0
E121: =D121*C121 -> 0 | N121: =M121*L121 -> 0
E122: =D122*C122 -> 0 | N122: =M122*L122 -> 0
E123: =D123*C123 -> 0 | N123: =M123*L123 -> 0
E124: =D124*C124 -> 0 | N124: =M124*L124 -> 0
E125: =D125*C125 -> 0 | N125: =M125*L125 -> 0
B126: TOTAL | E126: =IF(SUM(E116:E125)=0,"",SUM(E116:E125)) -> 17479.5 | H126: =E126/$C$99 -> 0.5425175 | K126: TOTAL | N126: =IF(SUM(N116:N125)=0,"",SUM(N116:N125)) -> 17582.485
B128: UTILITY AND PREP. COST | K128: UTILITY AND PREP. COST
B129: Name | E129: Total Cost | K129: Name | N129: Total Cost
B130: Shorenting Oil | C130: ='UTL COST'!$B$3 -> 369000 | D130: ='UTL COST'!$C$3 -> 0.0075 | E130: 0 | K130: Shorenting Oil | L130: ='UTL COST'!$B$3 -> 369000 | M130: ='UTL COST'!$C$3 -> 0.0075 | N130: 0
B131: ='UTL COST'!$A$7 -> Gas Pizza | C131: ='UTL COST'!$B$7 -> #REF! | D131: ='UTL COST'!$C$7 -> 450 | E131: ='UTL COST'!$D$7 -> #REF! | K131: ='UTL COST'!$A$7 -> Gas Pizza | L131: ='UTL COST'!$B$7 -> #REF! | M131: ='UTL COST'!$C$7 -> 450 | N131: ='UTL COST'!$D$7 -> #REF!
B132: Electricity | C132: ='UTL COST'!$B$5 -> #REF! | D132: ='UTL COST'!$C$5 -> 45000 | E132: ='UTL COST'!$D$5 -> #REF! | K132: Electricity | L132: ='UTL COST'!$B$5 -> #REF! | M132: ='UTL COST'!$C$5 -> 45000 | N132: ='UTL COST'!$D$5 -> #REF!
B133: Wood | C133: ='UTL COST'!$B$6 -> #REF! | D133: ='UTL COST'!$C$6 -> 525 | K133: Wood | L133: ='UTL COST'!$B$6 -> #REF! | M133: ='UTL COST'!$C$6 -> 525
B134: TOTAL | H134: =E134/$C$99 -> 0 | K134: TOTAL | N134: =IF(SUM(N130:N133)=0,"",SUM(N130:N133)) -> #REF!
B142: DISH NAME | C142: Truffle Cheese Rocket | K142: DISH NAME | L142: Pesto Shrimps
B144: EST. SALE PPRICE | C144: =E144*90000 -> 1350000 | E144: 15 | K144: EST. SALE PPRICE
B146: TOTAL COST | C146: =IF(SUM(E158,E173,E181)=0,"",SUM(E158,E173,E181)) -> #REF! | E146: =C146/90000 -> #REF! | K146: TOTAL COST | L146: =IF(SUM(N158,N173,N181)=0,"",SUM(N158,N173,N181)) -> #REF!
B148: COST MARGIN | C148: =IF(C146="","",IF(ISBLANK(C144),"",C146/C144)) -> #REF! | K148: COST MARGIN | L148: =IF(L146="","",IF(ISBLANK(L144),"",L146/L144)) -> #REF!
B150: NET PROFIT | C150: =C144-C146 -> #REF! | K150: NET PROFIT | L150: =L144-L146 -> #REF!
B153: PRIMARY INGREDIENTS | K153: PRIMARY INGREDIENTS
...

Sheet SALADS
A1: SALADS FOOD COST
B6: DISH NAME | C6: Rocket Parmesan | K6: DISH NAME | L6: Greek
B8: EST. SALE PPRICE | C8: 140000 | K8: EST. SALE PPRICE | L8: 140000
B10: TOTAL COST | C10: =IF(SUM(E22,E37,E45)=0,"",SUM(E22,E37,E45)) -> #REF! | E10: =C10/90000 -> #REF! | K10: TOTAL COST | L10: =IF(SUM(N22,N37,N45)=0,"",SUM(N22,N37,N45)) -> #REF!
B12: COST MARGIN | C12: =IF(C10="","",IF(ISBLANK(C8),"",C10/C8)) -> #REF! | K12: COST MARGIN | L12: =IF(L10="","",IF(ISBLANK(L8),"",L10/L8)) -> #REF!
B14: NET PROFIT | C14: =C8-C10 -> #REF! | K14: NET PROFIT | L14: =L8-L10 -> #REF!
B17: PRIMARY INGREDIENTS | K17: PRIMARY INGREDIENTS
B18: Product Name | C18: Qty. | D18: Cost (per unit) | E18: Total Cost | K18: Product Name | L18: Qty. | M18: Cost (per unit) | N18: Total Cost
B19: Parmesan Cheese | C19: 0.02 | D19: ='F&B'!$F$103 -> 148500 | E19: =IF(OR(ISBLANK(C19),ISBLANK(D19)),"",D19*C19) -> 2970 | K19: Fetta Cheese | L19: 0.07 | M19: ='F&B'!$F$86 -> 44550 | N19: =IF(OR(ISBLANK(L19),ISBLANK(M19)),"",M19*L19) -> 3118.5
B20: Lemon Mustard Sauce | C20: 1 | D20: =SAUCES!$L$133 -> 1303.6607 | E20: =IF(OR(ISBLANK(C20),ISBLANK(D20)),"",D20*C20) -> 1303.6607 | K20: Lemon Mustard Sauce | L20: 1 | M20: =D20 -> 1303.6607 | N20: =IF(OR(ISBLANK(L20),ISBLANK(M20)),"",M20*L20) -> 1303.6607
E21: =IF(OR(ISBLANK(C21),ISBLANK(D21)),"",D21*C21) | N21: =IF(OR(ISBLANK(L21),ISBLANK(M21)),"",M21*L21)
B22: TOTAL | E22: =IF(SUM(E19:E21)=0,"",SUM(E19:E21)) -> 4273.6607 | K22: TOTAL | N22: =IF(SUM(N19:N21)=0,"",SUM(N19:N21)) -> 4422.1607
B24: SECONDARY INGREDIENTS | K24: SECONDARY INGREDIENTS
B25: Product Name | C25: Qty | D25: Cost | E25: Total Cost | K25: Product Name | L25: Qty | M25: Cost | N25: Total Cost
B27: Rocket Leaves | C27: 1 | D27: ='F&B'!$F$280 -> 2970 | E27: =D27*C27 -> 2970 | K27: Iceberg | L27: 1 | M27: ='F&B'!$F$277 -> 13500 | N27: =M27*L27 -> 13500
B28: Fresh Mushrooms | C28: 0.05 | D28: ='F&B'!$F$278 -> 103500 | E28: =D28*C28 -> 5175 | K28: Tomato | L28: 0.03 | M28: ='F&B'!$F$279 -> 7200 | N28: =M28*L28 -> 216
B29: Cherry Tomato | C29: 0.03 | D29: ='F&B'!$F$283 -> 9000 | E29: =D29*C29 -> 270 | K29: Cucumber | L29: 0.12 | M29: ='F&B'!$F$284 -> 7200 | N29: =M29*L29 -> 864
B30: Balsamic Sauce | C30: 0.06 | D30: =SAUCES!$D$36 -> 21446.564 | E30: =D30*C30 -> 1286.7938 | K30: Black Olives | L30: 0.02 | M30: ='F&B'!$F$44/17 -> 13764.706 | N30: =M30*L30 -> 275.29412
B31: Walnuts | C31: 0.02 | D31: ='F&B'!$F$146 -> 65250 | E31: =D31*C31 -> 1305 | K31: Oregano | L31: 0.001 | M31: ='F&B'!$F$167 -> 37800 | N31: =M31*L31 -> 37.8
B32: Pomegranate | C32: 0.01 | D32: ='F&B'!$F$300 -> 13500 | E32: =D32*C32 -> 135 | K32: Rocca Leaves | L32: 0.05 | M32: =D27 -> 2970 | N32: =M32*L32 -> 148.5
E33: =D33*C33 -> 0 | K33: Bell Peppers | L33: 0.02 | M33: ='F&B'!$F$296 -> 9000 | N33: =M33*L33 -> 180
E34: =D34*C34 -> 0 | K34: Sweet Corn | L34: 0.03 | M34: ='F&B'!$F$60*3 -> 29700 | N34: =M34*L34 -> 891
E35: =D35*C35 -> 0
E36: =D36*C36 -> 0 | N36: =M36*L36 -> 0
B37: TOTAL | E37: =IF(SUM(E27:E36)=0,"",SUM(E27:E36)) -> 11141.794 | K37: TOTAL | N37: =IF(SUM(N27:N36)=0,"",SUM(N27:N36)) -> 16112.594
B39: UTILITY AND PREP. COST | K39: UTILITY AND PREP. COST
B40: Name | E40: Total Cost | K40: Name | N40: Total Cost
B41: Shorenting Oil | C41: ='UTL COST'!$B$3 -> 369000 | D41: ='UTL COST'!$C$3 -> 0.0075 | E41: 0 | K41: Shorenting Oil | L41: ='UTL COST'!$B$3 -> 369000 | M41: ='UTL COST'!$C$3 -> 0.0075 | N41: 0
B42: Gas | C42: ='UTL COST'!$B$4 -> #REF! | D42: ='UTL COST'!$C$4 -> 7000 | E42: 0 | K42: Gas | L42: ='UTL COST'!$B$4 -> #REF! | M42: ='UTL COST'!$C$4 -> 7000 | N42: 0
B43: Electricity | C43: ='UTL COST'!$B$5 -> #REF! | D43: ='UTL COST'!$C$5 -> 45000 | E43: ='UTL COST'!$D$5 -> #REF! | K43: Electricity | L43: ='UTL COST'!$B$5 -> #REF! | M43: ='UTL COST'!$C$5 -> 45000 | N43: ='UTL COST'!$D$5 -> #REF!
B44: Water | C44: ='UTL COST'!$B$6 -> #REF! | D44: ='UTL COST'!$C$6 -> 525 | E44: 0.1 | K44: Water | L44: ='UTL COST'!$B$6 -> #REF! | M44: ='UTL COST'!$C$6 -> 525 | N44: 0.1
B45: TOTAL | E45: =IF(SUM(E41:E44)=0,"",SUM(E41:E44)) -> #REF! | K45: TOTAL | N45: =IF(SUM(N41:N44)=0,"",SUM(N41:N44)) -> #REF!
B50: DISH NAME | C50: Caesar | K50: DISH NAME | L50: Caesar Chicken
B52: EST. SALE PPRICE | C52: 145000 | K52: EST. SALE PPRICE | L52: 180000
B54: TOTAL COST | C54: =IF(SUM(E66,E81,E89)=0,"",SUM(E66,E81,E89)) -> #REF! | K54: TOTAL COST | L54: =IF(SUM(N66,N81,N89)=0,"",SUM(N66,N81,N89)) -> #REF!
B56: COST MARGIN | C56: =IF(C54="","",IF(ISBLANK(C52),"",C54/C52)) -> #REF! | K56: COST MARGIN | L56: =IF(L54="","",IF(ISBLANK(L52),"",L54/L52)) -> #REF!
B58: NET PROFIT | C58: =C52-C54 -> #REF! | K58: NET PROFIT | L58: =L52-L54 -> #REF!
B61: PRIMARY INGREDIENTS | K61: PRIMARY INGREDIENTS
B62: Product Name | C62: Qty. | D62: Cost (per unit) | E62: Total Cost | K62: Product Name | L62: Qty. | M62: Cost (per unit) | N62: Total Cost
B63: Parmesan Cheese | C63: 0.05 | D63: =D19 -> 148500 | E63: =IF(OR(ISBLANK(C63),ISBLANK(D63)),"",D63*C63) -> 7425 | K63: Chicken Breast | L63: 0.16 | M63: =SANDWICHES!$D$19 -> 81000 | N63: =IF(OR(ISBLANK(L63),ISBLANK(M63)),"",M63*L63) -> 12960
E64: =IF(OR(ISBLANK(C64),ISBLANK(D64)),"",D64*C64) | K64: Parmesan Cheese | L64: 0.05 | M64: =D63 -> 148500 | N64: =IF(OR(ISBLANK(L64),ISBLANK(M64)),"",M64*L64) -> 7425
E65: =IF(OR(ISBLANK(C65),ISBLANK(D65)),"",D65*C65)
B66: TOTAL | E66: =IF(SUM(E63:E65)=0,"",SUM(E63:E65)) -> 7425 | K66: TOTAL | N66: =IF(SUM(N63:N65)=0,"",SUM(N63:N65)) -> 20385
B68: SECONDARY INGREDIENTS | K68: SECONDARY INGREDIENTS
B69: Product Name | C69: Qty | D69: Cost | E69: Total Cost | K69: Product Name | L69: Qty | M69: Cost | N69: Total Cost
B71: Iceberg | C71: 1 | D71: =M27 -> 13500 | E71: =D71*C71 -> 13500 | K71: Iceberg | L71: 1 | M71: =D71 -> 13500 | N71: =M71*L71 -> 13500
B72: Croutons | C72: 0.02 | D72: =Prep!J80 -> 71480.654 | E72: 5000 | K72: Croutons | L72: 0.02 | M72: =D72 -> 71480.654 | N72: 5000
B73: Caesar Sauce | C73: 1 | D73: =SAUCES!$D$16 -> 3406.9479 | E73: =D73*C73 -> 3406.9479 | K73: Caesar Sauce | L73: 1 | M73: =D73 -> 3406.9479 | N73: =M73*L73 -> 3406.9479
B74: Cherry Tomato | C74: 0.03 | D74: ='F&B'!$F$283 -> 9000 | E74: =D74*C74 -> 270 | K74: Cherry Tomato | L74: 0.03 | M74: ='F&B'!$F$283 -> 9000 | N74: =M74*L74 -> 270
E75: =D75*C75 -> 0 | N75: =M75*L75 -> 0
E76: =D76*C76 -> 0 | N76: =M76*L76 -> 0
E77: =D77*C77 -> 0 | N77: =M77*L77 -> 0
E78: =D78*C78 -> 0 | N78: =M78*L78 -> 0
E79: =D79*C79 -> 0 | N79: =M79*L79 -> 0
E80: =D80*C80 -> 0 | N80: =M80*L80 -> 0
B81: TOTAL | E81: =IF(SUM(E71:E80)=0,"",SUM(E71:E80)) -> 22176.948 | K81: TOTAL | N81: =IF(SUM(N71:N80)=0,"",SUM(N71:N80)) -> 22176.948
B83: UTILITY AND PREP. COST | K83: UTILITY AND PREP. COST
B84: Name | E84: Total Cost | K84: Name | N84: Total Cost
B85: Shorenting Oil | C85: ='UTL COST'!$B$3 -> 369000 | D85: ='UTL COST'!$C$3 -> 0.0075 | E85: 0 | K85: Shorenting Oil | L85: ='UTL COST'!$B$3 -> 369000 | M85: ='UTL COST'!$C$3 -> 0.0075 | N85: 0
B86: Gas | C86: ='UTL COST'!$B$4 -> #REF! | D86: ='UTL COST'!$C$4 -> 7000 | E86: 0 | K86: Gas | L86: ='UTL COST'!$B$4 -> #REF! | M86: ='UTL COST'!$C$4 -> 7000 | N86: ='UTL COST'!$D$4 -> #REF!
B87: Electricity | C87: ='UTL COST'!$B$5 -> #REF! | D87: ='UTL COST'!$C$5 -> 45000 | E87: ='UTL COST'!$D$5 -> #REF! | K87: Electricity | L87: ='UTL COST'!$B$5 -> #REF! | M87: ='UTL COST'!$C$5 -> 45000 | N87: ='UTL COST'!$D$5 -> #REF!
B88: Water | C88: ='UTL COST'!$B$6 -> #REF! | D88: ='UTL COST'!$C$6 -> 525 | E88: 0.1 | K88: Water | L88: ='UTL COST'!$B$6 -> #REF! | M88: ='UTL COST'!$C$6 -> 525 | N88: 0.1
B89: TOTAL | E89: =IF(SUM(E85:E88)=0,"",SUM(E85:E88)) -> #REF! | K89: TOTAL | N89: =IF(SUM(N85:N88)=0,"",SUM(N85:N88)) -> #REF!
B95: DISH NAME | C95: Pasta Tuna | K95: DISH NAME | L95: Fit Fig Bowl
B97: EST. SALE PPRICE | C97: 205000 | K97: EST. SALE PPRICE | L97: 1300000 | N97: =L97/90000 -> 14.444444
B99: TOTAL COST | C99: =IF(SUM(E111,E126,E134)=0,"",SUM(E111,E126,E134)) -> #REF! | K99: TOTAL COST | L99: =IF(SUM(N111,N126,N134)=0,"",SUM(N111,N126,N134)) -> #REF! | N99: =L99/90000 -> #REF!
B101: COST MARGIN | C101: =IF(C99="","",IF(ISBLANK(C97),"",C99/C97)) -> #REF! | K101: COST MARGIN | L101: =IF(L99="","",IF(ISBLANK(L97),"",L99/L97)) -> #REF!
B103: NET PROFIT | C103: =C97-C99 -> #REF! | K103: NET PROFIT | L103: =L97-L99 -> #REF!
B106: PRIMARY INGREDIENTS | K106: PRIMARY INGREDIENTS
B107: Product Name | C107: Qty. | D107: Cost (per unit) | E107: Total Cost | K107: Product Name | L107: Qty. | M107: Cost (per unit) | N107: Total Cost
B108: Tuna Can | C108: 1 | D108: ='F&B'!$F$65 -> 9900 | E108: =IF(OR(ISBLANK(C108),ISBLANK(D108)),"",D108*C108) -> 9900 | K108: Halloumi Cheese | L108: 0.12 | M108: ='F&B'!$F$90 -> 108000 | N108: =IF(OR(ISBLANK(L108),ISBLANK(M108)),"",M108*L108) -> 12960 | O108: =N108/90000 -> 0.144
B109: Fusilli Pasta | C109: 0.2 | D109: ='F&B'!$F$242/12 -> 1125 | E109: =IF(OR(ISBLANK(C109),ISBLANK(D109)),"",D109*C109) -> 225 | K109: Lettuce Sucrine | L109: 0.5 | M109: =D518 -> 9000 | N109: =IF(OR(ISBLANK(L109),ISBLANK(M109)),"",M109*L109) -> 4500 | O109: =N109/90000 -> 0.05
K110: Pomegranate | L110: 0.06 | M110: =D214 -> 13500 | N110: =IF(OR(ISBLANK(L110),ISBLANK(M110)),"",M110*L110) -> 810 | O110: =N110/90000 -> 0.009
B111: TOTAL | E111: =IF(SUM(E108:E110)=0,"",SUM(E108:E110)) -> 10125 | K111: TOTAL | N111: =IF(SUM(N108:N110)=0,"",SUM(N108:N110)) -> 18270 | O111: =N111/90000 -> 0.203
O112: =N112/90000 -> 0
B113: SECONDARY INGREDIENTS | K113: SECONDARY INGREDIENTS | O113: =N113/90000 -> 0
B114: Product Name | C114: Qty | D114: Cost | E114: Total Cost | K114: Product Name | L114: Qty | M114: Cost | N114: Total Cost | O114: =N114/90000 -> #VALUE!
O115: =N115/90000 -> 0
B116: Lettuce | C116: 0.12 | D116: ='F&B'!$F$285 -> 8100 | E116: =D116*C116 -> 972 | K116: Rocket | L116: 1 | M116: ='F&B'!$F$280 -> 2970 | N116: =M116*L116 -> 2970 | O116: =N116/90000 -> 0.033
B117: Sweet Corn | C117: 0.05 | D117: ='F&B'!$F$60*3 -> 29700 | E117: =D117*C117 -> 1485 | K117: Lemon Mayo | L117: 1 | M117: =D120 -> 1303.0689 | N117: =M117*L117 -> 1303.0689 | O117: =N117/90000 -> 0.014478543
B118: Cherry Tomato | C118: 0.002 | D118: ='F&B'!$F$283 -> 9000 | E118: =D118*C118 -> 18 | K118: Dry Figs | L118: 0.04 | M118: ='F&B'!F189 -> 144000 | N118: =M118*L118 -> 5760 | O118: =N118/90000 -> 0.064
B119: Black Olives | C119: 0.02 | D119: =M30 -> 13764.706 | E119: =D119*C119 -> 275.29412 | K119: Frikeh Grain | L119: 0.3 | M119: =1*90000 -> 90000 | N119: =M119*L119 -> 27000 | O119: =N119/90000 -> 0.3
B120: Lemon Mayo | C120: 1 | D120: =SAUCES!$L$77 -> 1303.0689 | E120: =D120*C120 -> 1303.0689 | K120: Carrots | L120: 0.02 | M120: =D121 -> 6750 | N120: =M120*L120 -> 135 | O120: =N120/90000 -> 0.0015
B121: Carrots | C121: 0.01 | D121: ='F&B'!$F$293 -> 6750 | E121: =D121*C121 -> 67.5 | K121: Wallnuts | L121: 0.03 | M121: =D166 -> 65250 | N121: =M121*L121 -> 1957.5
E122: =D122*C122 -> 0 | N122: =M122*L122 -> 0
E123: =D123*C123 -> 0 | N123: =M123*L123 -> 0
E124: =D124*C124 -> 0 | N124: =M124*L124 -> 0
E125: =D125*C125 -> 0 | N125: =M125*L125 -> 0
B126: TOTAL | E126: =IF(SUM(E116:E125)=0,"",SUM(E116:E125)) -> 4120.863 | K126: TOTAL | N126: =IF(SUM(N116:N125)=0,"",SUM(N116:N125)) -> 39125.569
B128: UTILITY AND PREP. COST | K128: UTILITY AND PREP. COST
B129: Name | E129: Total Cost | K129: Name | N129: Total Cost
B130: Shorenting Oil | C130: ='UTL COST'!$B$3 -> 369000 | D130: ='UTL COST'!$C$3 -> 0.0075 | E130: 0 | K130: Shorenting Oil | L130: ='UTL COST'!$B$3 -> 369000 | M130: ='UTL COST'!$C$3 -> 0.0075 | N130: 0
B131: Gas | C131: ='UTL COST'!$B$4 -> #REF! | D131: ='UTL COST'!$C$4 -> 7000 | E131: 0 | K131: Gas | L131: ='UTL COST'!$B$4 -> #REF! | M131: ='UTL COST'!$C$4 -> 7000 | N131: ='UTL COST'!$D$4 -> #REF!
B132: Electricity | C132: ='UTL COST'!$B$5 -> #REF! | D132: ='UTL COST'!$C$5 -> 45000 | E132: ='UTL COST'!$D$5 -> #REF! | K132: Electricity | L132: ='UTL COST'!$B$5 -> #REF! | M132: ='UTL COST'!$C$5 -> 45000 | N132: ='UTL COST'!$D$5 -> #REF!
B133: Water | C133: ='UTL COST'!$B$6 -> #REF! | D133: ='UTL COST'!$C$6 -> 525 | E133: 0.1 | K133: Water | L133: ='UTL COST'!$B$6 -> #REF! | M133: ='UTL COST'!$C$6 -> 525 | N133: 0.1
B134: TOTAL | E134: =IF(SUM(E130:E133)=0,"",SUM(E130:E133)) -> #REF! | K134: TOTAL | N134: =IF(SUM(N130:N133)=0,"",SUM(N130:N133)) -> #REF!
B142: DISH NAME | C142: Pro's | K142: DISH NAME | L142: Crab
B144: EST. SALE PPRICE | C144: 230000 | K144: EST. SALE PPRICE | L144: 180000
B146: TOTAL COST | C146: =IF(SUM(E158,E173,E181)=0,"",SUM(E158,E173,E181)) -> #REF! | K146: TOTAL COST | L146: =IF(SUM(N158,N173,N181)=0,"",SUM(N158,N173,N181)) -> #REF!
B148: COST MARGIN | C148: =IF(C146="","",IF(ISBLANK(C144),"",C146/C144)) -> #REF! | K148: COST MARGIN | L148: =IF(L146="","",IF(ISBLANK(L144),"",L146/L144)) -> #REF!
...

Sheet HALF SALADS
A1: HALF SALADS FOOD COST
B6: DISH NAME | C6: Rocket Parmesan | K6: DISH NAME | L6: Greek
B8: EST. SALE PPRICE | C8: 140000 | K8: EST. SALE PPRICE | L8: 140000
B10: TOTAL COST | C10: =IF(SUM(E22,E37,E45)=0,"",SUM(E22,E37,E45)) -> #REF! | E10: =C10/90000 -> #REF! | K10: TOTAL COST | L10: =IF(SUM(N22,N37,N45)=0,"",SUM(N22,N37,N45)) -> #REF!
B12: COST MARGIN | C12: =IF(C10="","",IF(ISBLANK(C8),"",C10/C8)) -> #REF! | K12: COST MARGIN | L12: =IF(L10="","",IF(ISBLANK(L8),"",L10/L8)) -> #REF!
B14: NET PROFIT | C14: =C8-C10 -> #REF! | K14: NET PROFIT | L14: =L8-L10 -> #REF!
B17: PRIMARY INGREDIENTS | K17: PRIMARY INGREDIENTS
B18: Product Name | C18: Qty. | D18: Cost (per unit) | E18: Total Cost | K18: Product Name | L18: Qty. | M18: Cost (per unit) | N18: Total Cost
B19: Parmesan Cheese | C19: 0.02 | D19: ='F&B'!$F$103 -> 148500 | E19: =IF(OR(ISBLANK(C19),ISBLANK(D19)),"",D19*C19) -> 2970 | K19: Fetta Cheese | L19: 0.07 | M19: ='F&B'!$F$86 -> 44550 | N19: =IF(OR(ISBLANK(L19),ISBLANK(M19)),"",M19*L19) -> 3118.5
B20: Lemon Mustard Sauce | C20: 1 | D20: =SAUCES!$L$133 -> 1303.6607 | E20: =IF(OR(ISBLANK(C20),ISBLANK(D20)),"",D20*C20) -> 1303.6607 | K20: Lemon Mustard Sauce | L20: 1 | M20: =D20 -> 1303.6607 | N20: =IF(OR(ISBLANK(L20),ISBLANK(M20)),"",M20*L20) -> 1303.6607
E21: =IF(OR(ISBLANK(C21),ISBLANK(D21)),"",D21*C21) | N21: =IF(OR(ISBLANK(L21),ISBLANK(M21)),"",M21*L21)
B22: TOTAL | E22: =IF(SUM(E19:E21)=0,"",SUM(E19:E21)) -> 4273.6607 | K22: TOTAL | N22: =IF(SUM(N19:N21)=0,"",SUM(N19:N21)) -> 4422.1607
B24: SECONDARY INGREDIENTS | K24: SECONDARY INGREDIENTS
B25: Product Name | C25: Qty | D25: Cost | E25: Total Cost | K25: Product Name | L25: Qty | M25: Cost | N25: Total Cost
B27: Rocket Leaves | C27: 1 | D27: ='F&B'!$F$280 -> 2970 | E27: =D27*C27 -> 2970 | K27: Sucree | L27: 0.2 | M27: ='F&B'!$F$277 -> 13500 | N27: =M27*L27 -> 2700
B28: Fresh Mushrooms | C28: 0.05 | D28: ='F&B'!$F$278 -> 103500 | E28: =D28*C28 -> 5175 | K28: Tomato | L28: 0.15 | M28: ='F&B'!$F$279 -> 7200 | N28: =M28*L28 -> 1080
B29: Cherry Tomato | C29: 0.03 | D29: ='F&B'!$F$283 -> 9000 | E29: =D29*C29 -> 270 | K29: Cucumber | L29: 0.05 | M29: ='F&B'!$F$284 -> 7200 | N29: =M29*L29 -> 360
B30: Balsamic Sauce | C30: 0.06 | D30: =SAUCES!$D$36 -> 21446.564 | E30: =D30*C30 -> 1286.7938 | K30: Black Olives | L30: 0.03 | M30: ='F&B'!$F$44/17 -> 13764.706 | N30: =M30*L30 -> 412.94118
B31: Walnuts | C31: 0.02 | D31: ='F&B'!$F$146 -> 65250 | E31: =D31*C31 -> 1305 | K31: Oregano | L31: 0.001 | M31: ='F&B'!$F$167 -> 37800 | N31: =M31*L31 -> 37.8
B32: Pomegranate | C32: 0.01 | D32: ='F&B'!$F$300 -> 13500 | E32: =D32*C32 -> 135 | K32: Olive Oil | L32: 0.002
E33: =D33*C33 -> 0 | K33: Bell Peppers | L33: 0.03 | M33: ='F&B'!$F$296 -> 9000 | N33: =M33*L33 -> 270
E34: =D34*C34 -> 0
E35: =D35*C35 -> 0
E36: =D36*C36 -> 0 | N36: =M36*L36 -> 0
B37: TOTAL | E37: =IF(SUM(E27:E36)=0,"",SUM(E27:E36)) -> 11141.794 | K37: TOTAL | N37: =IF(SUM(N27:N36)=0,"",SUM(N27:N36)) -> 4860.7412
B39: UTILITY AND PREP. COST | K39: UTILITY AND PREP. COST
B40: Name | E40: Total Cost | K40: Name | N40: Total Cost
B41: Shorenting Oil | C41: ='UTL COST'!$B$3 -> 369000 | D41: ='UTL COST'!$C$3 -> 0.0075 | E41: 0 | K41: Shorenting Oil | L41: ='UTL COST'!$B$3 -> 369000 | M41: ='UTL COST'!$C$3 -> 0.0075 | N41: 0
B42: Gas | C42: ='UTL COST'!$B$4 -> #REF! | D42: ='UTL COST'!$C$4 -> 7000 | E42: 0 | K42: Gas | L42: ='UTL COST'!$B$4 -> #REF! | M42: ='UTL COST'!$C$4 -> 7000 | N42: 0
B43: Electricity | C43: ='UTL COST'!$B$5 -> #REF! | D43: ='UTL COST'!$C$5 -> 45000 | E43: ='UTL COST'!$D$5 -> #REF! | K43: Electricity | L43: ='UTL COST'!$B$5 -> #REF! | M43: ='UTL COST'!$C$5 -> 45000 | N43: ='UTL COST'!$D$5 -> #REF!
B44: Water | C44: ='UTL COST'!$B$6 -> #REF! | D44: ='UTL COST'!$C$6 -> 525 | E44: 0.1 | K44: Water | L44: ='UTL COST'!$B$6 -> #REF! | M44: ='UTL COST'!$C$6 -> 525 | N44: 0.1
B45: TOTAL | E45: =IF(SUM(E41:E44)=0,"",SUM(E41:E44)) -> #REF! | K45: TOTAL | N45: =IF(SUM(N41:N44)=0,"",SUM(N41:N44)) -> #REF!
B50: DISH NAME | C50: Caesar | K50: DISH NAME | L50: Caesar Chicken
B52: EST. SALE PPRICE | C52: 145000 | K52: EST. SALE PPRICE | L52: 180000
B54: TOTAL COST | C54: =IF(SUM(E66,E81,E89)=0,"",SUM(E66,E81,E89)) -> #REF! | K54: TOTAL COST | L54: =IF(SUM(N66,N81,N89)=0,"",SUM(N66,N81,N89)) -> #REF!
B56: COST MARGIN | C56: =IF(C54="","",IF(ISBLANK(C52),"",C54/C52)) -> #REF! | K56: COST MARGIN | L56: =IF(L54="","",IF(ISBLANK(L52),"",L54/L52)) -> #REF!
B58: NET PROFIT | C58: =C52-C54 -> #REF! | K58: NET PROFIT | L58: =L52-L54 -> #REF!
B61: PRIMARY INGREDIENTS | K61: PRIMARY INGREDIENTS
B62: Product Name | C62: Qty. | D62: Cost (per unit) | E62: Total Cost | K62: Product Name | L62: Qty. | M62: Cost (per unit) | N62: Total Cost
B63: Parmesan Cheese | C63: 0.02 | D63: =D19 -> 148500 | E63: =IF(OR(ISBLANK(C63),ISBLANK(D63)),"",D63*C63) -> 2970 | K63: Chicken Breast | L63: 0.09 | M63: =SANDWICHES!$D$19 -> 81000 | N63: =IF(OR(ISBLANK(L63),ISBLANK(M63)),"",M63*L63) -> 7290
E64: =IF(OR(ISBLANK(C64),ISBLANK(D64)),"",D64*C64) | K64: Parmesan Cheese | L64: 0.02 | M64: =D63 -> 148500 | N64: =IF(OR(ISBLANK(L64),ISBLANK(M64)),"",M64*L64) -> 2970
E65: =IF(OR(ISBLANK(C65),ISBLANK(D65)),"",D65*C65)
B66: TOTAL | E66: =IF(SUM(E63:E65)=0,"",SUM(E63:E65)) -> 2970 | K66: TOTAL | N66: =IF(SUM(N63:N65)=0,"",SUM(N63:N65)) -> 10260
B68: SECONDARY INGREDIENTS | K68: SECONDARY INGREDIENTS
B69: Product Name | C69: Qty | D69: Cost | E69: Total Cost | K69: Product Name | L69: Qty | M69: Cost | N69: Total Cost
B71: Iceberg | C71: 0.3 | D71: =M27 -> 13500 | E71: =D71*C71 -> 4050 | K71: Iceberg | L71: 0.3 | M71: =M27 -> 13500 | N71: =M71*L71 -> 4050
B72: Croutons | C72: 0.02 | D72: =Prep!J80 -> 71480.654 | E72: 5000 | K72: Croutons | L72: 0.02 | M72: =Prep!J80 -> 71480.654 | N72: 5000
B73: Caesar Sauce | C73: 1 | D73: =SAUCES!$D$16 -> 3406.9479 | E73: =D73*C73 -> 3406.9479 | K73: Caesar Sauce | L73: 1 | M73: =SAUCES!$D$16 -> 3406.9479 | N73: =M73*L73 -> 3406.9479
B74: Cherry Tomato | C74: 0.03 | D74: ='F&B'!$F$283 -> 9000 | E74: =D74*C74 -> 270 | K74: Cherry Tomato | L74: 0.03 | M74: ='F&B'!$F$283 -> 9000 | N74: =M74*L74 -> 270
E75: =D75*C75 -> 0 | N75: =M75*L75 -> 0
E76: =D76*C76 -> 0 | N76: =M76*L76 -> 0
E77: =D77*C77 -> 0 | N77: =M77*L77 -> 0
E78: =D78*C78 -> 0 | N78: =M78*L78 -> 0
E79: =D79*C79 -> 0 | N79: =M79*L79 -> 0
E80: =D80*C80 -> 0 | N80: =M80*L80 -> 0
B81: TOTAL | E81: =IF(SUM(E71:E80)=0,"",SUM(E71:E80)) -> 12726.948 | K81: TOTAL | N81: =IF(SUM(N71:N80)=0,"",SUM(N71:N80)) -> 12726.948
B83: UTILITY AND PREP. COST | K83: UTILITY AND PREP. COST
B84: Name | E84: Total Cost | K84: Name | N84: Total Cost
B85: Shorenting Oil | C85: ='UTL COST'!$B$3 -> 369000 | D85: ='UTL COST'!$C$3 -> 0.0075 | E85: 0 | K85: Shorenting Oil | L85: ='UTL COST'!$B$3 -> 369000 | M85: ='UTL COST'!$C$3 -> 0.0075 | N85: 0
B86: Gas | C86: ='UTL COST'!$B$4 -> #REF! | D86: ='UTL COST'!$C$4 -> 7000 | E86: 0 | K86: Gas | L86: ='UTL COST'!$B$4 -> #REF! | M86: ='UTL COST'!$C$4 -> 7000 | N86: ='UTL COST'!$D$4 -> #REF!
B87: Electricity | C87: ='UTL COST'!$B$5 -> #REF! | D87: ='UTL COST'!$C$5 -> 45000 | E87: ='UTL COST'!$D$5 -> #REF! | K87: Electricity | L87: ='UTL COST'!$B$5 -> #REF! | M87: ='UTL COST'!$C$5 -> 45000 | N87: ='UTL COST'!$D$5 -> #REF!
B88: Water | C88: ='UTL COST'!$B$6 -> #REF! | D88: ='UTL COST'!$C$6 -> 525 | E88: 0.1 | K88: Water | L88: ='UTL COST'!$B$6 -> #REF! | M88: ='UTL COST'!$C$6 -> 525 | N88: 0.1
B89: TOTAL | E89: =IF(SUM(E85:E88)=0,"",SUM(E85:E88)) -> #REF! | K89: TOTAL | N89: =IF(SUM(N85:N88)=0,"",SUM(N85:N88)) -> #REF!
B95: DISH NAME | C95: Pasta Tuna | K95: DISH NAME | L95: Fit Fig Bowl
B97: EST. SALE PPRICE | C97: 205000 | K97: EST. SALE PPRICE | L97: 1300000 | N97: =L97/90000 -> 14.444444
B99: TOTAL COST | C99: =IF(SUM(E111,E126,E134)=0,"",SUM(E111,E126,E134)) -> #REF! | K99: TOTAL COST | L99: =IF(SUM(N111,N126,N134)=0,"",SUM(N111,N126,N134)) -> #REF! | N99: =L99/90000 -> #REF!
B101: COST MARGIN | C101: =IF(C99="","",IF(ISBLANK(C97),"",C99/C97)) -> #REF! | K101: COST MARGIN | L101: =IF(L99="","",IF(ISBLANK(L97),"",L99/L97)) -> #REF!
B103: NET PROFIT | C103: =C97-C99 -> #REF! | K103: NET PROFIT | L103: =L97-L99 -> #REF!
B106: PRIMARY INGREDIENTS | K106: PRIMARY INGREDIENTS
B107: Product Name | C107: Qty. | D107: Cost (per unit) | E107: Total Cost | K107: Product Name | L107: Qty. | M107: Cost (per unit) | N107: Total Cost
B108: Tuna Can | C108: 0.5 | D108: ='F&B'!$F$65 -> 9900 | E108: =IF(OR(ISBLANK(C108),ISBLANK(D108)),"",D108*C108) -> 4950 | K108: Halloumi Cheese | L108: 0.12 | M108: ='F&B'!$F$90 -> 108000 | N108: =IF(OR(ISBLANK(L108),ISBLANK(M108)),"",M108*L108) -> 12960 | O108: =N108/90000 -> 0.144
B109: Fusilli Pasta | C109: 0.25 | D109: ='F&B'!$F$242/8 -> 1687.5 | E109: =IF(OR(ISBLANK(C109),ISBLANK(D109)),"",D109*C109) -> 421.875 | K109: Lettuce Sucrine | L109: 0.5 | M109: =D518 -> 9000 | N109: =IF(OR(ISBLANK(L109),ISBLANK(M109)),"",M109*L109) -> 4500 | O109: =N109/90000 -> 0.05
B110: Argula | C110: 0.03 | K110: Pomegranate | L110: 0.06 | M110: =D214 -> 13500 | N110: =IF(OR(ISBLANK(L110),ISBLANK(M110)),"",M110*L110) -> 810 | O110: =N110/90000 -> 0.009
B111: TOTAL | E111: =IF(SUM(E108:E110)=0,"",SUM(E108:E110)) -> 5371.875 | K111: TOTAL | N111: =IF(SUM(N108:N110)=0,"",SUM(N108:N110)) -> 18270 | O111: =N111/90000 -> 0.203
O112: =N112/90000 -> 0
B113: SECONDARY INGREDIENTS | K113: SECONDARY INGREDIENTS | O113: =N113/90000 -> 0
B114: Product Name | C114: Qty | D114: Cost | E114: Total Cost | K114: Product Name | L114: Qty | M114: Cost | N114: Total Cost | O114: =N114/90000 -> #VALUE!
O115: =N115/90000 -> 0
B116: Iceburg | C116: 0.05 | D116: =M27 -> 13500 | E116: =D116*C116 -> 675 | K116: Rocket | L116: 1 | M116: ='F&B'!$F$280 -> 2970 | N116: =M116*L116 -> 2970 | O116: =N116/90000 -> 0.033
B117: Sweet Corn | C117: 0.05 | D117: ='F&B'!$F$60*3 -> 29700 | E117: =D117*C117 -> 1485 | K117: Lemon Mayo | L117: 1 | M117: =D120 -> 1303.0689 | N117: =M117*L117 -> 1303.0689 | O117: =N117/90000 -> 0.014478543
B118: Cherry Tomato | C118: 0.05 | D118: ='F&B'!$F$283 -> 9000 | E118: =D118*C118 -> 450 | K118: Dry Figs | L118: 0.04 | M118: ='F&B'!F189 -> 144000 | N118: =M118*L118 -> 5760 | O118: =N118/90000 -> 0.064
B119: Black Olives | C119: 0.03 | D119: =M30 -> 13764.706 | E119: =D119*C119 -> 412.94118 | K119: Frikeh Grain | L119: 0.3 | M119: =1*90000 -> 90000 | N119: =M119*L119 -> 27000 | O119: =N119/90000 -> 0.3
B120: Lemon Mayo | C120: 1 | D120: =SAUCES!$L$77 -> 1303.0689 | E120: =D120*C120 -> 1303.0689 | K120: Carrots | L120: 0.02 | M120: =D121 -> 6750 | N120: =M120*L120 -> 135 | O120: =N120/90000 -> 0.0015
B121: Carrots | C121: 0.05 | D121: ='F&B'!$F$293 -> 6750 | E121: =D121*C121 -> 337.5 | K121: Wallnuts | L121: 0.03 | M121: =D166 -> 65250 | N121: =M121*L121 -> 1957.5
E122: =D122*C122 -> 0 | N122: =M122*L122 -> 0
E123: =D123*C123 -> 0 | N123: =M123*L123 -> 0
E124: =D124*C124 -> 0 | N124: =M124*L124 -> 0
E125: =D125*C125 -> 0 | N125: =M125*L125 -> 0
B126: TOTAL | E126: =IF(SUM(E116:E125)=0,"",SUM(E116:E125)) -> 4663.5101 | K126: TOTAL | N126: =IF(SUM(N116:N125)=0,"",SUM(N116:N125)) -> 39125.569
B128: UTILITY AND PREP. COST | K128: UTILITY AND PREP. COST
B129: Name | E129: Total Cost | K129: Name | N129: Total Cost
B130: Shorenting Oil | C130: ='UTL COST'!$B$3 -> 369000 | D130: ='UTL COST'!$C$3 -> 0.0075 | E130: 0 | K130: Shorenting Oil | L130: ='UTL COST'!$B$3 -> 369000 | M130: ='UTL COST'!$C$3 -> 0.0075 | N130: 0
B131: Gas | C131: ='UTL COST'!$B$4 -> #REF! | D131: ='UTL COST'!$C$4 -> 7000 | E131: 0 | K131: Gas | L131: ='UTL COST'!$B$4 -> #REF! | M131: ='UTL COST'!$C$4 -> 7000 | N131: ='UTL COST'!$D$4 -> #REF!
B132: Electricity | C132: ='UTL COST'!$B$5 -> #REF! | D132: ='UTL COST'!$C$5 -> 45000 | E132: ='UTL COST'!$D$5 -> #REF! | K132: Electricity | L132: ='UTL COST'!$B$5 -> #REF! | M132: ='UTL COST'!$C$5 -> 45000 | N132: ='UTL COST'!$D$5 -> #REF!
B133: Water | C133: ='UTL COST'!$B$6 -> #REF! | D133: ='UTL COST'!$C$6 -> 525 | E133: 0.1 | K133: Water | L133: ='UTL COST'!$B$6 -> #REF! | M133: ='UTL COST'!$C$6 -> 525 | N133: 0.1
B134: TOTAL | E134: =IF(SUM(E130:E133)=0,"",SUM(E130:E133)) -> #REF! | K134: TOTAL | N134: =IF(SUM(N130:N133)=0,"",SUM(N130:N133)) -> #REF!
B142: DISH NAME | C142: Pro's | K142: DISH NAME | L142: Crab
B144: EST. SALE PPRICE | C144: 230000 | K144: EST. SALE PPRICE | L144: 180000
B146: TOTAL COST | C146: =IF(SUM(E158,E173,E181)=0,"",SUM(E158,E173,E181)) -> #REF! | K146: TOTAL COST | L146: =IF(SUM(N158,N173,N181)=0,"",SUM(N158,N173,N181)) -> #REF!
B148: COST MARGIN | C148: =IF(C146="","",IF(ISBLANK(C144),"",C146/C144)) -> #REF! | K148: COST MARGIN | L148: =IF(L146="","",IF(ISBLANK(L144),"",L146/L144)) -> #REF!
...

Sheet MANAKISH
A1: MANAKISH FOOD COST
B6: DISH NAME | C6: Zaatar | K6: DISH NAME | L6: Cheese | R6: DISH NAME | S6: Cheese + Zaatar
B8: EST. SALE PPRICE | C8: 30000 | K8: EST. SALE PPRICE | L8: 50000 | R8: EST. SALE PPRICE | S8: 50000
B10: TOTAL COST | C10: =IF(SUM(E22,E37,E45)=0,"",SUM(E22,E37,E45)) -> #REF! | H10: =C10/90000 -> #REF! | K10: TOTAL COST | L10: =IF(SUM(N22,N37,N45)=0,"",SUM(N22,N37,N45)) -> #REF! | P10: =L10/90000 -> #REF! | R10: TOTAL COST | S10: =IF(SUM(U22,U37,U45)=0,"",SUM(U22,U37,U45)) -> 6755.5231
B12: COST MARGIN | C12: =IF(C10="","",IF(ISBLANK(C8),"",C10/C8)) -> #REF! | K12: COST MARGIN | L12: =IF(L10="","",IF(ISBLANK(L8),"",L10/L8)) -> #REF! | R12: COST MARGIN | S12: =IF(S10="","",IF(ISBLANK(S8),"",S10/S8)) -> 0.13511046
B14: NET PROFIT | C14: =C8-C10 -> #REF! | K14: NET PROFIT | L14: =L8-L10 -> #REF! | R14: NET PROFIT | S14: =S8-S10 -> 43244.477
B17: PRIMARY INGREDIENTS | K17: PRIMARY INGREDIENTS | R17: PRIMARY INGREDIENTS
B18: Product Name | C18: Qty. | D18: Cost (per unit) | E18: Total Cost | K18: Product Name | L18: Qty. | M18: Cost (per unit) | N18: Total Cost | R18: Product Name | S18: Qty. | T18: Cost (per unit) | U18: Total Cost
K19: Mozzarella Cheese | L19: 0.16 | M19: ='F&B'!$F$99/12 -> 63000 | N19: =IF(OR(ISBLANK(L19),ISBLANK(M19)),"",M19*L19) -> 10080 | R19: Mozzarella Cheese | S19: 0.08 | T19: ='F&B'!$F$99/12 -> 63000 | U19: =IF(OR(ISBLANK(S19),ISBLANK(T19)),"",T19*S19) -> 5040
K20: Dough | L20: 1 | M20: =SAUCES!$D$92 -> 900.92308 | N20: =IF(OR(ISBLANK(L20),ISBLANK(M20)),"",M20*L20) -> 900.92308 | R20: Dough | S20: 1 | T20: =SAUCES!$D$92 -> 900.92308 | U20: =IF(OR(ISBLANK(S20),ISBLANK(T20)),"",T20*S20) -> 900.92308
B21: Dough | C21: 1 | D21: =SAUCES!$D$92 -> 900.92308 | E21: =IF(OR(ISBLANK(C21),ISBLANK(D21)),"",D21*C21) -> 900.92308 | N21: =IF(OR(ISBLANK(L21),ISBLANK(M21)),"",M21*L21) | U21: =IF(OR(ISBLANK(S21),ISBLANK(T21)),"",T21*S21)
B22: TOTAL | E22: =IF(SUM(E19:E21)=0,"",SUM(E19:E21)) -> 900.92308 | K22: TOTAL | N22: =IF(SUM(N19:N21)=0,"",SUM(N19:N21)) -> 10980.923 | R22: TOTAL | U22: =IF(SUM(U19:U21)=0,"",SUM(U19:U21)) -> 5940.9231
B24: SECONDARY INGREDIENTS | K24: SECONDARY INGREDIENTS | R24: SECONDARY INGREDIENTS
B25: Product Name | C25: Qty | D25: Cost | E25: Total Cost | K25: Product Name | L25: Qty | M25: Cost | N25: Total Cost | R25: Product Name | S25: Qty | T25: Cost | U25: Total Cost
B27: Zaatar | C27: 0.01 | D27: ='F&B'!$F$175 -> 51750 | E27: =D27*C27 -> 517.5 | N27: =M27*L27 -> 0 | R27: Zaatar | S27: 0.01 | T27: ='F&B'!$F$175 -> 51750 | U27: =T27*S27 -> 517.5
B28: Sunflower Oil | C28: 0.03 | D28: ='F&B'!$F$57/15 -> 9900 | E28: =D28*C28 -> 297 | N28: =M28*L28 -> 0 | R28: Sunflower Oil | S28: 0.03 | T28: ='F&B'!$F$57/15 -> 9900 | U28: =T28*S28 -> 297
E29: =D29*C29 -> 0 | N29: =M29*L29 -> 0 | U29: =T29*S29 -> 0
E30: =D30*C30 -> 0 | N30: =M30*L30 -> 0 | U30: =T30*S30 -> 0
E31: =D31*C31 -> 0 | N31: =M31*L31 -> 0 | U31: =T31*S31 -> 0
E32: =D32*C32 -> 0 | N32: =M32*L32 -> 0 | U32: =T32*S32 -> 0
E33: =D33*C33 -> 0 | N33: =M33*L33 -> 0 | U33: =T33*S33 -> 0
E34: =D34*C34 -> 0 | N34: =M34*L34 -> 0 | U34: =T34*S34 -> 0
E35: =D35*C35 -> 0 | N35: =M35*L35 -> 0 | U35: =T35*S35 -> 0
E36: =D36*C36 -> 0 | N36: =M36*L36 -> 0 | U36: =T36*S36 -> 0
B37: TOTAL | E37: =IF(SUM(E27:E36)=0,"",SUM(E27:E36)) -> 814.5 | K37: TOTAL | N37: =IF(SUM(N27:N36)=0,"",SUM(N27:N36)) | R37: TOTAL | U37: =IF(SUM(U27:U36)=0,"",SUM(U27:U36)) -> 814.5
B39: UTILITY AND PREP. COST | K39: UTILITY AND PREP. COST | R39: UTILITY AND PREP. COST
B40: Name | E40: Total Cost | K40: Name | N40: Total Cost | R40: Name | U40: Total Cost
B41: Shorenting Oil | C41: ='UTL COST'!$B$3 -> 369000 | D41: ='UTL COST'!$C$3 -> 0.0075 | E41: 0 | K41: Shorenting Oil | L41: ='UTL COST'!$B$3 -> 369000 | M41: ='UTL COST'!$C$3 -> 0.0075 | N41: 0 | R41: Shorenting Oil | S41: ='UTL COST'!$B$3 -> 369000 | T41: ='UTL COST'!$C$3 -> 0.0075 | U41: 0
B42: Gas | C42: ='UTL COST'!$B$4 -> #REF! | D42: ='UTL COST'!$C$4 -> 7000 | E42: ='UTL COST'!$D$4 -> #REF! | K42: Gas | L42: ='UTL COST'!$B$4 -> #REF! | M42: ='UTL COST'!$C$4 -> 7000 | N42: ='UTL COST'!$D$4 -> #REF! | R42: Gas | S42: ='UTL COST'!$B$4 -> #REF! | T42: ='UTL COST'!$C$4 -> 7000
B43: Electricity | C43: ='UTL COST'!$B$5 -> #REF! | D43: ='UTL COST'!$C$5 -> 45000 | E43: ='UTL COST'!$D$5 -> #REF! | K43: Electricity | L43: ='UTL COST'!$B$5 -> #REF! | M43: ='UTL COST'!$C$5 -> 45000 | N43: ='UTL COST'!$D$5 -> #REF! | R43: Electricity | S43: ='UTL COST'!$B$5 -> #REF! | T43: ='UTL COST'!$C$5 -> 45000
B44: Water | C44: ='UTL COST'!$B$6 -> #REF! | D44: ='UTL COST'!$C$6 -> 525 | E44: 0.1 | K44: Water | L44: ='UTL COST'!$B$6 -> #REF! | M44: ='UTL COST'!$C$6 -> 525 | N44: 0.1 | R44: Water | S44: ='UTL COST'!$B$6 -> #REF! | T44: ='UTL COST'!$C$6 -> 525 | U44: 0.1
B45: TOTAL | E45: =IF(SUM(E41:E44)=0,"",SUM(E41:E44)) -> #REF! | K45: TOTAL | N45: =IF(SUM(N41:N44)=0,"",SUM(N41:N44)) -> #REF! | R45: TOTAL | U45: =IF(SUM(U41:U44)=0,"",SUM(U41:U44)) -> 0.1
B50: DISH NAME | C50: Turkey Cheese | K50: DISH NAME | L50: Kafta Cheese
B52: EST. SALE PPRICE | C52: 105000 | K52: EST. SALE PPRICE | L52: 115000
B54: TOTAL COST | C54: =IF(SUM(E67,E82,E90)=0,"",SUM(E67,E82,E90)) -> #REF! | K54: TOTAL COST | L54: =IF(SUM(N67,N82,N90)=0,"",SUM(N67,N82,N90)) -> #REF!
B56: COST MARGIN | C56: =IF(C54="","",IF(ISBLANK(C52),"",C54/C52)) -> #REF! | K56: COST MARGIN | L56: =IF(L54="","",IF(ISBLANK(L52),"",L54/L52)) -> #REF!
B58: NET PROFIT | C58: =C52-C54 -> #REF! | K58: NET PROFIT | L58: =L52-L54 -> #REF!
B62: PRIMARY INGREDIENTS | K62: PRIMARY INGREDIENTS
B63: Product Name | C63: Qty. | D63: Cost (per unit) | E63: Total Cost | K63: Product Name | L63: Qty. | M63: Cost (per unit) | N63: Total Cost
B64: Mozzarella Cheese | C64: 0.16 | D64: =M19 -> 63000 | E64: =IF(OR(ISBLANK(C64),ISBLANK(D64)),"",D64*C64) -> 10080 | K64: Kafta | L64: 0.15 | M64: ='F&B'!$F$209 -> 99000 | N64: =IF(OR(ISBLANK(L64),ISBLANK(M64)),"",M64*L64) -> 14850
B65: Turkey | C65: 0.07 | D65: ='F&B'!$F$223 -> 142920 | E65: =IF(OR(ISBLANK(C65),ISBLANK(D65)),"",D65*C65) -> 10004.4 | K65: Mozzarella Cheese | L65: 0.08 | M65: =M19 -> 63000 | N65: =IF(OR(ISBLANK(L65),ISBLANK(M65)),"",M65*L65) -> 5040
B66: Dough | C66: 1 | D66: =SAUCES!$D$92 -> 900.92308 | E66: =IF(OR(ISBLANK(C66),ISBLANK(D66)),"",D66*C66) -> 900.92308 | K66: Dough | L66: 1 | M66: =SAUCES!$D$92 -> 900.92308 | N66: =IF(OR(ISBLANK(L66),ISBLANK(M66)),"",M66*L66) -> 900.92308
B67: TOTAL | E67: =IF(SUM(E64:E66)=0,"",SUM(E64:E66)) -> 20985.323 | K67: TOTAL | N67: =IF(SUM(N64:N66)=0,"",SUM(N64:N66)) -> 20790.923
B69: SECONDARY INGREDIENTS | K69: SECONDARY INGREDIENTS
B70: Product Name | C70: Qty | D70: Cost | E70: Total Cost | K70: Product Name | L70: Qty | M70: Cost | N70: Total Cost
E72: =D72*C72 -> 0 | K72: Mayonaise | L72: 0.04 | M72: ='F&B'!$F$250/3.78 -> 28809.524 | N72: =M72*L72 -> 1152.381
E73: =D73*C73 -> 0 | K73: Tomato | L73: 0.06 | M73: ='F&B'!$F$279 -> 7200 | N73: =M73*L73 -> 432
E74: =D74*C74 -> 0 | K74: Pickles | L74: 0.01 | M74: ='F&B'!$F$49/10 -> 13500 | N74: =M74*L74 -> 135
E75: =D75*C75 -> 0 | N75: =M75*L75 -> 0
E76: =D76*C76 -> 0 | N76: =M76*L76 -> 0
E77: =D77*C77 -> 0 | N77: =M77*L77 -> 0
E78: =D78*C78 -> 0 | N78: =M78*L78 -> 0
E79: =D79*C79 -> 0 | N79: =M79*L79 -> 0
E80: =D80*C80 -> 0 | N80: =M80*L80 -> 0
E81: =D81*C81 -> 0 | N81: =M81*L81 -> 0
B82: TOTAL | E82: =IF(SUM(E72:E81)=0,"",SUM(E72:E81)) | K82: TOTAL | N82: =IF(SUM(N72:N81)=0,"",SUM(N72:N81)) -> 1719.381
B84: UTILITY AND PREP. COST | K84: UTILITY AND PREP. COST
B85: Name | E85: Total Cost | K85: Name | N85: Total Cost
B86: Shorenting Oil | C86: ='UTL COST'!$B$3 -> 369000 | D86: ='UTL COST'!$C$3 -> 0.0075 | E86: 0 | K86: Shorenting Oil | L86: ='UTL COST'!$B$3 -> 369000 | M86: ='UTL COST'!$C$3 -> 0.0075 | N86: 0
B87: Gas | C87: ='UTL COST'!$B$4 -> #REF! | D87: ='UTL COST'!$C$4 -> 7000 | E87: ='UTL COST'!$D$4 -> #REF! | K87: Gas | L87: ='UTL COST'!$B$4 -> #REF! | M87: ='UTL COST'!$C$4 -> 7000 | N87: ='UTL COST'!$D$4 -> #REF!
B88: Electricity | C88: ='UTL COST'!$B$5 -> #REF! | D88: ='UTL COST'!$C$5 -> 45000 | E88: ='UTL COST'!$D$5 -> #REF! | K88: Electricity | L88: ='UTL COST'!$B$5 -> #REF! | M88: ='UTL COST'!$C$5 -> 45000 | N88: ='UTL COST'!$D$5 -> #REF!
B89: Water | C89: ='UTL COST'!$B$6 -> #REF! | D89: ='UTL COST'!$C$6 -> 525 | E89: 0.1 | K89: Water | L89: ='UTL COST'!$B$6 -> #REF! | M89: ='UTL COST'!$C$6 -> 525 | N89: 0.1
B90: TOTAL | E90: =IF(SUM(E86:E89)=0,"",SUM(E86:E89)) -> #REF! | K90: TOTAL | N90: =IF(SUM(N86:N89)=0,"",SUM(N86:N89)) -> #REF!
B96: DISH NAME | C96: Soujok Cheese Dough | K96: DISH NAME
B98: EST. SALE PPRICE | C98: 115000 | K98: EST. SALE PPRICE | L98: 75000
B100: TOTAL COST | C100: =IF(SUM(E112,E127,E135)=0,"",SUM(E112,E127,E135)) -> #REF! | K100: TOTAL COST | L100: =IF(SUM(N112,N127,N135)=0,"",SUM(N112,N127,N135)) -> #REF!
B102: COST MARGIN | C102: =IF(C100="","",IF(ISBLANK(C98),"",C100/C98)) -> #REF! | K102: COST MARGIN | L102: =IF(L100="","",IF(ISBLANK(L98),"",L100/L98)) -> #REF!
B104: NET PROFIT | C104: =C98-C100 -> #REF! | K104: NET PROFIT | L104: =L98-L100 -> #REF!
B107: PRIMARY INGREDIENTS | K107: PRIMARY INGREDIENTS
B108: Product Name | C108: Qty. | D108: Cost (per unit) | E108: Total Cost | K108: Product Name | L108: Qty. | M108: Cost (per unit) | N108: Total Cost
B109: Soujok | C109: 0.075 | D109: 220000 | E109: =IF(OR(ISBLANK(C109),ISBLANK(D109)),"",D109*C109) -> 16500 | K109: Fetta Cheese | L109: 0.15 | M109: ='F&B'!$F$86 -> 44550 | N109: =IF(OR(ISBLANK(L109),ISBLANK(M109)),"",M109*L109) -> 6682.5
B110: Mozzarella Cheese | C110: 0.08 | D110: =M19 -> 63000 | E110: =IF(OR(ISBLANK(C110),ISBLANK(D110)),"",D110*C110) -> 5040 | K110: Mozzarella Cheese | L110: 0.05 | M110: =M65 -> 63000 | N110: =IF(OR(ISBLANK(L110),ISBLANK(M110)),"",M110*L110) -> 3150
B111: Dough | C111: 1 | D111: =SAUCES!$D$92 -> 900.92308 | E111: =IF(OR(ISBLANK(C111),ISBLANK(D111)),"",D111*C111) -> 900.92308 | K111: Dough | L111: 1 | M111: =SAUCES!$D$92 -> 900.92308 | N111: =IF(OR(ISBLANK(L111),ISBLANK(M111)),"",M111*L111) -> 900.92308
B112: TOTAL | E112: =IF(SUM(E109:E111)=0,"",SUM(E109:E111)) -> 22440.923 | K112: TOTAL | N112: =IF(SUM(N109:N111)=0,"",SUM(N109:N111)) -> 10733.423
B114: SECONDARY INGREDIENTS | K114: SECONDARY INGREDIENTS
B115: Product Name | C115: Qty | D115: Cost | E115: Total Cost | K115: Product Name | L115: Qty | M115: Cost | N115: Total Cost
B117: Mayonaise | C117: 0.04 | D117: =M72 -> 28809.524 | E117: =D117*C117 -> 1152.381 | K117: Onions | L117: 0.03 | M117: ='F&B'!$F$290 -> 6300 | N117: =M117*L117 -> 189
B118: Tomato | C118: 0.06 | D118: =M73 -> 7200 | E118: =D118*C118 -> 432 | K118: Tomato | L118: 0.06 | M118: =M73 -> 7200 | N118: =M118*L118 -> 432
B119: Pickles | C119: 0.01 | D119: =M74 -> 13500 | E119: =D119*C119 -> 135 | N119: =M119*L119 -> 0
E120: =D120*C120 -> 0 | N120: =M120*L120 -> 0
E121: =D121*C121 -> 0 | N121: =M121*L121 -> 0
E122: =D122*C122 -> 0 | N122: =M122*L122 -> 0
E123: =D123*C123 -> 0 | N123: =M123*L123 -> 0
E124: =D124*C124 -> 0 | N124: =M124*L124 -> 0
E125: =D125*C125 -> 0 | N125: =M125*L125 -> 0
E126: =D126*C126 -> 0 | N126: =M126*L126 -> 0
B127: TOTAL | E127: =IF(SUM(E117:E126)=0,"",SUM(E117:E126)) -> 1719.381 | K127: TOTAL | N127: =IF(SUM(N117:N126)=0,"",SUM(N117:N126)) -> 621
B129: UTILITY AND PREP. COST | K129: UTILITY AND PREP. COST
B130: Name | E130: Total Cost | K130: Name | N130: Total Cost
B131: Shorenting Oil | C131: ='UTL COST'!$B$3 -> 369000 | D131: ='UTL COST'!$C$3 -> 0.0075 | E131: 0 | K131: Shorenting Oil | L131: ='UTL COST'!$B$3 -> 369000 | M131: ='UTL COST'!$C$3 -> 0.0075 | N131: 0
B132: Gas | C132: ='UTL COST'!$B$4 -> #REF! | D132: ='UTL COST'!$C$4 -> 7000 | E132: ='UTL COST'!$D$4 -> #REF! | K132: Gas | L132: ='UTL COST'!$B$4 -> #REF! | M132: ='UTL COST'!$C$4 -> 7000 | N132: ='UTL COST'!$D$4 -> #REF!
B133: Electricity | C133: ='UTL COST'!$B$5 -> #REF! | D133: ='UTL COST'!$C$5 -> 45000 | E133: ='UTL COST'!$D$5 -> #REF! | K133: Electricity | L133: ='UTL COST'!$B$5 -> #REF! | M133: ='UTL COST'!$C$5 -> 45000 | N133: ='UTL COST'!$D$5 -> #REF!
B134: Water | C134: ='UTL COST'!$B$6 -> #REF! | D134: ='UTL COST'!$C$6 -> 525 | E134: 0.1 | K134: Water | L134: ='UTL COST'!$B$6 -> #REF! | M134: ='UTL COST'!$C$6 -> 525 | N134: 0.1
B135: TOTAL | E135: =IF(SUM(E131:E134)=0,"",SUM(E131:E134)) -> #REF! | K135: TOTAL | N135: =IF(SUM(N131:N134)=0,"",SUM(N131:N134)) -> #REF!
B141: DISH NAME | C141: Lahme Baajin | K141: DISH NAME | L141: Halloumi Brown C
B143: EST. SALE PPRICE | C143: 115000 | K143: EST. SALE PPRICE | L143: 115000
B145: TOTAL COST | C145: =IF(SUM(E157,E172,E180)=0,"",SUM(E157,E172,E180)) -> #REF! | K145: TOTAL COST | L145: =IF(SUM(N157,N172,N180)=0,"",SUM(N157,N172,N180)) -> #REF!
B147: COST MARGIN | C147: =IF(C145="","",IF(ISBLANK(C143),"",C145/C143)) -> #REF! | K147: COST MARGIN | L147: =IF(L145="","",IF(ISBLANK(L143),"",L145/L143)) -> #REF!
B149: NET PROFIT | C149: =C143-C145 -> #REF! | K149: NET PROFIT | L149: =L143-L145 -> #REF!
B152: PRIMARY INGREDIENTS | K152: PRIMARY INGREDIENTS
...

Sheet LENT
A1: LENT FOOD COST
B6: DISH NAME | C6: Fried Platter | K6: DISH NAME | L6: Crab Sandwich
B8: EST. SALE PPRICE | C8: =E8*90000 -> 900000 | E8: 10 | K8: EST. SALE PPRICE | L8: =N8*90000 -> 900000 | N8: 10
B10: TOTAL COST | C10: =IF(SUM(E22,E37,E45)=0,"",SUM(E22,E37,E45)) -> #REF! | E10: =C10/90000 -> #REF! | K10: TOTAL COST | L10: =IF(SUM(N22,N37,N45)=0,"",SUM(N22,N37,N45)) -> #REF! | N10: =L10/90000 -> #REF!
B12: COST MARGIN | C12: =IF(C10="","",IF(ISBLANK(C8),"",C10/C8)) -> #REF! | K12: COST MARGIN | L12: =IF(L10="","",IF(ISBLANK(L8),"",L10/L8)) -> #REF!
B14: NET PROFIT | C14: =C8-C10 -> #REF! | K14: NET PROFIT | L14: =L8-L10 -> #REF!
B17: PRIMARY INGREDIENTS | K17: PRIMARY INGREDIENTS
B18: Product Name | C18: Qty. | D18: Cost (per unit) | E18: Total Cost | K18: Product Name | L18: Qty. | M18: Cost (per unit) | N18: Total Cost
B19: Eggplant | C19: 0.3 | D19: ='F&B'!F312 -> 16200 | E19: =IF(OR(ISBLANK(C19),ISBLANK(D19)),"",D19*C19) -> 4860 | K19: Crab Sticks | L19: 0.15 | M19: ='F&B'!$F$270 -> 15840 | N19: =IF(OR(ISBLANK(L19),ISBLANK(M19)),"",M19*L19) -> 2376
B20: Cauliflower | C20: 0.7 | D20: 100000 | E20: =IF(OR(ISBLANK(C20),ISBLANK(D20)),"",D20*C20) -> 70000 | K20: Ciabatta Brown | L20: 1 | M20: ='F&B'!F16/40 -> 11925 | N20: =IF(OR(ISBLANK(L20),ISBLANK(M20)),"",M20*L20) -> 11925
K21: Lemon Mustard Dressing | L21: 1 | M21: =SAUCES!L16 -> 629.96299 | N21: =IF(OR(ISBLANK(L21),ISBLANK(M21)),"",M21*L21) -> 629.96299
B22: TOTAL | E22: =IF(SUM(E19:E21)=0,"",SUM(E19:E21)) -> 74860 | K22: TOTAL | N22: =IF(SUM(N19:N21)=0,"",SUM(N19:N21)) -> 14930.963
B24: SECONDARY INGREDIENTS | K24: SECONDARY INGREDIENTS
B25: Product Name | C25: Qty | D25: Cost | E25: Total Cost | K25: Product Name | L25: Qty | M25: Cost | N25: Total Cost
B27: Hinidbi | C27: 0.75 | D27: 120000 | E27: =D27*C27 -> 90000 | K27: Iceberg | L27: 0.03 | M27: ='F&B'!$F$277 -> 13500 | N27: =M27*L27 -> 405
K28: Sweet Corn | L28: 0.04 | M28: ='F&B'!$F$60*3 -> 29700 | N28: =M28*L28 -> 1188
E29: =D29*C29 -> 0 | K29: Coleslaw | L29: 1 | N29: =M29*L29 -> 0
E30: =D30*C30 -> 0 | K30: Garnish | L30: 1 | N30: =M30*L30 -> 0
E31: =D31*C31 -> 0 | K31: Avocado | L31: 0.03 | M31: ='F&B'!$F$288 -> 54000 | N31: =M31*L31 -> 1620
E32: =D32*C32 -> 0 | K32: French Fries Side | L32: 0.2 | M32: ='F&B'!$F$68/10 -> 19665 | N32: =M32*L32 -> 3933
E33: =D33*C33 -> 0 | N33: =M33*L33 -> 0
E34: =D34*C34 -> 0 | N34: =M34*L34 -> 0
E35: =D35*C35 -> 0 | N35: =M35*L35 -> 0
E36: =D36*C36 -> 0 | N36: =M36*L36 -> 0
B37: TOTAL | E37: =IF(SUM(E27:E36)=0,"",SUM(E27:E36)) -> 90000 | K37: TOTAL | N37: =IF(SUM(N27:N36)=0,"",SUM(N27:N36)) -> 7146
B39: UTILITY AND PREP. COST | K39: UTILITY AND PREP. COST
B40: Name | E40: Total Cost | K40: Name | N40: Total Cost
B41: Shorenting Oil | C41: ='UTL COST'!$B$3 -> 369000 | D41: ='UTL COST'!$C$3 -> 0.0075 | E41: ='UTL COST'!$D$3 -> 2767.5 | K41: Shorenting Oil | L41: ='UTL COST'!$B$3 -> 369000 | M41: ='UTL COST'!$C$3 -> 0.0075 | N41: ='UTL COST'!$D$3 -> 2767.5
B42: Gas | C42: ='UTL COST'!$B$4 -> #REF! | D42: ='UTL COST'!$C$4 -> 7000 | E42: ='UTL COST'!$D$4 -> #REF! | K42: Gas | L42: ='UTL COST'!$B$4 -> #REF! | M42: ='UTL COST'!$C$4 -> 7000 | N42: ='UTL COST'!$D$4 -> #REF!
B43: Electricity | C43: ='UTL COST'!$B$5 -> #REF! | D43: ='UTL COST'!$C$5 -> 45000 | E43: ='UTL COST'!$D$5 -> #REF! | K43: Electricity | L43: ='UTL COST'!$B$5 -> #REF! | M43: ='UTL COST'!$C$5 -> 45000 | N43: ='UTL COST'!$D$5 -> #REF!
B44: Water | C44: ='UTL COST'!$B$6 -> #REF! | D44: ='UTL COST'!$C$6 -> 525 | E44: 0.1 | K44: Water | L44: ='UTL COST'!$B$6 -> #REF! | M44: ='UTL COST'!$C$6 -> 525 | N44: 0.1
B45: TOTAL | E45: =IF(SUM(E41:E44)=0,"",SUM(E41:E44)) -> #REF! | K45: TOTAL | N45: =IF(SUM(N41:N44)=0,"",SUM(N41:N44)) -> #REF!
B50: DISH NAME | C50: Hindbi | K50: DISH NAME | L50: Batata Harra
B52: EST. SALE PPRICE | C52: =E52*90000 -> 540000 | E52: 6 | K52: EST. SALE PPRICE | L52: 125000
B54: TOTAL COST | C54: =IF(SUM(E66,E81,E89)=0,"",SUM(E66,E81,E89)) -> #REF! | E54: =C54/90000 -> #REF! | K54: TOTAL COST | L54: =IF(SUM(N66,N81,N89)=0,"",SUM(N66,N81,N89)) -> #REF!
B56: COST MARGIN | C56: =IF(C54="","",IF(ISBLANK(C52),"",C54/C52)) -> #REF! | K56: COST MARGIN | L56: =IF(L54="","",IF(ISBLANK(L52),"",L54/L52)) -> #REF!
B58: NET PROFIT | C58: =C52-C54 -> #REF! | K58: NET PROFIT | L58: =L52-L54 -> #REF!
B61: PRIMARY INGREDIENTS | K61: PRIMARY INGREDIENTS
B62: Product Name | C62: Qty. | D62: Cost (per unit) | E62: Total Cost | K62: Product Name | L62: Qty. | M62: Cost (per unit) | N62: Total Cost
B63: Hindbi | C63: 0.75 | D63: =1.4*90000 -> 126000 | E63: =IF(OR(ISBLANK(C63),ISBLANK(D63)),"",D63*C63) -> 94500 | K63: Potato | L63: 0.1 | M63: ='F&B'!$F$281 -> 5400 | N63: =IF(OR(ISBLANK(L63),ISBLANK(M63)),"",M63*L63) -> 540
B64: Onions | C64: 0.2 | D64: ='F&B'!F290 -> 6300 | E64: =IF(OR(ISBLANK(C64),ISBLANK(D64)),"",D64*C64) -> 1260 | N64: =IF(OR(ISBLANK(L64),ISBLANK(M64)),"",M64*L64)
B65: Lemon | C65: =L73 -> 0.02 | D65: =M73 -> 8100 | E65: =N73 -> 162 | N65: =IF(OR(ISBLANK(L65),ISBLANK(M65)),"",M65*L65)
B66: TOTAL | E66: =IF(SUM(E63:E65)=0,"",SUM(E63:E65)) -> 95922 | K66: TOTAL | N66: =IF(SUM(N63:N65)=0,"",SUM(N63:N65)) -> 540
B68: SECONDARY INGREDIENTS | K68: SECONDARY INGREDIENTS
B69: Product Name | C69: Qty | D69: Cost | E69: Total Cost | K69: Product Name | L69: Qty | M69: Cost | N69: Total Cost
B71: Sunflower Oil | C71: 0.04 | D71: =M71 -> 18562.5 | E71: =D71*C71 -> 742.5 | K71: Sunflower Oil | L71: 0.11 | M71: ='F&B'!F57/8 -> 18562.5 | N71: =M71*L71 -> 2041.875
E72: =D72*C72 -> 0 | K72: Coriander | L72: 0.25 | M72: ='F&B'!F311 -> 2970 | N72: =M72*L72 -> 742.5
E73: =D73*C73 -> 0 | K73: Lemon Juice | L73: 0.02 | M73: ='F&B'!F287 -> 8100 | N73: =M73*L73 -> 162
E74: =D74*C74 -> 0 | N74: =M74*L74 -> 0
E75: =D75*C75 -> 0 | N75: =M75*L75 -> 0
E76: =D76*C76 -> 0 | N76: =M76*L76 -> 0
E77: =D77*C77 -> 0 | N77: =M77*L77 -> 0
E78: =D78*C78 -> 0 | N78: =M78*L78 -> 0
E79: =D79*C79 -> 0 | N79: =M79*L79 -> 0
E80: =D80*C80 -> 0 | N80: =M80*L80 -> 0
B81: TOTAL | E81: =IF(SUM(E71:E80)=0,"",SUM(E71:E80)) -> 742.5 | K81: TOTAL | N81: =IF(SUM(N71:N80)=0,"",SUM(N71:N80)) -> 2946.375
B83: UTILITY AND PREP. COST | K83: UTILITY AND PREP. COST
B84: Name | E84: Total Cost | K84: Name | N84: Total Cost
B85: Shorenting Oil | C85: ='UTL COST'!$B$3 -> 369000 | D85: ='UTL COST'!$C$3 -> 0.0075 | E85: ='UTL COST'!$D$3 -> 2767.5 | K85: Shorenting Oil | L85: ='UTL COST'!$B$3 -> 369000 | M85: ='UTL COST'!$C$3 -> 0.0075 | N85: ='UTL COST'!$D$3 -> 2767.5
B86: Gas | C86: ='UTL COST'!$B$4 -> #REF! | D86: ='UTL COST'!$C$4 -> 7000 | E86: ='UTL COST'!$D$4 -> #REF! | K86: Gas | L86: ='UTL COST'!$B$4 -> #REF! | M86: ='UTL COST'!$C$4 -> 7000 | N86: ='UTL COST'!$D$4 -> #REF!
B87: Electricity | C87: ='UTL COST'!$B$5 -> #REF! | D87: ='UTL COST'!$C$5 -> 45000 | E87: ='UTL COST'!$D$5 -> #REF! | K87: Electricity | L87: ='UTL COST'!$B$5 -> #REF! | M87: ='UTL COST'!$C$5 -> 45000 | N87: ='UTL COST'!$D$5 -> #REF!
B88: Water | C88: ='UTL COST'!$B$6 -> #REF! | D88: ='UTL COST'!$C$6 -> 525 | E88: 0.1 | K88: Water | L88: ='UTL COST'!$B$6 -> #REF! | M88: ='UTL COST'!$C$6 -> 525 | N88: 0.1
B89: TOTAL | E89: =IF(SUM(E85:E88)=0,"",SUM(E85:E88)) -> #REF! | K89: TOTAL | N89: =IF(SUM(N85:N88)=0,"",SUM(N85:N88)) -> #REF!
B98: DISH NAME | C98: Tuna Sand | K98: DISH NAME | L98: Fish Burger
B100: EST. SALE PPRICE | C100: =E100*90000 -> 990000 | E100: 11 | K100: EST. SALE PPRICE | L100: =N100*90000 -> 1080000 | N100: 12
B102: TOTAL COST | C102: =IF(SUM(E114,E129,E137)=0,"",SUM(E114,E129,E137)) -> #REF! | E102: =C102/90000 -> #REF! | K102: TOTAL COST | L102: =IF(SUM(N114,N129,N137)=0,"",SUM(N114,N129,N137)) -> #REF! | N102: =L102/90000 -> #REF!
B104: COST MARGIN | C104: =IF(C102="","",IF(ISBLANK(C100),"",C102/C100)) -> #REF! | K104: COST MARGIN | L104: =IF(L102="","",IF(ISBLANK(L100),"",L102/L100)) -> #REF!
B106: NET PROFIT | C106: =C100-C102 -> #REF! | K106: NET PROFIT | L106: =L100-L102 -> #REF!
B109: PRIMARY INGREDIENTS | K109: PRIMARY INGREDIENTS
B110: Product Name | C110: Qty. | D110: Cost (per unit) | E110: Total Cost | K110: Product Name | L110: Qty. | M110: Cost (per unit) | N110: Total Cost
B111: Tuna | C111: 1 | D111: ='F&B'!E65*90000 -> 99000 | E111: =IF(OR(ISBLANK(C111),ISBLANK(D111)),"",D111*C111) -> 99000 | K111: Fish Filet | L111: 0.2 | M111: =D156 -> 53910 | N111: =IF(OR(ISBLANK(L111),ISBLANK(M111)),"",M111*L111) -> 10782
B112: Ciabatta Brown | C112: 1 | D112: =M20 -> 11925 | E112: =IF(OR(ISBLANK(C112),ISBLANK(D112)),"",D112*C112) -> 11925 | K112: Burger Bun Brown | L112: 1 | M112: ='F&B'!F13/6 -> 5550 | N112: =IF(OR(ISBLANK(L112),ISBLANK(M112)),"",M112*L112) -> 5550
B113: Lemon Mustard Dressing | C113: 1 | D113: =M21 -> 629.96299 | E113: =IF(OR(ISBLANK(C113),ISBLANK(D113)),"",D113*C113) -> 629.96299 | K113: Breading | L113: 1 | M113: =D158 -> 629.96299 | N113: =IF(OR(ISBLANK(L113),ISBLANK(M113)),"",M113*L113) -> 629.96299
B114: TOTAL | E114: =IF(SUM(E111:E113)=0,"",SUM(E111:E113)) -> 111554.96 | K114: TOTAL | N114: =IF(SUM(N111:N113)=0,"",SUM(N111:N113)) -> 16961.963
B116: SECONDARY INGREDIENTS | K116: SECONDARY INGREDIENTS
B117: Product Name | C117: Qty | D117: Cost | E117: Total Cost | K117: Product Name | L117: Qty | M117: Cost | N117: Total Cost
B119: Iceberg | C119: 0.03 | D119: ='F&B'!$F$277 -> 13500 | E119: =D119*C119 -> 405
B120: Sweet Corn | C120: 0.04 | D120: ='F&B'!$F$60*3 -> 29700 | E120: =D120*C120 -> 1188 | K120: Iceberg | L120: 0.09 | M120: ='F&B'!F277 -> 13500 | N120: =M120*L120 -> 1215
B121: Coleslaw | C121: 1 | E121: =D121*C121 -> 0 | K121: Green Salad | L121: 1 | M121: =SAUCES!$D$68 -> 3768.1048 | N121: =M121*L121 -> 3768.1048
B122: Garnish | C122: 1 | E122: =D122*C122 -> 0 | K122: French Fries Side | L122: 0.16 | M122: ='F&B'!$F$68/10 -> 19665 | N122: =M122*L122 -> 3146.4
B123: Pickles | C123: 0.015 | D123: 81000 | E123: 1215 | K123: Tartar Sauce | L123: 1 | M123: =D164 -> 1364.1381 | N123: =M123*L123 -> 1364.1381
B124: French Fries Side | C124: 0.2 | D124: ='F&B'!$F$68/10 -> 19665 | E124: =D124*C124 -> 3933 | N124: =M124*L124 -> 0
E125: =D125*C125 -> 0 | N125: =M125*L125 -> 0
E126: =D126*C126 -> 0 | N126: =M126*L126 -> 0
E127: =D127*C127 -> 0 | N127: =M127*L127 -> 0
E128: =D128*C128 -> 0 | N128: =M128*L128 -> 0
B129: TOTAL | E129: =IF(SUM(E119:E128)=0,"",SUM(E119:E128)) -> 6741 | K129: TOTAL | N129: =IF(SUM(N119:N128)=0,"",SUM(N119:N128)) -> 9493.6428
B131: UTILITY AND PREP. COST | K131: UTILITY AND PREP. COST
B132: Name | E132: Total Cost | K132: Name | N132: Total Cost
B133: Shorenting Oil | C133: ='UTL COST'!$B$3 -> 369000 | D133: ='UTL COST'!$C$3 -> 0.0075 | E133: ='UTL COST'!$D$3 -> 2767.5 | K133: Shorenting Oil | L133: ='UTL COST'!$B$3 -> 369000 | M133: ='UTL COST'!$C$3 -> 0.0075 | N133: ='UTL COST'!$D$3 -> 2767.5
B134: Gas | C134: ='UTL COST'!$B$4 -> #REF! | D134: ='UTL COST'!$C$4 -> 7000 | E134: ='UTL COST'!$D$4 -> #REF! | K134: Gas | L134: ='UTL COST'!$B$4 -> #REF! | M134: ='UTL COST'!$C$4 -> 7000 | N134: ='UTL COST'!$D$4 -> #REF!
B135: Electricity | C135: ='UTL COST'!$B$5 -> #REF! | D135: ='UTL COST'!$C$5 -> 45000 | E135: ='UTL COST'!$D$5 -> #REF! | K135: Electricity | L135: ='UTL COST'!$B$5 -> #REF! | M135: ='UTL COST'!$C$5 -> 45000 | N135: ='UTL COST'!$D$5 -> #REF!
B136: Water | C136: ='UTL COST'!$B$6 -> #REF! | D136: ='UTL COST'!$C$6 -> 525 | E136: 0.1 | K136: Water | L136: ='UTL COST'!$B$6 -> #REF! | M136: ='UTL COST'!$C$6 -> 525 | N136: 0.1
B137: TOTAL | E137: =IF(SUM(E133:E136)=0,"",SUM(E133:E136)) -> #REF! | K137: TOTAL | N137: =IF(SUM(N133:N136)=0,"",SUM(N133:N136)) -> #REF!
B143: DISH NAME | C143: Fish and Chips | K143: DISH NAME | L143: Cauliflower Burger
B145: EST. SALE PPRICE | C145: =E145*90000 -> 1170000 | E145: 13 | K145: EST. SALE PPRICE | L145: 850000
B147: TOTAL COST | C147: =IF(SUM(E159,E174,E182)=0,"",SUM(E159,E174,E182)) -> #REF! | E147: =C147/90000 -> #REF! | K147: TOTAL COST | L147: =IF(SUM(N159,N174,N182)=0,"",SUM(N159,N174,N182)) -> #REF!
B149: COST MARGIN | C149: =IF(C147="","",IF(ISBLANK(C145),"",C147/C145)) -> #REF! | K149: COST MARGIN | L149: =IF(L147="","",IF(ISBLANK(L145),"",L147/L145)) -> #REF!
B151: NET PROFIT | C151: =C145-C147 -> #REF! | K151: NET PROFIT | L151: =L145-L147 -> #REF!
B154: PRIMARY INGREDIENTS | K154: PRIMARY INGREDIENTS
...

Sheet SANDWICHES
A1: SANDWICHES FOOD COST
B6: DISH NAME | C6: Chicken Sub | K6: DISH NAME | L6: Light Chicken
B8: EST. SALE PPRICE | C8: 143000 | K8: EST. SALE PPRICE | L8: 170000
B10: TOTAL COST | C10: =IF(SUM(E22,E37,E45)=0,"",SUM(E22,E37,E45)) -> #REF! | E10: =C10/90000 -> #REF! | K10: TOTAL COST | L10: =IF(SUM(N22,N37,N45)=0,"",SUM(N22,N37,N45)) -> #REF! | N10: =L10/90000 -> #REF!
B12: COST MARGIN | C12: =IF(C10="","",IF(ISBLANK(C8),"",C10/C8)) -> #REF! | K12: COST MARGIN | L12: =IF(L10="","",IF(ISBLANK(L8),"",L10/L8)) -> #REF!
B14: NET PROFIT | C14: =C8-C10 -> #REF! | K14: NET PROFIT | L14: =L8-L10 -> #REF!
B17: PRIMARY INGREDIENTS | K17: PRIMARY INGREDIENTS
B18: Product Name | C18: Qty. | D18: Cost (per unit) | E18: Total Cost | K18: Product Name | L18: Qty. | M18: Cost (per unit) | N18: Total Cost
B19: Chicken Breast | C19: 0.16 | D19: ='F&B'!F229 -> 81000 | E19: =IF(OR(ISBLANK(C19),ISBLANK(D19)),"",D19*C19) -> 12960 | F19: =E19/$C$10 -> #REF! | K19: Chicken Breast | L19: 0.16 | M19: =D19 -> 81000 | N19: =IF(OR(ISBLANK(L19),ISBLANK(M19)),"",M19*L19) -> 12960 | O19: =N19/$L$10 -> #REF!
B20: Submarine Bread | C20: 1 | D20: ='F&B'!$F$27/5 -> 5940 | E20: =IF(OR(ISBLANK(C20),ISBLANK(D20)),"",D20*C20) -> 5940 | F20: =E20/$C$10 -> #REF! | K20: Brown Ciabatta | L20: 1 | M20: ='F&B'!$F$16/40 -> 11925 | N20: =IF(OR(ISBLANK(L20),ISBLANK(M20)),"",M20*L20) -> 11925 | O20: =N20/$L$10 -> #REF!
E21: =IF(OR(ISBLANK(C21),ISBLANK(D21)),"",D21*C21) | N21: =IF(OR(ISBLANK(L21),ISBLANK(M21)),"",M21*L21)
B22: TOTAL | E22: =IF(SUM(E19:E21)=0,"",SUM(E19:E21)) -> 18900 | K22: TOTAL | N22: =IF(SUM(N19:N21)=0,"",SUM(N19:N21)) -> 24885
B24: SECONDARY INGREDIENTS | K24: SECONDARY INGREDIENTS
B25: Product Name | C25: Qty | D25: Cost | E25: Total Cost | K25: Product Name | L25: Qty | M25: Cost | N25: Total Cost
B27: Mozzarella Cheese | C27: 0.06 | D27: ='F&B'!$F$99/12 -> 63000 | E27: =D27*C27 -> 3780 | F27: =E27/$C$10 -> #REF! | K27: Fresh Mushrooms | L27: 0.01 | M27: ='F&B'!$F$278 -> 103500 | N27: =M27*L27 -> 1035 | O27: =N27/$L$10 -> #REF!
